Workbook

Sheet Czytaj_mnie
A1: HCV w Polsce – model inwestycji w testowanie i leczenie (arkusz z formułami)
A2: Wszystkie wyniki są SZACUNKAMI MODELU, nie danymi. Stan danych: 28.10.2026 (wersja po audycie 2). Arkusze L_* i Inw_*: S0 (zaniechanie), I1, I2, I3, I4, I5, V1 wobec status quo (S1). ICER główny = perspektywa NFZ.
A3: Przełącznik Ustawienia!B5 (x_testy): 0 = wariant pełny (testy w porównaniu); 1 = testy finansuje inny płatnik – porównujemy tylko koszt wyleczenia (leki, monitorowanie, nawigacja) z kosztami nieleczenia. To przesunięcie kosztu testów do innego płatnika, nie jego zniknięcie z finansów publicznych.
A4: Arkusz Na_pacjenta: koszt wyleczenia vs koszt nieleczenia na jednego zdiagnozowanego pacjenta. Arkusz Analizy_scen: warianty założeń (K=1, cena 2017, malejąca zapadalność, opieka u wszystkich itd.). Arkusz Zmiany: lista zmian 28.10.2026.
A5: Żółte komórki = dane wejściowe (nazwy x_…). Zmiana parametru kosztowego przelicza koszty, salda, ROI i rok zwrotu.
A6: Liczebności stanów (arkusze L_*) pochodzą z silnika Markowa (JavaScript, ten sam co w aplikacji) i są wklejone jako wartości;
A7: zmiana parametrów przejść/epidemiologii wymaga ponownego uruchomienia silnika (kalkulator w aplikacji robi to na żywo).
A8: Perspektywy (AOTMiT): NFZ; sektor publiczny = NFZ + budżet (MZ/SW) + ZUS + KRUS + utracone składki i PIT; społeczna = NFZ + budżet + produktywność (ZUS to transfery).
A9: Dyskonto: koszty 5%, efekty 3,5% (AOTMiT). Saldo > 0 = koszt netto dla państwa; saldo < 0 = oszczędność netto.
A10: Liczby leczonych są roczne – nie sumuj osób między latami (suma kursów leczenia ≠ liczba unikalnych osób).
A11: Materiał edukacyjny, neutralny; bez nazw leków i firm. Recenzja panelu ról w aplikacji jest symulowana.
A12: Deklaracja finansowania i konfliktu interesów: Autor pracuje w sektorze farmaceutycznym. Analiza powstała prywatnie, bez zlecenia i finansowania jakiejkolwiek firmy. Nie wymienia ani nie promuje żadnych produktów leczniczych. Część wykorzystanych źródeł była finansowana przez przemysł — oznaczono to w Źródłach.

Sheet Parametry
A1: id | B1: nazwa | C1: wartosc | D1: min | E1: max | F1: rozklad | G1: param_rozkladu | H1: zrodlo | I1: data_zrodla | J1: typ | K1: metoda | L1: platnik | M1: jednostka
A2: N0 | B2: Osoby z wiremią HCV w PL na start (2026) | C2: 155000 | D2: 145000 | E2: 165000 | F2: trójkątny | G2: min=145000; moda=155000; max=165000 | H2: Szacunki ekspertów i Polaris Observatory (przegląd w raporcie HCV); Flisiak i in. Eur J Gastroenterol Hepatol 2015;27:70–76 | I2: 2020–2024 | J2: dane źródłowe | K2: punkt środkowy przedziału publikowanych szacunków | L2: — | M2: osoby
A3: AGE0 | B3: Wiek startowy kohorty | C3: 53.33 | D3: 47.33 | E3: 59.33 | F3: normalny | G3: sd=3 | H3: NFZ app-stat B.71 2025 wg grup wieku (n=4 839) | I3: 2025 | J3: prognoza/szacunek | K3: średnia ważona środków grup wieku B.71 2025 (18–40 z 7–17: 29; 41–60: 50,5; 61–80: 70,5; 81+: 85 – założenie); przesuwa cały rozkład wieku kohorty; SD 3 lata w PSA = założenie (niepewność, czy leczeni odzwierciedlają niewykrytych) | L3: — | M3: lata
A4: RET | B4: Wiek emerytalny ważony płcią | C4: 63 | D4: 60 | E4: 65 | F4: stały (tornado) | G4: — | H4: NFZ B.71 2025 wg płci (M 55,5%); ustawa o emeryturach (60/65) | I4: 2025 | J4: prognoza/szacunek | K4: średnia ważona udziałem płci | L4: — | M4: lata
A5: D_F0 | B5: Rozkład włóknienia na starcie F0 | C5: 0.213 | F5: Dirichlet | G5: alfa=180 (n=845) | H5: Pierucka 2016 (nowo rozpoznani, n=845) | I5: 2016 | J5: dane źródłowe | K5: udział obserwowany | L5: — | M5: odsetek
A6: D_F1 | B6: Rozkład włóknienia na starcie F1 | C6: 0.361 | F6: Dirichlet | G6: alfa=305 (n=845) | H6: Pierucka 2016 (nowo rozpoznani, n=845) | I6: 2016 | J6: dane źródłowe | K6: udział obserwowany | L6: — | M6: odsetek
A7: D_F2 | B7: Rozkład włóknienia na starcie F2 | C7: 0.233 | F7: Dirichlet | G7: alfa=197 (n=845) | H7: Pierucka 2016 (nowo rozpoznani, n=845) | I7: 2016 | J7: dane źródłowe | K7: udział obserwowany | L7: — | M7: odsetek
A8: D_F3 | B8: Rozkład włóknienia na starcie F3 | C8: 0.11 | F8: Dirichlet | G8: alfa=93 (n=845) | H8: Pierucka 2016 (nowo rozpoznani, n=845) | I8: 2016 | J8: dane źródłowe | K8: udział obserwowany | L8: — | M8: odsetek
A9: D_F4 | B9: Rozkład włóknienia na starcie F4 | C9: 0.083 | F9: Dirichlet | G9: alfa=70 (n=845) | H9: Pierucka 2016 (nowo rozpoznani, n=845) | I9: 2016 | J9: dane źródłowe | K9: udział obserwowany | L9: — | M9: odsetek
A10: p_F0F1 | B10: Prawdopodobieństwo roczne F0→F1 | C10: 0.117 | D10: 0.104 | E10: 0.13 | F10: beta | G10: alfa=274.65; beta=2072.75 | H10: Thein 2008 Hepatology 48:418 (metaanaliza), doi 10.1002/hep.22375 | I10: 2008 | J10: dane zagraniczne/literatura międzynarodowa | K10: metaanaliza; SE=(górny−dolny 95% CI)/3,92 | L10: — | M10: /rok
A11: p_F1F2 | B11: Prawdopodobieństwo roczne F1→F2 | C11: 0.085 | D11: 0.075 | E11: 0.096 | F11: beta | G11: alfa=230.27; beta=2478.76 | H11: Thein 2008 Hepatology 48:418 (metaanaliza), doi 10.1002/hep.22375 | I11: 2008 | J11: dane zagraniczne/literatura międzynarodowa | K11: metaanaliza; SE=(górny−dolny 95% CI)/3,92 | L11: — | M11: /rok
A12: p_F2F3 | B12: Prawdopodobieństwo roczne F2→F3 | C12: 0.12 | D12: 0.109 | E12: 0.133 | F12: beta | G12: alfa=337.94; beta=2478.23 | H12: Thein 2008 Hepatology 48:418 (metaanaliza), doi 10.1002/hep.22375 | I12: 2008 | J12: dane zagraniczne/literatura międzynarodowa | K12: metaanaliza; SE=(górny−dolny 95% CI)/3,92 | L12: — | M12: /rok
A13: p_F3F4 | B13: Prawdopodobieństwo roczne F3→F4 | C13: 0.116 | D13: 0.104 | E13: 0.129 | F13: beta | G13: alfa=292.34; beta=2227.83 | H13: Thein 2008 Hepatology 48:418 (metaanaliza), doi 10.1002/hep.22375 | I13: 2008 | J13: dane zagraniczne/literatura międzynarodowa | K13: metaanaliza; SE=(górny−dolny 95% CI)/3,92 | L13: — | M13: /rok
A14: p_CCDC | B14: Prawdopodobieństwo roczne CC→DC | C14: 0.0592 | D14: 0.0272 | E14: 0.08 | F14: beta | G14: alfa=186.85; beta=2969.48 | H14: Analiza ekonomiczna wnioskodawcy przygotowana przez firmę konsultingową, opublikowana w BIP AOTMiT (zlecenie 153/2017): wartości Tab. 28, błędy standardowe do PSA Tab. 198 – parametry z literatury międzynarodowej (źródło przygotowane na zlecenie wnioskodawcy – możliwa stronniczość sponsora) | I14: 2017 | J14: dane źródłowe (PL HTA; pierwotnie lit. międzynar.) | K14: — | L14: — | M14: /rok
A15: p_CCHCC | B15: Prawdopodobieństwo roczne CC→HCC | C15: 0.0367 | D15: 0.02 | E15: 0.048 | F15: beta | G15: alfa=112.20; beta=2945.03 | H15: Analiza ekonomiczna wnioskodawcy przygotowana przez firmę konsultingową, opublikowana w BIP AOTMiT (zlecenie 153/2017): wartości Tab. 28, błędy standardowe do PSA Tab. 198 – parametry z literatury międzynarodowej (źródło przygotowane na zlecenie wnioskodawcy – możliwa stronniczość sponsora) | I15: 2017 | J15: dane źródłowe (PL HTA; pierwotnie lit. międzynar.) | K15: — | L15: — | M15: /rok
A16: p_DCHCC | B16: Prawdopodobieństwo roczne DC→HCC | C16: 0.0215 | D16: 0.0131 | E16: 0.0681 | F16: beta | G16: alfa=28.25; beta=1285.61 | H16: Analiza ekonomiczna wnioskodawcy przygotowana przez firmę konsultingową, opublikowana w BIP AOTMiT (zlecenie 153/2017): wartości Tab. 28, błędy standardowe do PSA Tab. 198 – parametry z literatury międzynarodowej (źródło przygotowane na zlecenie wnioskodawcy – możliwa stronniczość sponsora) | I16: 2017 | J16: dane źródłowe (PL HTA; pierwotnie lit. międzynar.) | K16: — | L16: — | M16: /rok
A17: p_DCLT | B17: Prawdopodobieństwo roczne DC→LT | C17: 0.0418 | D17: 0.0376 | E17: 0.046 | F17: beta | G17: alfa=3.02; beta=69.13 | H17: Analiza ekonomiczna wnioskodawcy przygotowana przez firmę konsultingową, opublikowana w BIP AOTMiT (zlecenie 153/2017): wartości Tab. 28, błędy standardowe do PSA Tab. 198 – parametry z literatury międzynarodowej (źródło przygotowane na zlecenie wnioskodawcy – możliwa stronniczość sponsora) | I17: 2017 | J17: dane źródłowe (PL HTA; pierwotnie lit. międzynar.) | K17: — | L17: — | M17: /rok
A18: p_DCD | B18: Prawdopodobieństwo roczne DC→zgon wątrobowy | C18: 0.1081 | D18: 0.0934 | E18: 0.1228 | F18: beta | G18: alfa=185.18; beta=1527.85 | H18: Analiza ekonomiczna wnioskodawcy przygotowana przez firmę konsultingową, opublikowana w BIP AOTMiT (zlecenie 153/2017): wartości Tab. 28, błędy standardowe do PSA Tab. 198 – parametry z literatury międzynarodowej (źródło przygotowane na zlecenie wnioskodawcy – możliwa stronniczość sponsora) | I18: 2017 | J18: dane źródłowe (PL HTA; pierwotnie lit. międzynar.) | K18: — | L18: — | M18: /rok
A19: p_HCCD | B19: Prawdopodobieństwo roczne HCC→zgon wątrobowy | C19: 0.2715 | D19: 0.257 | E19: 0.286 | F19: beta | G19: alfa=980.36; beta=2630.54 | H19: Analiza ekonomiczna wnioskodawcy przygotowana przez firmę konsultingową, opublikowana w BIP AOTMiT (zlecenie 153/2017): wartości Tab. 28, błędy standardowe do PSA Tab. 198 – parametry z literatury międzynarodowej (źródło przygotowane na zlecenie wnioskodawcy – możliwa stronniczość sponsora) | I19: 2017 | J19: dane źródłowe (PL HTA; pierwotnie lit. międzynar.) | K19: — | L19: — | M19: /rok
A20: p_HCCLT | B20: Prawdopodobieństwo roczne HCC→LT | C20: 0.0093 | D20: 0.0084 | E20: 0.0103 | F20: beta | G20: alfa=342.73; beta=36510.31 | H20: Analiza ekonomiczna wnioskodawcy przygotowana przez firmę konsultingową, opublikowana w BIP AOTMiT (zlecenie 153/2017): wartości Tab. 28, błędy standardowe do PSA Tab. 198 – parametry z literatury międzynarodowej (źródło przygotowane na zlecenie wnioskodawcy – możliwa stronniczość sponsora) | I20: 2017 | J20: dane źródłowe (PL HTA; pierwotnie lit. międzynar.) | K20: — | L20: — | M20: /rok
A21: p_LTD | B21: Prawdopodobieństwo roczne LT (rok 1)→zgon | C21: 0.18 | D21: 0.175 | E21: 0.185 | F21: beta | G21: alfa=4250.70; beta=19364.30 | H21: Analiza ekonomiczna wnioskodawcy przygotowana przez firmę konsultingową, opublikowana w BIP AOTMiT (zlecenie 153/2017): wartości Tab. 28, błędy standardowe do PSA Tab. 198 – parametry z literatury międzynarodowej (źródło przygotowane na zlecenie wnioskodawcy – możliwa stronniczość sponsora) | I21: 2017 | J21: dane źródłowe (PL HTA; pierwotnie lit. międzynar.) | K21: — | L21: — | M21: /rok
... A32: u_SVR | B32: Przyrost użyteczności po SVR | C32: 0.055 | D32: 0.044 | E32: 0.066 | F32: gamma | G32: k=100.00; theta=0.0005 | H32: Analiza ekonomiczna wnioskodawcy przygotowana przez firmę konsultingową, opublikowana w BIP AOTMiT (zlecenie 153/2017): wartości Tab. 28, błędy standardowe do PSA Tab. 198 – parametry z literatury międzynarodowej (źródło przygotowane na zlecenie wnioskodawcy – możliwa stronniczość sponsora) | I32: 2017 | J32: dane źródłowe | K32: — | L32: — | M32: QALY/rok
A33: CPI | B33: Indeks CPI GUS 2016→2025 | C33: 1.5758813 | F33: stały | G33: — | H33: GUS: wskaźniki cen towarów i usług konsumpcyjnych 1950–2025 (rok poprzedni=100) | I33: 2026 | J33: prognoza/szacunek | K33: inflacja kosztu: iloczyn rocznych CPI 2017–2025 (102,0;101,6;102,3;103,4;105,1;114,4;111,4;103,6;103,6) | L33: — | M33: indeks
A34: c_F | B34: Koszt NFZ/rok: F0–F3 bez leczenia (ceny 2025) | C34: 2960.2457 | D34: 2368.2 | E34: 3552.29 | F34: gamma | G34: k=61.47; theta=48.1607 | H34: Kaczor 2012 (koszty stanów, ceny 2016) via analiza ekonomiczna wnioskodawcy (firma konsultingowa) opublikowana w BIP AOTMiT, zlecenie 153/2017, Tab. 73/198 × CPI GUS | I34: 2016→2025 | J34: prognoza/szacunek | K34: wartość źródłowa 1878.47 zł (2016) × CPI 1.5759; SE źródłowe przeskalowane | L34: NFZ | M34: zł/os./rok
A35: c_SVRn | B35: Koszt NFZ/rok: F0–F3 po SVR (ceny 2025) | C35: 612.59233 | D35: 490.07 | E35: 735.11 | F35: gamma | G35: k=61.47; theta=9.9653 | H35: Kaczor 2012 (koszty stanów, ceny 2016) via analiza ekonomiczna wnioskodawcy (firma konsultingowa) opublikowana w BIP AOTMiT, zlecenie 153/2017, Tab. 73/198 × CPI GUS | I35: 2016→2025 | J35: prognoza/szacunek | K35: wartość źródłowa 388.73 zł (2016) × CPI 1.5759; SE źródłowe przeskalowane | L35: NFZ | M35: zł/os./rok
A36: c_CC | B36: Koszt NFZ/rok: CC (ceny 2025) | C36: 5415.4687 | D36: 4332.37 | E36: 6498.56 | F36: gamma | G36: k=100.00; theta=54.1556 | H36: Kaczor 2012 (koszty stanów, ceny 2016) via analiza ekonomiczna wnioskodawcy (firma konsultingowa) opublikowana w BIP AOTMiT, zlecenie 153/2017, Tab. 73/198 × CPI GUS | I36: 2016→2025 | J36: prognoza/szacunek | K36: wartość źródłowa 3436.47 zł (2016) × CPI 1.5759; SE źródłowe przeskalowane | L36: NFZ | M36: zł/os./rok
A37: c_SVRcc | B37: Koszt NFZ/rok: CC po SVR (ceny 2025) | C37: 2738.0622 | D37: 2190.45 | E37: 3285.67 | F37: gamma | G37: k=100.00; theta=27.3813 | H37: Kaczor 2012 (koszty stanów, ceny 2016) via analiza ekonomiczna wnioskodawcy (firma konsultingowa) opublikowana w BIP AOTMiT, zlecenie 153/2017, Tab. 73/198 × CPI GUS | I37: 2016→2025 | J37: prognoza/szacunek | K37: wartość źródłowa 1737.48 zł (2016) × CPI 1.5759; SE źródłowe przeskalowane | L37: NFZ | M37: zł/os./rok
A38: c_DC | B38: Koszt NFZ/rok: DC (ceny 2025) | C38: 18064.831 | D38: 14451.87 | E38: 21677.8 | F38: gamma | G38: k=100.00; theta=180.6477 | H38: Kaczor 2012 (koszty stanów, ceny 2016) via analiza ekonomiczna wnioskodawcy (firma konsultingowa) opublikowana w BIP AOTMiT, zlecenie 153/2017, Tab. 73/198 × CPI GUS | I38: 2016→2025 | J38: prognoza/szacunek | K38: wartość źródłowa 11463.32 zł (2016) × CPI 1.5759; SE źródłowe przeskalowane | L38: NFZ | M38: zł/os./rok
A39: c_HCC | B39: Koszt NFZ/rok: HCC (ceny 2025) | C39: 62879.885 | D39: 50303.91 | E39: 75455.86 | F39: gamma | G39: k=100.00; theta=628.7985 | H39: Kaczor 2012 (koszty stanów, ceny 2016) via analiza ekonomiczna wnioskodawcy (firma konsultingowa) opublikowana w BIP AOTMiT, zlecenie 153/2017, Tab. 73/198 × CPI GUS | I39: 2016→2025 | J39: prognoza/szacunek | K39: wartość źródłowa 39901.41 zł (2016) × CPI 1.5759; SE źródłowe przeskalowane | L39: NFZ | M39: zł/os./rok
A40: c_LT | B40: Koszt NFZ/rok: LT (rok przeszczepienia) (ceny 2025) | C40: 342818.35 | D40: 274254.68 | E40: 411382.02 | F40: gamma | G40: k=100.00; theta=3428.1828 | H40: Kaczor 2012 (koszty stanów, ceny 2016) via analiza ekonomiczna wnioskodawcy (firma konsultingowa) opublikowana w BIP AOTMiT, zlecenie 153/2017, Tab. 73/198 × CPI GUS | I40: 2016→2025 | J40: prognoza/szacunek | K40: wartość źródłowa 217540.72 zł (2016) × CPI 1.5759; SE źródłowe przeskalowane | L40: NFZ | M40: zł/os./rok
A41: c_PLT | B41: Koszt NFZ/rok: po LT (rok 2+) (ceny 2025) | C41: 31787.81 | D41: 25430.25 | E41: 38145.37 | F41: gamma | G41: k=100.00; theta=317.8797 | H41: Kaczor 2012 (koszty stanów, ceny 2016) via analiza ekonomiczna wnioskodawcy (firma konsultingowa) opublikowana w BIP AOTMiT, zlecenie 153/2017, Tab. 73/198 × CPI GUS | I41: 2016→2025 | J41: prognoza/szacunek | K41: wartość źródłowa 20171.45 zł (2016) × CPI 1.5759; SE źródłowe przeskalowane | L41: NFZ | M41: zł/os./rok
A42: c_DAA | B42: Koszt DAA na pacjenta (refundacja B.71) | C42: 22760 | D42: 17366 | E42: 29829 | F42: lognormalny | G42: mu=ln(22760); sigma=0.138 (SD logarytmu ilorazu 2017–2025, n=9) | H42: NFZ app-stat B.71: 109,98 mln zł / 4 832 pacjentów (2025); szereg 2017–2025 (33 872 zł w 2017 → 22 760 zł w 2025) | I42: 2017–2025 | J42: dane źródłowe | K42: iloraz wartość/pacjenci; zmienność = SD logarytmu ilorazu 2017–2025; min/max = 95% rozkładu (17,4–29,8 tys. zł); scenariusze: 33 872 zł (2017) i najwyższa cena urzędowa terapii 8 tyg. w wykazie MZ 2025 (97 716 zł) – tylko w analizie scenariuszowej | L42: NFZ | M42: zł/pacjent
A43: c_MON | B43: Ryczałt diagnostyczny/monitorowanie B.71 (ceny 2025) | C43: 5765.1299 | D43: 3731.52 | E43: 6918.16 | F43: gamma | G43: SE 10% | H43: Zarządzenie 53/2017/DGL (5.08.08.0000002) 3 731,52 zł × CPI 2017→2025 | I43: 2017→2025 | J43: prognoza/szacunek | K43: inflacja kosztu CPI GUS 2018–2025 | L43: NFZ | M43: zł/pacjent
A44: c_AHCV | B44: Badanie anty-HCV (POZ) | C44: 46.2 | D44: 40 | E44: 57 | F44: stały | G44: — | H44: Zarządzenie Prezesa NFZ 22/2025/DSOZ (tekst ujedn. 23.09.2026) via psoz.pl | I44: 2026 | J44: dane źródłowe | K44: — | L44: NFZ | M44: zł/test
A45: c_RNA | B45: Badanie HCV RNA jakościowe | C45: 180 | D45: 150 | E45: 235 | F45: stały | G45: — | H45: Cennik laboratorium komercyjnego od 01.02.2025 (brak taryfy NFZ dla POZ – proxy rynkowe) | I45: 2025 | J45: dane źródłowe (proxy) | K45: cena rynkowa jako proxy | L45: NFZ | M45: zł/test
... A47: VIR | B47: Odsetek wiremicznych wśród anty-HCV+ | C47: 0.4 | D47: 0.35 | E47: 0.5 | F47: beta | G47: alfa=40; beta=60 | H47: Flisiak i in. (Clin Exp Hepatol 2020) | I47: 2020 | J47: dane źródłowe | K47: — | L47: — | M47: odsetek
A48: PREV_K | B48: Odsetek anty-HCV+ wśród PWID | C48: 0.312 | F48: stały | G48: — | H48: KCPU 2021 (31,2%); Rosińska i in. BMC Infect Dis 2015 (59%, dane 2004–05), doi 10.1186/s12879-015-0828-9 | I48: 2021/2004–05 | J48: dane źródłowe | K48: informacyjnie – wydajność kanału liczona z Y_KEY | L48: MZ/SW | M48: odsetek
A49: VIR_K | B49: Odsetek wiremicznych wśród anty-HCV+ PWID | C49: 0.5 | D49: 0.4 | E49: 0.7 | F49: beta | G49: alfa=50; beta=50 | H49: KBPN 'Serwis Informacyjny Uzależnienia' 79 (≥ połowa wiremiczna) | I49: 2017 | J49: dane źródłowe | K49: dolna granica 'co najmniej połowa' | L49: MZ/SW | M49: odsetek
A50: T_SQ | B50: Leczeni/rok – status quo | C50: 4832 | D50: 4407 | E50: 5200 | F50: stały | G50: — | H50: NFZ app-stat B.71 2025 | I50: 2025 | J50: dane źródłowe | K50: ostatnia obserwacja; wariant: trend liniowy 2020–2025 (n=6; +138/rok; R²=0,57) i log-liniowy (R²=0,55) | L50: NFZ | M50: osoby/rok
A51: T_WHO | B51: Leczeni/rok – eliminacja WHO 2030 | C51: 17500 | D51: 15000 | E51: 20000 | F51: stały | G51: — | H51: Flisiak i in. 2015 (scenariusz eliminacji: 15 000/rok); eksperci 2026 (ok. 20 000/rok) | I51: 2023 | J51: dane źródłowe | K51: środek przedziału | L51: NFZ | M51: osoby/rok
A52: ZUS12_B18 | B52: Wydatki ZUS 2012 B18 (renty+socjalne+rehab.+absencja) | C52: 49555600 | F52: stały | G52: — | H52: Łazarski/IZwOZ 2015, Tab. 57 (dane ZUS) | I52: 2012 | J52: dane źródłowe | K52: — | L52: ZUS | M52: zł
A53: ZUS12_K74 | B53: Wydatki ZUS 2012 K74 | C53: 55049600 | F53: stały | G53: — | H53: Łazarski/IZwOZ 2015, Tab. 57 | I53: 2012 | J53: dane źródłowe | K53: — | L53: ZUS | M53: zł
A54: ZUS12_C22 | B54: Wydatki ZUS 2012 C22 | C54: 6026300 | F54: stały | G54: — | H54: Łazarski/IZwOZ 2015, Tab. 57 | I54: 2012 | J54: dane źródłowe | K54: — | L54: ZUS | M54: zł
A55: DAYS_RATIO_B18 | B55: Wolumen absencji B18 2025/2013 | C55: 0.13862154 | F55: stały | G55: — | H55: ZUS PSZ 2025 (28 057 dni) / Łazarski 2013 (202,4 tys.) | I55: 2013/2025 | J55: dane źródłowe | K55: iloraz wolumenów | L55: ZUS | M55: ×
A56: W_RATIO | B56: Wzrost przeciętnego wynagrodzenia 2012→2025 | C56: 2.528221 | F56: stały | G56: — | H56: GUS: 3 521,67 zł (2012), 8 903,56 zł (2025, MP 2026 poz. 192) | I56: 2026 | J56: dane źródłowe | K56: iloraz | L56: — | M56: ×
A57: AF_B18 | B57: Udział HCV w B18 | C57: 0.50085251 | D57: 0.45 | E57: 0.55 | F57: beta | G57: alfa=3525; beta=3513 | H57: PZH: Choroby zakaźne i zatrucia w Polsce 2024 (B18.2 vs B18.0–1) | I57: 2024 | J57: prognoza/szacunek | K57: udział rejestracji jako proxy frakcji atrybutywnej | L57: ZUS | M57: odsetek
A58: AF_LIVER | B58: Udział HCV w raku wątroby (C22) | C58: 0.42 | D58: 0.33 | E58: 0.465 | F58: beta | G58: alfa=201; beta=277 (n=478) | H58: Rejestr LIVER (abstrakt JCO 2012, n=478, 2009–10 – wybrane ośrodki); CEH 2021 (33–35%) | I58: 2012/2021 | J58: prognoza/szacunek | K58: beta: średnia 0,42, 97,5. percentyl ≈ 0,465; min = CEH 2021 (pojedynczy ośrodek, 33–35%); stosowany tylko do C22 (HCC, renty C22) | L58: ZUS | M58: odsetek
A59: z_F | B59: Roczny koszt ZUS (zasiłek chorobowy) na pracującą osobę w wieku produkcyjnym z HCV pod opieką | C59: 2055.9066 | D59: 1233.54 | E59: 2878.27 | F59: gamma | G59: SE 20% (założenie) | H59: pochodna: ABS_D × SB_DAY (dni ZUS PSZ 2025 × dzienny zasiłek 80%) | I59: 2025 | J59: prognoza/szacunek | K59: dni × stawka (audyt 2, K-A); wcześniej top-down z wydatków ZUS 2012 skalowanych dniami i płacą (≈620 zł/dzień – zawyżone ok. 3×) i naliczane wszystkim pod opieką bez względu na wiek | L59: ZUS | M59: zł/os./rok
A60: PEN_K74 | B60: Średnia renta ZUS/świadczeniobiorcę K74 (2025) | C60: 20932.191 | D60: 16745.75 | E60: 25118.63 | F60: gamma | G60: SE 10% | H60: Łazarski 2015 (11 762.77 zł w 2012) × wskaźniki waloryzacji rent i emerytur ZUS 2013–2025 (iloczyn 1,7795) | I60: 2012/2025 | J60: prognoza/szacunek | K60: indeksacja wskaźnikiem waloryzacji świadczeń (ZUS/MRPiPS), nie wzrostem płac | L60: ZUS | M60: zł/rok
A61: PEN_C22 | B61: Średnia renta ZUS/świadczeniobiorcę C22 (2025) | C61: 23788.727 | D61: 19030.98 | E61: 28546.47 | F61: gamma | G61: SE 10% | H61: Łazarski 2015 (13 367.99 zł w 2012) × wskaźniki waloryzacji rent i emerytur ZUS 2013–2025 (iloczyn 1,7795) | I61: 2012/2025 | J61: prognoza/szacunek | K61: indeksacja wskaźnikiem waloryzacji świadczeń (ZUS/MRPiPS), nie wzrostem płac | L61: ZUS | M61: zł/rok
A62: EMP | B62: Wskaźnik zatrudnienia w wieku produkcyjnym | C62: 0.798 | D62: 0.75 | E62: 0.85 | F62: beta | G62: alfa=798; beta=202 | H62: GUS BAEL IV kw. 2025 (18–59/64 lata) | I62: 2026 | J62: dane źródłowe | K62: — | L62: — | M62: odsetek
A63: AGRI | B63: Udział pracujących w rolnictwie (KRUS) | C63: 0.062 | D63: 0.05 | E63: 0.08 | F63: stały | G63: — | H63: GUS BAEL IV kw. 2025 | I63: 2026 | J63: dane źródłowe | K63: podział świadczeń ZUS/KRUS proporcjonalnie do struktury zatrudnienia (założenie: ta sama kwota świadczenia) | L63: KRUS | M63: odsetek
A64: WAGE | B64: Przeciętne roczne wynagrodzenie brutto | C64: 106842.72 | F64: stały | G64: — | H64: GUS 2025: 8 903,56 zł/mies. (MP 2026 poz. 192) | I64: 2026 | J64: dane źródłowe | K64: ×12 | L64: — | M64: zł/rok
A65: WLOSS | B65: Utrata zdolności do pracy w DC/HCC/LT/po LT | C65: 0.3839 | D65: 0.192 | E65: 0.5759 | F65: stały | G65: — | H65: kalibracja: renty ZUS w modelu (status quo 2026) = przeliczenie top-down wydatków ZUS 2012 (K74+C22) × waloryzacja × AF_LIVER | I65: 2012/2025 | J65: założenie scenariuszowe | K65: odsetek osób z DC/HCC/po przeszczepieniu, które tracą pracę i pobierają rentę; brak danych bezpośrednich (EMP dla populacji ogólnej – nie korygowane dla PWID) | L65: — | M65: odsetek
A66: FRIC | B66: Okres frykcyjny | C66: 0.25 | D66: 0.17 | E66: 0.5 | F66: stały | G66: — | H66: Koopmanschap 1995 (metoda frykcyjna; NL) – transfer | I66: 1995 | J66: dane zagraniczne/literatura międzynarodowa | K66: metoda frykcyjna: strata tylko w okresie zastąpienia pracownika | L66: — | M66: rok
A67: R_FUS | B67: Składki FUS (emer.19,52+rent.8,0+chor.2,45+wyp.1,67) | C67: 0.3164 | F67: stały | G67: — | H67: ustawa o systemie ubezpieczeń społecznych (stawki 2025) | I67: 2025 | J67: dane źródłowe | K67: suma stawek ustawowych | L67: ZUS | M67: % brutto
A68: R_FP | B68: Fundusz Pracy + FGŚP | C68: 0.0255 | F68: stały | G68: — | H68: ustawa o promocji zatrudnienia; ustawa o FGŚP | I68: 2025 | J68: dane źródłowe | K68: — | L68: Budżet/fundusze celowe | M68: % brutto
A69: R_NFZ | B69: Składka zdrowotna 9% (od podstawy po składkach) | C69: 0.077661 | F69: stały | G69: — | H69: ustawa o świadczeniach opieki zdrowotnej | I69: 2025 | J69: dane źródłowe | K69: 9% × (1−13,71%) | L69: NFZ | M69: % brutto
A70: R_PIT | B70: Efektywny PIT przy przeciętnym wynagrodzeniu | C70: 0.066484174 | F70: stały | G70: — | H70: ustawa o PIT (12%, KUP 250 zł, kwota zmniejszająca 300 zł/mies.) | I70: 2025 | J70: prognoza/szacunek | K70: obliczenie dla przeciętnego wynagrodzenia | L70: Budżet/JST | M70: % brutto
A71: D_C | B71: Stopa dyskontowa – koszty | C71: 0.05 | D71: 0 | E71: 0.05 | F71: stały | G71: — | H71: Wytyczne HTA AOTMiT 2016 | I71: 2016 | J71: dane źródłowe | K71: — | L71: — | M71: /rok
A72: D_E | B72: Stopa dyskontowa – efekty | C72: 0.035 | D72: 0 | E72: 0.035 | F72: stały | G72: — | H72: Wytyczne HTA AOTMiT 2016 | I72: 2016 | J72: dane źródłowe | K72: — | L72: — | M72: /rok
A73: THR | B73: Próg opłacalności | C73: 244821 | F73: stały | G73: — | H73: Obwieszczenie Prezesa GUS z 30.10.2025, MP 2025 poz. 1133 (PKB per capita 2024 × 3); nowe obwieszczenie spodziewane ok. 30.10.2026 – do aktualizacji (stan 28.10.2026) | I73: 2025 | J73: dane źródłowe | K73: — | L73: — | M73: zł/QALY
A74: INC | B74: Nowe przewlekłe zakażenia HCV/rok (kohorta otwarta) | C74: 5420 | D74: 3800 | E74: 7000 | F74: trójkątny | G74: min=3800; moda=5420; max=7000 | H74: Flisiak i in. Eur J Gastroenterol Hepatol 2015;27:70–76 (model choroby HCV dla Polski; badanie wspierane finansowo przez producenta leków, jeden ze współautorów z firmy HTA) – 5 420 nowych zakażeń w 2013 r. (rekonstrukcja wsteczna), założone stałe w czasie | I74: 2013 | J74: prognoza/szacunek | K74: stała roczna liczba jak w źródle; zakres ±30% (założenie – brak pomiaru zapadalności w PL; zgłoszenia EPIMELD 3 525–4 029/rok mierzą rozpoznania, nie zakażenia) | L74: — | M74: osoby/rok
A75: AGE_INC | B75: Wiek w chwili zakażenia (nowe kohorty) | C75: 29 | D75: 25 | E75: 40 | F75: stały (tornado) | G75: — | H75: NFZ B.71 2025: środek grupy 18–40 lat (proxy – najmłodsza grupa leczonych) | I75: 2025 | J75: prognoza/szacunek | K75: proxy; brak danych o wieku zakażenia | L75: — | M75: lata
A76: RE | B76: Reinfekcja po SVR – osoby w terapii substytucyjnej (OST) wśród leczonych w status quo | C76: 0.038 | D76: 0.025 | E76: 0.058 | F76: lognormalny | G76: mu=ln(0.038); sigma=0.21 | H76: Hajarizadeh i in. J Hepatol 2020;72:643–657 (metaanaliza, 36 badań) | I76: 2020 | J76: dane zagraniczne/literatura międzynarodowa | K76: 3,8/100 osobolat dla osób na OST (95% CI 2,5–5,8); stosowane do udziału PWID wśród leczonych w status quo | L76: — | M76: /rok
A77: PWID_SH | B77: Udział osób przyjmujących narkotyki wśród leczonych (status quo) | C77: 0.032 | D77: 0.02 | E77: 0.1 | F77: stały (tornado) | G77: — | H77: PZH: PWID = 3,2% rozpoznań HCV w 2023 r. (Przegl Epidemiol 2025;79(4)) | I77: 2023 | J77: dane źródłowe | K77: udział w rozpoznaniach jako proxy udziału w leczonych; max = założenie | L77: — | M77: odsetek
A78: DC0 | B78: Osoby z marskością zdekompensowaną (DC) na starcie | C78: 1590 | D78: 1028 | E78: 2460 | F78: lognormalny | G78: sigma=0.223 | H78: Flisiak i in. Eur J Gastroenterol Hepatol 2015;27:70–76 (model choroby HCV dla Polski; badanie wspierane finansowo przez producenta leków, jeden ze współautorów z firmy HTA): 1 590 (2013); scenariusz bazowy źródła (ok. 2 490 leczonych/rok): 2 460 w 2030; przy ~5 000 leczonych/rok liczba stała do 2030 | I78: 2013/2030 | J78: prognoza/szacunek | K78: 1 590 (2013) – źródło przewiduje stałą liczbę do 2030 przy ~5 000 leczonych/rok; sigma = ln(2460/1590)/1,96 (symetrycznie w skali log) | L78: NFZ | M78: osoby
A79: HCC0 | B79: Osoby z rakiem wątrobowokomórkowym (HCC) związanym z HCV na starcie | C79: 2535 | D79: 1992 | E79: 3227 | F79: pochodny (∝ K_HCC) | G79: HCC0 × K_HCC/K_HCC_bazowe | H79: stan ustalony: 712 nowych HCC/rok (KRN 2023 × 0,42) / (p_HCCD + p_HCCLT) | I79: 2023 | J79: prognoza/szacunek | K79: liczba chorych z HCC spójna z zapadalnością z KRN; w PSA skalowana razem z K_HCC (wspólny cel kalibracji) | L79: NFZ | M79: osoby
A80: PLT0 | B80: Osoby po przeszczepieniu wątroby z powodu HCV (rok 2+) | C80: 1585 | D80: 792 | E80: 3170 | F80: lognormalny | G80: sigma=0.354 | H80: Poltransplant 2013: 318 przeszczepień wątroby, 27,8% z powodu HCV (via Flisiak i in. Eur J Gastroenterol Hepatol 2015;27:70–76 (model choroby HCV dla Polski; badanie wspierane finansowo przez producenta leków, jeden ze współautorów z firmy HTA)) | I80: 2013 | J80: prognoza/szacunek | K80: stan ustalony: 318×0,278×(1−p_LTD)/p_PLTD; sigma = ln(2)/1,96 (możliwy spadek wskazań HCV w erze DAA) | L80: NFZ | M80: osoby
A81: LINK | B81: Odsetek wykrytych (RNA+), którzy rozpoczynają leczenie | C81: 0.5 | D81: 0.3 | E81: 0.574 | F81: trójkątny | G81: min=0.3; moda=0.5; max=0.574 | H81: Brak danych PL (luka). Moda: założenie modelu kaskady; max: Anglia 57,4% wszystkich RNA+ rozpoczęło leczenie (UKHSA, Hepatitis C in England 2025 (publ. IV 2026; dane 2015–2024): 66 537 / 115 870) | I81: 2025 | J81: założenie scenariuszowe / dane zagraniczne/literatura międzynarodowa | K81: bez testu refleksyjnego i nawigacji; górna granica = wynik 10-letniego programu krajowego w Anglii | L81: NFZ | M81: odsetek
A82: LINK_UP | B82: Odsetek rozpoczynających leczenie przy teście refleksyjnym + nawigacji | C82: 0.574 | D82: 0.5 | E82: 0.815 | F82: trójkątny | G82: min=0.5; moda=0.574; max=0.815 | H82: UKHSA, Hepatitis C in England 2025 (publ. IV 2026; dane 2015–2024): 66 537 rozpoczęć leczenia / 115 870 osób RNA+ = 57,4% (baza); 81,5% wśród 81 642 osób z identyfikatorem pozwalającym na powiązanie (maksimum). Egipt 91,8% – niezweryfikowane, nieużywane | I82: 2015–2024 | J82: dane zagraniczne/literatura międzynarodowa | K82: wariant pakietu eliminacyjnego (test refleksyjny + nawigacja); min = LINK bazowy (bez efektu nawigacji) | L82: NFZ | M82: odsetek
A83: Y_MZ | B83: Wykryci RNA+ na 1 test anty-HCV – program populacyjny w POZ (kalibracja) | C83: 0.000625 | F83: stały | G83: — | H83: ~700 dodatkowych rozpoznań (EPIMELD V 2025–III 2026) / 1,12 mln testów (MZ, I 2026) | I83: 2026 | J83: prognoza/szacunek | K83: iloraz; okresy nie pokrywają się – szacunek zgrubny | L83: NFZ | M83: /test
A84: Y_POZ | B84: Wykryci RNA+ na 1 test – POZ | C84: 0.0008 | D84: 0.000625 | E84: 0.0047 | F84: trójkątny | G84: min=0.000625; moda=0.0008; max=0.0047 | H84: Clin Exp Hepatol 2020 (723 654 testów 2018–19: anty-HCV 0,2% w POZ × 40% wiremii); min: program MZ 2025–26 (~700 rozpoznań / 1,12 mln testów); max: PLoS One 2017;12:e0185055 (losowa próba pacjentów POZ 2012–16: 0,47% RNA+, 95% CI 0,38–0,57) | I84: 2012–16/2018–19/2026 | J84: dane źródłowe | K84: baza = wynik rzeczywistego testowania w POZ, spójny z obserwowaną wydajnością programu MZ; 0,47% to rozpowszechnienie sprzed leczenia ~ćwierć miliona osób i obejmuje już rozpoznanych – górna granica | L84: NFZ | M84: /test
A85: Y_LAB | B85: Wykryci RNA+ na 1 test – szpitale (przy przyjęciu) i laboratoria | C85: 0.0026 | D85: 0.0024 | E85: 0.0048 | F85: trójkątny | G85: min=0.0024; moda=0.0026; max=0.0048 | H85: Clin Exp Hepatol 2020 (723 654 testów 2018–19): szpitale 0,6–0,7% anty-HCV (baza 0,65%); laboratoria diagnostyczne w czasie kampanii 1,2% (maksimum); całość badania 0,5%; × 40% wiremii | I85: 2018–19 | J85: dane źródłowe | K85: iloczyn odsetków; baza = szpitale (stały kanał), laboratoria w kampanii = górna granica | L85: NFZ | M85: /test
A86: Y_KEY | B86: Wykryci RNA+ na 1 test – osoby przyjmujące narkotyki (31,2% × 50%) | C86: 0.156 | D86: 0.1248 | E86: 0.295 | F86: stały (tornado) | G86: — | H86: KCPU 2021 (31,2% anty-HCV wśród badanych osób przyjmujących narkotyki) × 50% wiremii (założenie źródła); max: Rosińska i in. BMC Infect Dis 2015 (59%, dane 2004–05) | I86: 2021 (max 2004–05) | J86: dane źródłowe | K86: baza = najnowsze dane; min = −20% (założenie); max = starsze badanie bio-behawioralne | L86: MZ/SW | M86: /test
A87: KEY_POOL | B87: Osoby z HCV wśród aktywnie wstrzykujących narkotyki (górny limit wykryć) | C87: 10000 | D87: 7000 | E87: 13000 | F87: stały (tornado) | G87: — | H87: Flisiak i in. Eur J Gastroenterol Hepatol 2015;27:70–76 (model choroby HCV dla Polski; badanie wspierane finansowo przez producenta leków, jeden ze współautorów z firmy HTA), Tab. 2 (10 000; 5% zakażonych) | I87: 2013 | J87: prognoza/szacunek | K87: limit skumulowanych wykryć w kanale populacji kluczowych; zakres ±30% (założenie) | L87: MZ/SW | M87: osoby
A88: OH | B88: Narzut logistyczny na koszt testów (pobranie, transport próbek, outreach) | C88: 0.2 | D88: 0 | E88: 0.5 | F88: stały (tornado) | G88: — | H88: brak danych PL – założenie scenariuszowe (do weryfikacji w pilotażu) | I88: 2026 | J88: założenie scenariuszowe | K88: mnożnik (1+OH) na koszt testów; nawigacja i koszty stałe liczone osobno (NAV, FIX) | L88: NFZ / MZ | M88: odsetek
A89: PROG_Y | B89: Długość programu inwestycyjnego | C89: 10 | D89: 5 | E89: 15 | F89: stały | G89: — | H89: założenie scenariuszowe (horyzont do 2035 – zbieżny z celem WHO 2030 + 5 lat) | I89: 2026 | J89: założenie scenariuszowe | K89: — | L89: — | M89: lata
A90: THR_INFO | B90: Liczba lat horyzontu domyślnego | C90: 20 | F90: stały | G90: — | H90: Wytyczne AOTMiT 2016: horyzont adekwatny do przebiegu choroby; 20 lat dla decyzji budżetowych | I90: 2016 | J90: założenie scenariuszowe | K90: — | L90: — | M90: lata
A91: K_DC | B91: Mnożnik kalibracyjny przejść do DC (CC→DC, CC po SVR→DC) | C91: 0.3714 | D91: 0.2401 | E91: 0.5745 | F91: lognormalny | G91: sigma=0.223 | H91: Kalibracja do Flisiak i in. Eur J Gastroenterol Hepatol 2015;27:70–76 (model choroby HCV dla Polski; badanie wspierane finansowo przez producenta leków, jeden ze współautorów z firmy HTA): DC ≈ 1 590 w 2030 przy ~5 000 leczonych/rok | I91: 2026 | J91: prognoza/szacunek | K91: dopasowanie iteracyjne: status quo odtwarza DC ≈ 1 590 w 2030 (model źródłowy – brak polskich danych o DC); sigma = ln(2460/1590)/1,96; K=1 (bez kalibracji) = scenariusz | L91: — | M91: ×
A92: K_HCC | B92: Mnożnik kalibracyjny przejść do HCC (CC→HCC, CC po SVR→HCC) | C92: 1.2371 | D92: 0.972 | E92: 1.5745 | F92: lognormalny | G92: sigma=0.123 | H92: Kalibracja do Krajowego Rejestru Nowotworów: 1 695 nowych zachorowań C22 (2023) × udział HCV 0,42 (rejestr LIVER) ≈ 712 nowych HCC/rok | I92: 2023 | J92: prognoza/szacunek | K92: dopasowanie: nowe HCC w status quo w 2026 ≈ 712; sigma = ln(0,42/0,33)/1,96 (zakres udziału HCV); C22 obejmuje też raka dróg żółciowych – cel raczej zawyżony; K=1 = scenariusz | L92: — | M92: ×
A93: RAMP | B93: Okres dochodzenia programu do pełnej skali (kadry, ośrodki) | C93: 3 | D93: 1 | E93: 5 | F93: stały (tornado) | G93: — | H93: założenie scenariuszowe (panel: wykonalność kadrowa; maks. obserwowane B.71 = 12 171 leczonych w 2017 r., NFZ) | I93: 2026 | J93: założenie scenariuszowe | K93: budżet roku t × min(1, t/RAMP) | L93: — | M93: lata
A94: CAP_OBS | B94: Największa obserwowana liczba leczonych w B.71 w roku (punkt odniesienia wykonalności) | C94: 12171 | F94: stały | G94: — | H94: NFZ app-stat B.71: 12 171 leczonych w 2017 (2018: 9 436; 2019: 8 521) | I94: 2017 | J94: dane źródłowe | K94: — | L94: NFZ | M94: osoby/rok
A95: AGEW_1 | B95: Struktura wieku kohorty startowej – liczba leczonych B.71 w grupie 18–40 (z 7–17) | C95: 915 | F95: stały | G95: — | H95: NFZ app-stat B.71 2025 wg grup wieku | I95: 2025 | J95: dane źródłowe | K95: wagi kohorty wielowiekowej (ten sam rozkład stanów w każdej grupie – uproszczenie) | L95: — | M95: osoby
A96: AGEW_2 | B96: Struktura wieku kohorty startowej – liczba leczonych B.71 w grupie 41–60 | C96: 2339 | F96: stały | G96: — | H96: NFZ app-stat B.71 2025 wg grup wieku | I96: 2025 | J96: dane źródłowe | K96: wagi kohorty wielowiekowej (ten sam rozkład stanów w każdej grupie – uproszczenie) | L96: — | M96: osoby
A97: AGEW_3 | B97: Struktura wieku kohorty startowej – liczba leczonych B.71 w grupie 61–80 | C97: 1478 | F97: stały | G97: — | H97: NFZ app-stat B.71 2025 wg grup wieku | I97: 2025 | J97: dane źródłowe | K97: wagi kohorty wielowiekowej (ten sam rozkład stanów w każdej grupie – uproszczenie) | L97: — | M97: osoby
A98: AGEW_4 | B98: Struktura wieku kohorty startowej – liczba leczonych B.71 w grupie 81+ | C98: 111 | F98: stały | G98: — | H98: NFZ app-stat B.71 2025 wg grup wieku | I98: 2025 | J98: dane źródłowe | K98: wagi kohorty wielowiekowej (ten sam rozkład stanów w każdej grupie – uproszczenie) | L98: — | M98: osoby
A99: RE_KEY | B99: Reinfekcja po SVR – osoby aktywnie wstrzykujące narkotyki (kanał populacji kluczowych) | C99: 0.062 | D99: 0.043 | E99: 0.09 | F99: lognormalny | G99: mu=ln(0.062); sigma=0.188 | H99: Hajarizadeh i in. J Hepatol 2020;72:643–657 (metaanaliza): 6,2/100 osobolat u aktywnie wstrzykujących (95% CI 4,3–9,0) | I99: 2020 | J99: dane zagraniczne/literatura międzynarodowa | K99: sigma=(ln 9,0−ln 4,3)/3,92; reinfekcja trafia do F1 (uproszczenie) | L99: — | M99: /rok
A100: SMR_PWID | B100: Nadwyżka umieralności osób przyjmujących narkotyki (mnożnik umieralności ogólnej) | C100: 14.68 | D100: 13.01 | E100: 16.35 | F100: stały (tornado) | G100: — | H100: Mathers i in. Bull World Health Organ 2013;91:102–123 (metaanaliza 32 kohort; SMR 14,68, 95% CI 13,01–16,35), doi 10.2471/BLT.12.108282 | I100: 2013 | J100: dane zagraniczne/literatura międzynarodowa | K100: mnożnik tablic trwania życia GUS w kanale populacji kluczowych; zakres = 95% CI (populacje głównie spoza PL) | L100: — | M100: ×
A101: c_LT1 | B101: Koszt NFZ 1. roku po przeszczepieniu wątroby (stan LT) | C101: 47540.572 | D101: 38032.457 | E101: 57048.686 | F101: gamma | G101: SE 10% | H101: Kaczor 2012 (koszty stanów, ceny 2016) via analiza ekonomiczna wnioskodawcy (firma konsultingowa) opublikowana w BIP AOTMiT, zlecenie 153/2017, Tab. 73/198 × CPI GUS (30 167,61 zł w cenach 2016) | I101: 2016→2025 | J101: prognoza/szacunek | K101: koszt stanu LT (rok po zabiegu); zabieg = c_LT (zdarzenie) | L101: NFZ | M101: zł/rok
A102: VALP | B102: Iloczyn wskaźników waloryzacji rent ZUS 2013–2025 | C102: 1.7795291 | F102: stały | G102: — | H102: ZUS/MRPiPS: wskaźniki waloryzacji 2013–2025 (104,0; 101,6; 100,68; 100,24; 100,44; 102,98; 102,86; 103,56; 104,24; 107,0; 114,8; 112,12; 105,5) | I102: 2025 | J102: dane źródłowe | K102: iloczyn | L102: — | M102: ×
A103: DX_IN | B103: Nowe rozpoznania przewlekłego HCV rocznie (wejście do opieki) | C103: 4029 | D103: 3525 | E103: 4944 | F103: stały (tornado) | G103: — | H103: NIZP PZH-PIB EPIMELD (meldunek 12B/2025): 4 029 rozpoznań w 2025; min 3 525 (2024); max = 2025 × 1,227 (wzrost r/r w 2026, EPIMELD 10A/2026) | I103: 2024–2026 | J103: dane źródłowe | K103: skalowane wielkością puli wiremicznych | L103: NFZ | M103: osoby/rok
A104: T_PRE | B104: Czas w opiece przed leczeniem (kwalifikacja, kolejka) na osobę leczoną | C104: 0.53972603 | D104: 0.147945 | E104: 1.60274 | F104: stały (tornado) | G104: — | H104: NFZ Informator o terminach leczenia (X 2026): mediana oczekiwania – poradnia hepatologiczna 197 dni; min: poradnia chorób zakaźnych 54 dni; max: p90 hepatologia 585 dni | I104: 2026 | J104: dane źródłowe | K104: lata opieki przed rozpoczęciem leczenia | L104: NFZ | M104: lata
A105: W0 | B105: Zdiagnozowani pod opieką czekający na leczenie (na start) | C105: 0 | D105: 0 | E105: 10000 | F105: stały (tornado) | G105: — | H105: NFZ B.71 i EPIMELD 2019–2025: leczonych było co roku więcej niż nowych rozpoznań (stosunek 1,20 w 2025) – brak dowodu zaległości; max = założenie | I105: 2025 | J105: prognoza/szacunek | K105: stan zaległości; 0 = brak kolejki osób zdiagnozowanych | L105: NFZ | M105: osoby
A106: CARE_ALL | B106: Przełącznik: koszt opieki u wszystkich z wiremią (wariant sprzed audytu) | C106: 0 | F106: stały | G106: — | H106: przełącznik metody (0 = tylko zdiagnozowani pod opieką) | I106: 2026 | J106: założenie scenariuszowe | K106: używany tylko w analizie scenariuszowej | L106: — | M106: 0/1
A107: HALF_CYCLE | B107: Przełącznik: korekta połowy cyklu (trapez) | C107: 1 | F107: stały | G107: — | H107: CHEERS 2022 / ISPOR – dobra praktyka modelowania | I107: 2022 | J107: założenie scenariuszowe | K107: 1 = włączona | L107: — | M107: 0/1
A108: ABS_D | B108: Dni absencji chorobowej na pracującą osobę w wieku produkcyjnym z HCV pod opieką rocznie | C108: 10.034841 | F108: stały | G108: — | H108: ZUS PSZ 2025: 28 057 dni absencji B18 × AF_B18 / pracujący w wieku produkcyjnym pod opieką w status quo 2026 (model) | I108: 2025 | J108: prognoza/szacunek | K108: dopasowanie kalibracyjne (odtwarza dni ZUS 2025); absencja tylko u pracujących przed wiekiem emerytalnym (audyt 2, K-A) | L108: ZUS | M108: dni/rok
A109: NAV | B109: Koszt nawigacji/łączenia z opieką na osobę wykrytą (pakiet z testem refleksyjnym) | C109: 2006.934 | D109: 938.91 | E109: 4289.87 | F109: gamma | G109: SE 20% (założenie) | H109: Project INSPIRE, Nowy Jork (J Public Health Manag Pract 2019; PMC6314903): 656–787 USD na uczestnika (ceny 2015) × parytet siły nabywczej PKB 2015 (Bank Światowy, 1,7651 zł/USD) × CPI GUS 2016–2025 – dane zagraniczne (USA) | I109: 2015 | J109: dane zagraniczne/literatura międzynarodowa | K109: średnia dwóch ośrodków; zakres symetryczny w skali log: ÷/× (kurs rynkowy NBP 3,7730 / PPP) – max = przeliczenie kursem rynkowym | L109: NFZ / MZ | M109: zł/osobę
A110: FIX | B110: Koszty stałe programu wykrywania (koordynacja, IT, działania informacyjne) rocznie | C110: 1223620.5 | D110: 611810.27 | E110: 2447241.1 | F110: stały (tornado) | G110: — | H110: założenie: 5 etatów koordynacji × przeciętne wynagrodzenie GUS 2025 × 1,2048 (składki pracodawcy) + 0,58 mln zł (rząd wielkości: konkurs Krajowego Centrum ds. AIDS na akcyjne testowanie HIV/kiła/HCV 2025 – proxy działań terenowych/informacyjnych) | I110: 2025 | J110: założenie scenariuszowe | K110: w I1, I2, I4 przez PROG_Y lat; I3 działa w istniejącej sieci (bez kosztu stałego – założenie); zakres ×0,5–2 | L110: MZ | M110: zł/rok
A111: INC_TREND | B111: Roczna zmiana liczby nowych zakażeń | C111: 0 | D111: -0.05 | E111: 0 | F111: stały (tornado) | G111: — | H111: założenie: stała zapadalność jak w źródle; scenariusz −5%/rok (spadek zakażeń przy redukcji szkód – założenie) | I111: 2026 | J111: założenie scenariuszowe | K111: INC × (1+INC_TREND)^t | L111: — | M111: /rok
...

Sheet Ustawienia
A1: nazwa | B1: wartość | C1: opis
A2: x_dk | B2: 0.05 | C2: stopa dyskontowa kosztów (AOTMiT 5%)
A3: x_de | B3: 0.035 | C3: stopa dyskontowa efektów (AOTMiT 3,5%)
A4: x_H | B4: 20 | C4: horyzont analizy w latach (1–50)
A5: x_testy | B5: 0 | C5: 1 = testy i koszty stałe programu finansuje inny płatnik (wyłączone z porównania); 0 = wariant pełny

Sheet L_S1
A1: S1: Status quo (4 832 leczonych/rok) – liczebności (silnik, wartości) i koszty (formuły), zł/rok, niezdyskontowane. Szacunek modelu.
A2: rok | B2: t | C2: treated | D2: NFZ_diag | E2: MZ_SW | F2: nNAV | G2: FIXon | H2: cF03 | I2: cF4 | J2: cDC | K2: cHCC | L2: cPLT | M2: cSVn | N2: cSVc | O2: cLTn | P2: cLT1 | Q2: wAdv | R2: wHCC | S2: wGH | T2: cAbs | U2: cAbsW | V2: QALY | W2: newDC | X2: newHCC | Y2: LT | Z2: liverD | AA2: NFZ_med | AB2: NFZ_DAA | AC2: NFZ_mon | AD2: NFZ_diag_k | AE2: MZ_SW_k | AF2: NAV_k | AG2: FIX_k | AH2: ZUS | AI2: KRUS | AJ2: lostw | AK2: lost_FUS | AL2: lost_NFZ | AM2: lost_PIT | AN2: lost_FP | AO2: NFZ | AP2: PUBLIC | AQ2: SOCIETAL | AR2: INV_NFZ | AS2: INV_PUB
A3: 2026 | B3: 0 | C3: 4832 | D3: 0 | E3: 0 | F3: 0 | G3: 0 | H3: 2320.855 | I3: 208.058 | J3: 1579.412 | K3: 2524.99 | L3: 1540.438 | M3: 6431.679 | N3: 567.81 | O3: 89.046 | P3: 44.523 | Q3: 2134.761 | R3: 1703.413 | S3: 312.377 | T3: 2528.914 | U3: 1400.363 | V3: 113392.92 | W3: 265.86 | X3: 711.886 | Y3: 89.046 | Z3: 922.327 | AA3: =H3*x_c_F+I3*x_c_CC+J3*x_c_DC+K3*x_c_HCC+L3*x_c_PLT+M3*x_c_SVRn+N3*x_c_SVRcc+O3*x_c_LT+P3*x_c_LT1 -> 2.8240502e+08 | AB3: =C3*x_c_DAA -> 109976320 | AC3: =C3*x_c_MON -> 27857108 | AD3: =D3*(1-x_testy) -> 0 | AE3: =E3*(1-x_testy) -> 0 | AF3: =F3*x_NAV -> 0 | AG3: =G3*x_FIX*(1-x_testy) -> 0 | AH3: =x_z_F*U3+(1-x_AGRI)*x_EMP*x_WLOSS*(x_PEN_K74*Q3+x_PEN_C22*R3) -> 27364032 | AI3: =x_AGRI*x_EMP*x_WLOSS*(x_PEN_K74*Q3+x_PEN_C22*R3) -> 1618412.6 | AJ3: =x_EMP*x_WAGE*(x_WLOSS*(Q3+R3)+S3)+U3*x_ABS_D*x_WAGE/365 -> 1.5637604e+08 | AK3: =AJ3*x_R_FUS -> 49477379 | AL3: =AJ3*x_R_NFZ -> 12144320 | AM3: =AJ3*x_R_PIT -> 10396532 | AN3: =AJ3*x_R_FP -> 3987589 | AO3: =AA3+AB3+AC3+AD3+AF3 -> 4.2023845e+08 | AP3: =AO3+AE3+AG3+AH3+AI3+AK3+AL3+AM3+AN3 -> 5.2522671e+08 | AQ3: =AO3+AE3+AG3+AJ3 -> 5.7661449e+08 | AR3: =AB3+AC3+AD3+AF3 -> 1.3783343e+08 | AS3: =AR3+AE3+AG3 -> 1.3783343e+08
A4: 2027 | B4: 1 | C4: 4832 | D4: 0 | E4: 0 | F4: 0 | G4: 0 | H4: 2307.655 | I4: 219.602 | J4: 1564.594 | K4: 2522.589 | L4: 1489.389 | M4: 10633.791 | N4: 958.016 | O4: 87.923 | P4: 88.484 | Q4: 2138.396 | R4: 1717.819 | S4: 940.006 | T4: 2527.257 | U4: 1441.565 | V4: 114502.79 | W4: 275.683 | X4: 742.641 | Y4: 87.923 | Z4: 925.838 | AA4: =H4*x_c_F+I4*x_c_CC+J4*x_c_DC+K4*x_c_HCC+L4*x_c_PLT+M4*x_c_SVRn+N4*x_c_SVRcc+O4*x_c_LT+P4*x_c_LT1 -> 2.857346e+08 | AB4: =C4*x_c_DAA -> 109976320 | AC4: =C4*x_c_MON -> 27857108 | AD4: =D4*(1-x_testy) -> 0 | AE4: =E4*(1-x_testy) -> 0 | AF4: =F4*x_NAV -> 0 | AG4: =G4*x_FIX*(1-x_testy) -> 0 | AH4: =x_z_F*U4+(1-x_AGRI)*x_EMP*x_WLOSS*(x_PEN_K74*Q4+x_PEN_C22*R4) -> 27569082 | AI4: =x_AGRI*x_EMP*x_WLOSS*(x_PEN_K74*Q4+x_PEN_C22*R4) -> 1626367 | AJ4: =x_EMP*x_WAGE*(x_WLOSS*(Q4+R4)+S4)+U4*x_ABS_D*x_WAGE/365 -> 2.1059953e+08 | AK4: =AJ4*x_R_FUS -> 66633692 | AL4: =AJ4*x_R_NFZ -> 16355370 | AM4: =AJ4*x_R_PIT -> 14001536 | AN4: =AJ4*x_R_FP -> 5370288 | AO4: =AA4+AB4+AC4+AD4+AF4 -> 4.2356803e+08 | AP4: =AO4+AE4+AG4+AH4+AI4+AK4+AL4+AM4+AN4 -> 5.5512437e+08 | AQ4: =AO4+AE4+AG4+AJ4 -> 6.3416756e+08 | AR4: =AB4+AC4+AD4+AF4 -> 1.3783343e+08 | AS4: =AR4+AE4+AG4 -> 1.3783343e+08
A5: 2028 | B5: 2 | C5: 4832 | D5: 0 | E5: 0 | F5: 0 | G5: 0 | H5: 2293.265 | I5: 232.353 | J5: 1562.24 | K5: 2550.931 | L5: 1475.77 | M5: 14757.577 | N5: 1359.883 | O5: 87.651 | P5: 87.787 | Q5: 2147.743 | R5: 1757.091 | S5: 1573.278 | T5: 2525.618 | U5: 1481.15 | V5: 115688.46 | W5: 287.283 | X5: 774.535 | Y5: 87.651 | Z5: 927.579 | AA5: =H5*x_c_F+I5*x_c_CC+J5*x_c_DC+K5*x_c_HCC+L5*x_c_PLT+M5*x_c_SVRn+N5*x_c_SVRcc+O5*x_c_LT+P5*x_c_LT1 -> 2.9056791e+08 | AB5: =C5*x_c_DAA -> 109976320 | AC5: =C5*x_c_MON -> 27857108 | AD5: =D5*(1-x_testy) -> 0 | AE5: =E5*(1-x_testy) -> 0 | AF5: =F5*x_NAV -> 0 | AG5: =G5*x_FIX*(1-x_testy) -> 0 | AH5: =x_z_F*U5+(1-x_AGRI)*x_EMP*x_WLOSS*(x_PEN_K74*Q5+x_PEN_C22*R5) -> 27975146 | AI5: =x_AGRI*x_EMP*x_WLOSS*(x_PEN_K74*Q5+x_PEN_C22*R5) -> 1647827.8 | AJ5: =x_EMP*x_WAGE*(x_WLOSS*(Q5+R5)+S5)+U5*x_ABS_D*x_WAGE/365 -> 2.6630026e+08 | AK5: =AJ5*x_R_FUS -> 84257403 | AL5: =AJ5*x_R_NFZ -> 20681145 | AM5: =AJ5*x_R_PIT -> 17704753 | AN5: =AJ5*x_R_FP -> 6790656.7 | AO5: =AA5+AB5+AC5+AD5+AF5 -> 4.2840134e+08 | AP5: =AO5+AE5+AG5+AH5+AI5+AK5+AL5+AM5+AN5 -> 5.8745827e+08 | AQ5: =AO5+AE5+AG5+AJ5 -> 6.947016e+08 | AR5: =AB5+AC5+AD5+AF5 -> 1.3783343e+08 | AS5: =AR5+AE5+AG5 -> 1.3783343e+08
A6: 2029 | B6: 3 | C6: 4832 | D6: 0 | E6: 0 | F6: 0 | G6: 0 | H6: 2278.401 | I6: 245.586 | J6: 1571.333 | K6: 2601.368 | L6: 1461.227 | M6: 18799.94 | N6: 1773.467 | O6: 88.124 | P6: 87.888 | Q6: 2166.882 | R6: 1814.876 | S6: 2215.331 | T6: 2523.987 | U6: 1519.149 | V6: 116926.82 | W6: 299.555 | X6: 805.722 | Y6: 88.124 | Z6: 937.757 | AA6: =H6*x_c_F+I6*x_c_CC+J6*x_c_DC+K6*x_c_HCC+L6*x_c_PLT+M6*x_c_SVRn+N6*x_c_SVRcc+O6*x_c_LT+P6*x_c_LT1 -> 2.9724471e+08 | AB6: =C6*x_c_DAA -> 109976320 | AC6: =C6*x_c_MON -> 27857108 | AD6: =D6*(1-x_testy) -> 0 | AE6: =E6*(1-x_testy) -> 0 | AF6: =F6*x_NAV -> 0 | AG6: =G6*x_FIX*(1-x_testy) -> 0 | AH6: =x_z_F*U6+(1-x_AGRI)*x_EMP*x_WLOSS*(x_PEN_K74*Q6+x_PEN_C22*R6) -> 28563403 | AI6: =x_AGRI*x_EMP*x_WLOSS*(x_PEN_K74*Q6+x_PEN_C22*R6) -> 1681546.7 | AJ6: =x_EMP*x_WAGE*(x_WLOSS*(Q6+R6)+S6)+U6*x_ABS_D*x_WAGE/365 -> 3.2367147e+08 | AK6: =AJ6*x_R_FUS -> 1.0240965e+08 | AL6: =AJ6*x_R_NFZ -> 25136650 | AM6: =AJ6*x_R_PIT -> 21519030 | AN6: =AJ6*x_R_FP -> 8253622.5 | AO6: =AA6+AB6+AC6+AD6+AF6 -> 4.3507814e+08 | AP6: =AO6+AE6+AG6+AH6+AI6+AK6+AL6+AM6+AN6 -> 6.2264205e+08 | AQ6: =AO6+AE6+AG6+AJ6 -> 7.5874961e+08 | AR6: =AB6+AC6+AD6+AF6 -> 1.3783343e+08 | AS6: =AR6+AE6+AG6 -> 1.3783343e+08
A7: 2030 | B7: 4 | C7: 4832 | D7: 0 | E7: 0 | F7: 0 | G7: 0 | H7: 2263.649 | I7: 258.71 | J7: 1590.035 | K7: 2666.072 | L7: 1446.439 | M7: 22759 | N7: 2197.668 | O7: 89.202 | P7: 88.663 | Q7: 2194.943 | R7: 1885.483 | S7: 2871.709 | T7: 2522.359 | U7: 1555.596 | V7: 118203.52 | W7: 311.65 | X7: 834.807 | Y7: 89.202 | Z7: 953.972 | AA7: =H7*x_c_F+I7*x_c_CC+J7*x_c_DC+K7*x_c_HCC+L7*x_c_PLT+M7*x_c_SVRn+N7*x_c_SVRcc+O7*x_c_LT+P7*x_c_LT1 -> 3.0520165e+08 | AB7: =C7*x_c_DAA -> 109976320 | AC7: =C7*x_c_MON -> 27857108 | AD7: =D7*(1-x_testy) -> 0 | AE7: =E7*(1-x_testy) -> 0 | AF7: =F7*x_NAV -> 0 | AG7: =G7*x_FIX*(1-x_testy) -> 0 | AH7: =x_z_F*U7+(1-x_AGRI)*x_EMP*x_WLOSS*(x_PEN_K74*Q7+x_PEN_C22*R7) -> 29289784 | AI7: =x_AGRI*x_EMP*x_WLOSS*(x_PEN_K74*Q7+x_PEN_C22*R7) -> 1724606.3 | AJ7: =x_EMP*x_WAGE*(x_WLOSS*(Q7+R7)+S7)+U7*x_ABS_D*x_WAGE/365 -> 3.8297119e+08 | AK7: =AJ7*x_R_FUS -> 1.2117209e+08 | AL7: =AJ7*x_R_NFZ -> 29741926 | AM7: =AJ7*x_R_PIT -> 25461523 | AN7: =AJ7*x_R_FP -> 9765765.4 | AO7: =AA7+AB7+AC7+AD7+AF7 -> 4.4303508e+08 | AP7: =AO7+AE7+AG7+AH7+AI7+AK7+AL7+AM7+AN7 -> 6.6019077e+08 | AQ7: =AO7+AE7+AG7+AJ7 -> 8.2600627e+08 | AR7: =AB7+AC7+AD7+AF7 -> 1.3783343e+08 | AS7: =AR7+AE7+AG7 -> 1.3783343e+08
A8: 2031 | B8: 5 | C8: 4832 | D8: 0 | E8: 0 | F8: 0 | G8: 0 | H8: 2249.476 | I8: 271.252 | J8: 1616.09 | K8: 2738.254 | L8: 1431.964 | M8: 26634.076 | N8: 2630.502 | O8: 90.728 | P8: 89.965 | Q8: 2230.668 | R8: 1963.977 | S8: 3546.222 | T8: 2520.729 | U8: 1590.528 | V8: 119508.27 | W8: 322.934 | X8: 860.79 | Y8: 90.728 | Z8: 974.025 | AA8: =H8*x_c_F+I8*x_c_CC+J8*x_c_DC+K8*x_c_HCC+L8*x_c_PLT+M8*x_c_SVRn+N8*x_c_SVRcc+O8*x_c_LT+P8*x_c_LT1 -> 3.1392097e+08 | AB8: =C8*x_c_DAA -> 109976320 | AC8: =C8*x_c_MON -> 27857108 | AD8: =D8*(1-x_testy) -> 0 | AE8: =E8*(1-x_testy) -> 0 | AF8: =F8*x_NAV -> 0 | AG8: =G8*x_FIX*(1-x_testy) -> 0 | AH8: =x_z_F*U8+(1-x_AGRI)*x_EMP*x_WLOSS*(x_PEN_K74*Q8+x_PEN_C22*R8) -> 30113064 | AI8: =x_AGRI*x_EMP*x_WLOSS*(x_PEN_K74*Q8+x_PEN_C22*R8) -> 1774276.6 | AJ8: =x_EMP*x_WAGE*(x_WLOSS*(Q8+R8)+S8)+U8*x_ABS_D*x_WAGE/365 -> 4.4432167e+08 | AK8: =AJ8*x_R_FUS -> 1.4058338e+08 | AL8: =AJ8*x_R_NFZ -> 34506465 | AM8: =AJ8*x_R_PIT -> 29540359 | AN8: =AJ8*x_R_FP -> 11330203 | AO8: =AA8+AB8+AC8+AD8+AF8 -> 4.5175439e+08 | AP8: =AO8+AE8+AG8+AH8+AI8+AK8+AL8+AM8+AN8 -> 6.9960214e+08 | AQ8: =AO8+AE8+AG8+AJ8 -> 8.9607607e+08 | AR8: =AB8+AC8+AD8+AF8 -> 1.3783343e+08 | AS8: =AR8+AE8+AG8 -> 1.3783343e+08
A9: 2032 | B9: 6 | C9: 4832 | D9: 0 | E9: 0 | F9: 0 | G9: 0 | H9: 2236.247 | I9: 282.847 | J9: 1647.059 | K9: 2812.173 | L9: 1418.185 | M9: 30425.008 | N9: 3069.267 | O9: 92.542 | P9: 91.635 | Q9: 2272.551 | R9: 2046.171 | S9: 4241.049 | T9: 2519.094 | U9: 1623.998 | V9: 120830.92 | W9: 332.945 | X9: 882.962 | Y9: 92.542 | Z9: 995.927 | AA9: =H9*x_c_F+I9*x_c_CC+J9*x_c_DC+K9*x_c_HCC+L9*x_c_PLT+M9*x_c_SVRn+N9*x_c_SVRcc+O9*x_c_LT+P9*x_c_LT1 -> 3.2293899e+08 | AB9: =C9*x_c_DAA -> 109976320 | AC9: =C9*x_c_MON -> 27857108 | AD9: =D9*(1-x_testy) -> 0 | AE9: =E9*(1-x_testy) -> 0 | AF9: =F9*x_NAV -> 0 | AG9: =G9*x_FIX*(1-x_testy) -> 0 | AH9: =x_z_F*U9+(1-x_AGRI)*x_EMP*x_WLOSS*(x_PEN_K74*Q9+x_PEN_C22*R9) -> 30995673 | AI9: =x_AGRI*x_EMP*x_WLOSS*(x_PEN_K74*Q9+x_PEN_C22*R9) -> 1828067 | AJ9: =x_EMP*x_WAGE*(x_WLOSS*(Q9+R9)+S9)+U9*x_ABS_D*x_WAGE/365 -> 5.077225e+08 | AK9: =AJ9*x_R_FUS -> 1.606434e+08 | AL9: =AJ9*x_R_NFZ -> 39430237 | AM9: =AJ9*x_R_PIT -> 33755511 | AN9: =AJ9*x_R_FP -> 12946924 | AO9: =AA9+AB9+AC9+AD9+AF9 -> 4.6077242e+08 | AP9: =AO9+AE9+AG9+AH9+AI9+AK9+AL9+AM9+AN9 -> 7.4037223e+08 | AQ9: =AO9+AE9+AG9+AJ9 -> 9.6849492e+08 | AR9: =AB9+AC9+AD9+AF9 -> 1.3783343e+08 | AS9: =AR9+AE9+AG9 -> 1.3783343e+08
A10: 2033 | B10: 7 | C10: 4832 | D10: 0 | E10: 0 | F10: 0 | G10: 0 | H10: 2224.233 | I10: 293.219 | J10: 1680.533 | K10: 2883.148 | L10: 1405.327 | M10: 34132.208 | N10: 3510.756 | O10: 94.493 | P10: 93.517 | Q10: 2318.976 | R10: 2128.603 | S10: 4956.95 | T10: 2517.452 | U10: 1656.052 | V10: 122162.84 | W10: 341.368 | X10: 900.889 | Y10: 94.493 | Z10: 1018.015 | AA10: =H10*x_c_F+I10*x_c_CC+J10*x_c_DC+K10*x_c_HCC+L10*x_c_PLT+M10*x_c_SVRn+N10*x_c_SVRcc+O10*x_c_LT+P10*x_c_LT1 -> 3.318566e+08 | AB10: =C10*x_c_DAA -> 109976320 | AC10: =C10*x_c_MON -> 27857108 | AD10: =D10*(1-x_testy) -> 0 | AE10: =E10*(1-x_testy) -> 0 | AF10: =F10*x_NAV -> 0 | AG10: =G10*x_FIX*(1-x_testy) -> 0 | AH10: =x_z_F*U10+(1-x_AGRI)*x_EMP*x_WLOSS*(x_PEN_K74*Q10+x_PEN_C22*R10) -> 31904317 | AI10: =x_AGRI*x_EMP*x_WLOSS*(x_PEN_K74*Q10+x_PEN_C22*R10) -> 1883770.8 | AJ10: =x_EMP*x_WAGE*(x_WLOSS*(Q10+R10)+S10)+U10*x_ABS_D*x_WAGE/365 -> 5.7307241e+08 | AK10: =AJ10*x_R_FUS -> 1.8132011e+08 | AL10: =AJ10*x_R_NFZ -> 44505377 | AM10: =AJ10*x_R_PIT -> 38100246 | AN10: =AJ10*x_R_FP -> 14613347 | AO10: =AA10+AB10+AC10+AD10+AF10 -> 4.6969003e+08 | AP10: =AO10+AE10+AG10+AH10+AI10+AK10+AL10+AM10+AN10 -> 7.820172e+08 | AQ10: =AO10+AE10+AG10+AJ10 -> 1.0427624e+09 | AR10: =AB10+AC10+AD10+AF10 -> 1.3783343e+08 | AS10: =AR10+AE10+AG10 -> 1.3783343e+08
A11: 2034 | B11: 8 | C11: 4832 | D11: 0 | E11: 0 | F11: 0 | G11: 0 | H11: 2213.629 | I11: 302.172 | J11: 1714.258 | K11: 2947.492 | L11: 1393.462 | M11: 37756.249 | N11: 3951.388 | O11: 96.443 | P11: 95.468 | Q11: 2368.312 | R11: 2208.491 | S11: 5693.415 | T11: 2515.801 | U11: 1686.729 | V11: 123496.53 | W11: 348.005 | X11: 914.329 | Y11: 96.443 | Z11: 1038.863 | AA11: =H11*x_c_F+I11*x_c_CC+J11*x_c_DC+K11*x_c_HCC+L11*x_c_PLT+M11*x_c_SVRn+N11*x_c_SVRcc+O11*x_c_LT+P11*x_c_LT1 -> 3.403395e+08 | AB11: =C11*x_c_DAA -> 109976320 | AC11: =C11*x_c_MON -> 27857108 | AD11: =D11*(1-x_testy) -> 0 | AE11: =E11*(1-x_testy) -> 0 | AF11: =F11*x_NAV -> 0 | AG11: =G11*x_FIX*(1-x_testy) -> 0 | AH11: =x_z_F*U11+(1-x_AGRI)*x_EMP*x_WLOSS*(x_PEN_K74*Q11+x_PEN_C22*R11) -> 32810250 | AI11: =x_AGRI*x_EMP*x_WLOSS*(x_PEN_K74*Q11+x_PEN_C22*R11) -> 1939482.4 | AJ11: =x_EMP*x_WAGE*(x_WLOSS*(Q11+R11)+S11)+U11*x_ABS_D*x_WAGE/365 -> 6.4018359e+08 | AK11: =AJ11*x_R_FUS -> 2.0255409e+08 | AL11: =AJ11*x_R_NFZ -> 49717297 | AM11: =AJ11*x_R_PIT -> 42562077 | AN11: =AJ11*x_R_FP -> 16324681 | AO11: =AA11+AB11+AC11+AD11+AF11 -> 4.7817293e+08 | AP11: =AO11+AE11+AG11+AH11+AI11+AK11+AL11+AM11+AN11 -> 8.240808e+08 | AQ11: =AO11+AE11+AG11+AJ11 -> 1.1183565e+09 | AR11: =AB11+AC11+AD11+AF11 -> 1.3783343e+08 | AS11: =AR11+AE11+AG11 -> 1.3783343e+08
A12: 2035 | B12: 9 | C12: 4832 | D12: 0 | E12: 0 | F12: 0 | G12: 0 | H12: 2204.561 | I12: 309.58 | J12: 1746.23 | K12: 3002.435 | L12: 1382.527 | M12: 41297.973 | N12: 4387.381 | O12: 98.276 | P12: 97.359 | Q12: 2418.985 | R12: 2283.662 | S12: 6448.861 | T12: 2514.141 | U12: 1716.052 | V12: 124825.78 | W12: 352.763 | X12: 923.239 | Y12: 98.276 | Z12: 1057.386 | AA12: =H12*x_c_F+I12*x_c_CC+J12*x_c_DC+K12*x_c_HCC+L12*x_c_PLT+M12*x_c_SVRn+N12*x_c_SVRcc+O12*x_c_LT+P12*x_c_LT1 -> 3.4811925e+08 | AB12: =C12*x_c_DAA -> 109976320 | AC12: =C12*x_c_MON -> 27857108 | AD12: =D12*(1-x_testy) -> 0 | AE12: =E12*(1-x_testy) -> 0 | AF12: =F12*x_NAV -> 0 | AG12: =G12*x_FIX*(1-x_testy) -> 0 | AH12: =x_z_F*U12+(1-x_AGRI)*x_EMP*x_WLOSS*(x_PEN_K74*Q12+x_PEN_C22*R12) -> 33689196 | AI12: =x_AGRI*x_EMP*x_WLOSS*(x_PEN_K74*Q12+x_PEN_C22*R12) -> 1993594.3 | AJ12: =x_EMP*x_WAGE*(x_WLOSS*(Q12+R12)+S12)+U12*x_ABS_D*x_WAGE/365 -> 7.0879848e+08 | AK12: =AJ12*x_R_FUS -> 2.2426384e+08 | AL12: =AJ12*x_R_NFZ -> 55045999 | AM12: =AJ12*x_R_PIT -> 47123881 | AN12: =AJ12*x_R_FP -> 18074361 | AO12: =AA12+AB12+AC12+AD12+AF12 -> 4.8595268e+08 | AP12: =AO12+AE12+AG12+AH12+AI12+AK12+AL12+AM12+AN12 -> 8.6614355e+08 | AQ12: =AO12+AE12+AG12+AJ12 -> 1.1947512e+09 | AR12: =AB12+AC12+AD12+AF12 -> 1.3783343e+08 | AS12: =AR12+AE12+AG12 -> 1.3783343e+08
A13: 2036 | B13: 10 | C13: 4832 | D13: 0 | E13: 0 | F13: 0 | G13: 0 | H13: 2197.101 | I13: 315.372 | J13: 1774.721 | K13: 3045.991 | L13: 1372.329 | M13: 44757.851 | N13: 4814.782 | O13: 99.888 | P13: 99.082 | Q13: 2469.528 | R13: 2352.49 | S13: 7220.787 | T13: 2512.473 | U13: 1744.048 | V13: 126144.52 | W13: 355.61 | X13: 927.665 | Y13: 99.888 | Z13: 1072.677 | AA13: =H13*x_c_F+I13*x_c_CC+J13*x_c_DC+K13*x_c_HCC+L13*x_c_PLT+M13*x_c_SVRn+N13*x_c_SVRcc+O13*x_c_LT+P13*x_c_LT1 -> 3.5498212e+08 | AB13: =C13*x_c_DAA -> 109976320 | AC13: =C13*x_c_MON -> 27857108 | AD13: =D13*(1-x_testy) -> 0 | AE13: =E13*(1-x_testy) -> 0 | AF13: =F13*x_NAV -> 0 | AG13: =G13*x_FIX*(1-x_testy) -> 0 | AH13: =x_z_F*U13+(1-x_AGRI)*x_EMP*x_WLOSS*(x_PEN_K74*Q13+x_PEN_C22*R13) -> 34521272 | AI13: =x_AGRI*x_EMP*x_WLOSS*(x_PEN_K74*Q13+x_PEN_C22*R13) -> 2044788.5 | AJ13: =x_EMP*x_WAGE*(x_WLOSS*(Q13+R13)+S13)+U13*x_ABS_D*x_WAGE/365 -> 7.786027e+08 | AK13: =AJ13*x_R_FUS -> 2.4634989e+08 | AL13: =AJ13*x_R_NFZ -> 60467064 | AM13: =AJ13*x_R_PIT -> 51764757 | AN13: =AJ13*x_R_FP -> 19854369 | AO13: =AA13+AB13+AC13+AD13+AF13 -> 4.9281555e+08 | AP13: =AO13+AE13+AG13+AH13+AI13+AK13+AL13+AM13+AN13 -> 9.0781769e+08 | AQ13: =AO13+AE13+AG13+AJ13 -> 1.2714182e+09 | AR13: =AB13+AC13+AD13+AF13 -> 1.3783343e+08 | AS13: =AR13+AE13+AG13 -> 1.3783343e+08
A14: 2037 | B14: 11 | C14: 4832 | D14: 0 | E14: 0 | F14: 0 | G14: 0 | H14: 2191.273 | I14: 319.523 | J14: 1798.289 | K14: 3076.825 | L14: 1362.555 | M14: 48135.673 | N14: 5229.543 | O14: 101.2 | P14: 100.544 | Q14: 2518.59 | R14: 2413.799 | S14: 8005.884 | T14: 2510.796 | U14: 1770.744 | V14: 127445.76 | W14: 356.58 | X14: 927.774 | Y14: 101.2 | Z14: 1084.115 | AA14: =H14*x_c_F+I14*x_c_CC+J14*x_c_DC+K14*x_c_HCC+L14*x_c_PLT+M14*x_c_SVRn+N14*x_c_SVRcc+O14*x_c_LT+P14*x_c_LT1 -> 3.607654e+08 | AB14: =C14*x_c_DAA -> 109976320 | AC14: =C14*x_c_MON -> 27857108 | AD14: =D14*(1-x_testy) -> 0 | AE14: =E14*(1-x_testy) -> 0 | AF14: =F14*x_NAV -> 0 | AG14: =G14*x_FIX*(1-x_testy) -> 0 | AH14: =x_z_F*U14+(1-x_AGRI)*x_EMP*x_WLOSS*(x_PEN_K74*Q14+x_PEN_C22*R14) -> 35290368 | AI14: =x_AGRI*x_EMP*x_WLOSS*(x_PEN_K74*Q14+x_PEN_C22*R14) -> 2091996.5 | AJ14: =x_EMP*x_WAGE*(x_WLOSS*(Q14+R14)+S14)+U14*x_ABS_D*x_WAGE/365 -> 8.4923148e+08 | AK14: =AJ14*x_R_FUS -> 2.6869684e+08 | AL14: =AJ14*x_R_NFZ -> 65952166 | AM14: =AJ14*x_R_PIT -> 56460453 | AN14: =AJ14*x_R_FP -> 21655403 | AO14: =AA14+AB14+AC14+AD14+AF14 -> 4.9859882e+08 | AP14: =AO14+AE14+AG14+AH14+AI14+AK14+AL14+AM14+AN14 -> 9.4874605e+08 | AQ14: =AO14+AE14+AG14+AJ14 -> 1.3478303e+09 | AR14: =AB14+AC14+AD14+AF14 -> 1.3783343e+08 | AS14: =AR14+AE14+AG14 -> 1.3783343e+08
... A52: 2075 | B52: 49 | C52: 4832 | D52: 0 | E52: 0 | F52: 0 | G52: 0 | H52: 2269.693 | I52: 206.878 | J52: 1065.879 | K52: 1833.318 | L52: 667.348 | M52: 144449.32 | N52: 7942.268 | O52: 60.507 | P52: 60.633 | Q52: 627.338 | R52: 925.699 | S52: 2570.878 | T52: 2476.572 | U52: 1830.32 | V52: 179762.59 | W52: 196.568 | X52: 532.393 | Y52: 60.507 | Z52: 642.926 | AA52: =H52*x_c_F+I52*x_c_CC+J52*x_c_DC+K52*x_c_HCC+L52*x_c_PLT+M52*x_c_SVRn+N52*x_c_SVRcc+O52*x_c_LT+P52*x_c_LT1 -> 2.9744688e+08 | AB52: =C52*x_c_DAA -> 109976320 | AC52: =C52*x_c_MON -> 27857108 | AD52: =D52*(1-x_testy) -> 0 | AE52: =E52*(1-x_testy) -> 0 | AF52: =F52*x_NAV -> 0 | AG52: =G52*x_FIX*(1-x_testy) -> 0 | AH52: =x_z_F*U52+(1-x_AGRI)*x_EMP*x_WLOSS*(x_PEN_K74*Q52+x_PEN_C22*R52) -> 13864406 | AI52: =x_AGRI*x_EMP*x_WLOSS*(x_PEN_K74*Q52+x_PEN_C22*R52) -> 667685.76 | AJ52: =x_EMP*x_WAGE*(x_WLOSS*(Q52+R52)+S52)+U52*x_ABS_D*x_WAGE/365 -> 2.7540393e+08 | AK52: =AJ52*x_R_FUS -> 87137803 | AL52: =AJ52*x_R_NFZ -> 21388145 | AM52: =AJ52*x_R_PIT -> 18310003 | AN52: =AJ52*x_R_FP -> 7022800.2 | AO52: =AA52+AB52+AC52+AD52+AF52 -> 4.352803e+08 | AP52: =AO52+AE52+AG52+AH52+AI52+AK52+AL52+AM52+AN52 -> 5.8367115e+08 | AQ52: =AO52+AE52+AG52+AJ52 -> 7.1068423e+08 | AR52: =AB52+AC52+AD52+AF52 -> 1.3783343e+08 | AS52: =AR52+AE52+AG52 -> 1.3783343e+08

Sheet L_S0
A1: S0: Brak leczenia (zaniechanie) – liczebności (silnik, wartości) i koszty (formuły), zł/rok, niezdyskontowane. Szacunek modelu.
A2: rok | B2: t | C2: treated | D2: NFZ_diag | E2: MZ_SW | F2: nNAV | G2: FIXon | H2: cF03 | I2: cF4 | J2: cDC | K2: cHCC | L2: cPLT | M2: cSVn | N2: cSVc | O2: cLTn | P2: cLT1 | Q2: wAdv | R2: wHCC | S2: wGH | T2: cAbs | U2: cAbsW | V2: QALY | W2: newDC | X2: newHCC | Y2: LT | Z2: liverD | AA2: NFZ_med | AB2: NFZ_DAA | AC2: NFZ_mon | AD2: NFZ_diag_k | AE2: MZ_SW_k | AF2: NAV_k | AG2: FIX_k | AH2: ZUS | AI2: KRUS | AJ2: lostw | AK2: lost_FUS | AL2: lost_NFZ | AM2: lost_PIT | AN2: lost_FP | AO2: NFZ | AP2: PUBLIC | AQ2: SOCIETAL | AR2: INV_NFZ | AS2: INV_PUB
A3: 2026 | B3: 0 | C3: 0 | D3: 0 | E3: 0 | F3: 0 | G3: 0 | H3: 5509.246 | I3: 498.943 | J3: 1582.633 | K3: 2532.748 | L3: 1540.438 | M3: 0 | N3: 0 | O3: 89.046 | P3: 44.523 | Q3: 2136.942 | R3: 1708.668 | S3: 312.377 | T3: 6008.189 | U3: 3342.327 | V3: 113001.84 | W3: 272.301 | X3: 727.402 | Y3: 89.046 | Z3: 922.327 | AA3: =H3*x_c_F+I3*x_c_CC+J3*x_c_DC+K3*x_c_HCC+L3*x_c_PLT+M3*x_c_SVRn+N3*x_c_SVRcc+O3*x_c_LT+P3*x_c_LT1 -> 2.8847003e+08 | AB3: =C3*x_c_DAA -> 0 | AC3: =C3*x_c_MON -> 0 | AD3: =D3*(1-x_testy) -> 0 | AE3: =E3*(1-x_testy) -> 0 | AF3: =F3*x_NAV -> 0 | AG3: =G3*x_FIX*(1-x_testy) -> 0 | AH3: =x_z_F*U3+(1-x_AGRI)*x_EMP*x_WLOSS*(x_PEN_K74*Q3+x_PEN_C22*R3) -> 31405570 | AI3: =x_AGRI*x_EMP*x_WLOSS*(x_PEN_K74*Q3+x_PEN_C22*R3) -> 1621654.1 | AJ3: =x_EMP*x_WAGE*(x_WLOSS*(Q3+R3)+S3)+U3*x_ABS_D*x_WAGE/365 -> 1.6232375e+08 | AK3: =AJ3*x_R_FUS -> 51359234 | AL3: =AJ3*x_R_NFZ -> 12606225 | AM3: =AJ3*x_R_PIT -> 10791960 | AN3: =AJ3*x_R_FP -> 4139255.6 | AO3: =AA3+AB3+AC3+AD3+AF3 -> 2.8847003e+08 | AP3: =AO3+AE3+AG3+AH3+AI3+AK3+AL3+AM3+AN3 -> 4.0039393e+08 | AQ3: =AO3+AE3+AG3+AJ3 -> 4.5079378e+08 | AR3: =AB3+AC3+AD3+AF3 -> 0 | AS3: =AR3+AE3+AG3 -> 0
A4: 2027 | B4: 1 | C4: 0 | D4: 0 | E4: 0 | F4: 0 | G4: 0 | H4: 9065.783 | I4: 870.396 | J4: 1577.392 | K4: 2552.872 | L4: 1489.389 | M4: 0 | N4: 0 | O4: 88.331 | P4: 88.689 | Q4: 2147.277 | R4: 1738.504 | S4: 941.663 | T4: 9936.179 | U4: 5676.044 | V4: 113838.04 | W4: 289.562 | X4: 776.664 | Y4: 88.331 | Z4: 930.689 | AA4: =H4*x_c_F+I4*x_c_CC+J4*x_c_DC+K4*x_c_HCC+L4*x_c_PLT+M4*x_c_SVRn+N4*x_c_SVRcc+O4*x_c_LT+P4*x_c_LT1 -> 3.0241239e+08 | AB4: =C4*x_c_DAA -> 0 | AC4: =C4*x_c_MON -> 0 | AD4: =D4*(1-x_testy) -> 0 | AE4: =E4*(1-x_testy) -> 0 | AF4: =F4*x_NAV -> 0 | AG4: =G4*x_FIX*(1-x_testy) -> 0 | AH4: =x_z_F*U4+(1-x_AGRI)*x_EMP*x_WLOSS*(x_PEN_K74*Q4+x_PEN_C22*R4) -> 36469595 | AI4: =x_AGRI*x_EMP*x_WLOSS*(x_PEN_K74*Q4+x_PEN_C22*R4) -> 1639244.2 | AJ4: =x_EMP*x_WAGE*(x_WLOSS*(Q4+R4)+S4)+U4*x_ABS_D*x_WAGE/365 -> 2.2414689e+08 | AK4: =AJ4*x_R_FUS -> 70920076 | AL4: =AJ4*x_R_NFZ -> 17407472 | AM4: =AJ4*x_R_PIT -> 14902221 | AN4: =AJ4*x_R_FP -> 5715745.7 | AO4: =AA4+AB4+AC4+AD4+AF4 -> 3.0241239e+08 | AP4: =AO4+AE4+AG4+AH4+AI4+AK4+AL4+AM4+AN4 -> 4.4946675e+08 | AQ4: =AO4+AE4+AG4+AJ4 -> 5.2655928e+08 | AR4: =AB4+AC4+AD4+AF4 -> 0 | AS4: =AR4+AE4+AG4 -> 0
A5: 2028 | B5: 2 | C5: 0 | D5: 0 | E5: 0 | F5: 0 | G5: 0 | H5: 12524.131 | I5: 1282.177 | J5: 1590.922 | K5: 2617.33 | L5: 1475.935 | M5: 0 | N5: 0 | O5: 88.855 | P5: 88.593 | Q5: 2168.208 | R5: 1802.923 | S5: 1581.493 | T5: 13806.308 | U5: 8090.74 | V5: 114734.08 | W5: 309.818 | X5: 830.282 | Y5: 88.855 | Z5: 941.777 | AA5: =H5*x_c_F+I5*x_c_CC+J5*x_c_DC+K5*x_c_HCC+L5*x_c_PLT+M5*x_c_SVRn+N5*x_c_SVRcc+O5*x_c_LT+P5*x_c_LT1 -> 3.1892487e+08 | AB5: =C5*x_c_DAA -> 0 | AC5: =C5*x_c_MON -> 0 | AD5: =D5*(1-x_testy) -> 0 | AE5: =E5*(1-x_testy) -> 0 | AF5: =F5*x_NAV -> 0 | AG5: =G5*x_FIX*(1-x_testy) -> 0 | AH5: =x_z_F*U5+(1-x_AGRI)*x_EMP*x_WLOSS*(x_PEN_K74*Q5+x_PEN_C22*R5) -> 42000247 | AI5: =x_AGRI*x_EMP*x_WLOSS*(x_PEN_K74*Q5+x_PEN_C22*R5) -> 1676673 | AJ5: =x_EMP*x_WAGE*(x_WLOSS*(Q5+R5)+S5)+U5*x_ABS_D*x_WAGE/365 -> 2.8858566e+08 | AK5: =AJ5*x_R_FUS -> 91308504 | AL5: =AJ5*x_R_NFZ -> 22411851 | AM5: =AJ5*x_R_PIT -> 19186379 | AN5: =AJ5*x_R_FP -> 7358934.4 | AO5: =AA5+AB5+AC5+AD5+AF5 -> 3.1892487e+08 | AP5: =AO5+AE5+AG5+AH5+AI5+AK5+AL5+AM5+AN5 -> 5.0286746e+08 | AQ5: =AO5+AE5+AG5+AJ5 -> 6.0751053e+08 | AR5: =AB5+AC5+AD5+AF5 -> 0 | AS5: =AR5+AE5+AG5 -> 0
A6: 2029 | B6: 3 | C6: 0 | D6: 0 | E6: 0 | F6: 0 | G6: 0 | H6: 15886.581 | I6: 1736.309 | J6: 1622.319 | K6: 2716.741 | L6: 1462.036 | M6: 0 | N6: 0 | O6: 90.506 | P6: 89.681 | Q6: 2204.278 | R6: 1895.414 | S6: 2238.147 | T6: 17622.891 | U6: 10577.531 | V6: 115663.72 | W6: 332.072 | X6: 886.439 | Y6: 90.506 | Z6: 965.574 | AA6: =H6*x_c_F+I6*x_c_CC+J6*x_c_DC+K6*x_c_HCC+L6*x_c_PLT+M6*x_c_SVRn+N6*x_c_SVRcc+O6*x_c_LT+P6*x_c_LT1 -> 3.3833192e+08 | AB6: =C6*x_c_DAA -> 0 | AC6: =C6*x_c_MON -> 0 | AD6: =D6*(1-x_testy) -> 0 | AE6: =E6*(1-x_testy) -> 0 | AF6: =F6*x_NAV -> 0 | AG6: =G6*x_FIX*(1-x_testy) -> 0 | AH6: =x_z_F*U6+(1-x_AGRI)*x_EMP*x_WLOSS*(x_PEN_K74*Q6+x_PEN_C22*R6) -> 47962077 | AI6: =x_AGRI*x_EMP*x_WLOSS*(x_PEN_K74*Q6+x_PEN_C22*R6) -> 1732804.9 | AJ6: =x_EMP*x_WAGE*(x_WLOSS*(Q6+R6)+S6)+U6*x_ABS_D*x_WAGE/365 -> 3.5608499e+08 | AK6: =AJ6*x_R_FUS -> 1.1266529e+08 | AL6: =AJ6*x_R_NFZ -> 27653917 | AM6: =AJ6*x_R_PIT -> 23674016 | AN6: =AJ6*x_R_FP -> 9080167.3 | AO6: =AA6+AB6+AC6+AD6+AF6 -> 3.3833192e+08 | AP6: =AO6+AE6+AG6+AH6+AI6+AK6+AL6+AM6+AN6 -> 5.6110019e+08 | AQ6: =AO6+AE6+AG6+AJ6 -> 6.9441691e+08 | AR6: =AB6+AC6+AD6+AF6 -> 0 | AS6: =AR6+AE6+AG6 -> 0
A7: 2030 | B7: 4 | C7: 0 | D7: 0 | E7: 0 | F7: 0 | G7: 0 | H7: 19156.208 | I7: 2231.599 | J7: 1669.888 | K7: 2842.689 | L7: 1448.65 | M7: 0 | N7: 0 | O7: 93.142 | P7: 91.824 | Q7: 2255.107 | R7: 2010.229 | S7: 2920.285 | T7: 21387.807 | U7: 13127.598 | V7: 116610.46 | W7: 355.49 | X7: 943.617 | Y7: 93.142 | Z7: 999.539 | AA7: =H7*x_c_F+I7*x_c_CC+J7*x_c_DC+K7*x_c_HCC+L7*x_c_PLT+M7*x_c_SVRn+N7*x_c_SVRcc+O7*x_c_LT+P7*x_c_LT1 -> 3.60052e+08 | AB7: =C7*x_c_DAA -> 0 | AC7: =C7*x_c_MON -> 0 | AD7: =D7*(1-x_testy) -> 0 | AE7: =E7*(1-x_testy) -> 0 | AF7: =F7*x_NAV -> 0 | AG7: =G7*x_FIX*(1-x_testy) -> 0 | AH7: =x_z_F*U7+(1-x_AGRI)*x_EMP*x_WLOSS*(x_PEN_K74*Q7+x_PEN_C22*R7) -> 54295378 | AI7: =x_AGRI*x_EMP*x_WLOSS*(x_PEN_K74*Q7+x_PEN_C22*R7) -> 1804891.6 | AJ7: =x_EMP*x_WAGE*(x_WLOSS*(Q7+R7)+S7)+U7*x_ABS_D*x_WAGE/365 -> 4.2715675e+08 | AK7: =AJ7*x_R_FUS -> 1.3515239e+08 | AL7: =AJ7*x_R_NFZ -> 33173420 | AM7: =AJ7*x_R_PIT -> 28399163 | AN7: =AJ7*x_R_FP -> 10892497 | AO7: =AA7+AB7+AC7+AD7+AF7 -> 3.60052e+08 | AP7: =AO7+AE7+AG7+AH7+AI7+AK7+AL7+AM7+AN7 -> 6.2376975e+08 | AQ7: =AO7+AE7+AG7+AJ7 -> 7.8720875e+08 | AR7: =AB7+AC7+AD7+AF7 -> 0 | AS7: =AR7+AE7+AG7 -> 0
A8: 2031 | B8: 5 | C8: 0 | D8: 0 | E8: 0 | F8: 0 | G8: 0 | H8: 22336.98 | I8: 2764.61 | J8: 1731.46 | K8: 2987.771 | L8: 1436.598 | M8: 0 | N8: 0 | O8: 96.607 | P8: 94.875 | Q8: 2319.901 | R8: 2142.36 | S8: 3634.83 | T8: 25101.589 | U8: 15732.575 | V8: 117562.58 | W8: 379.386 | X8: 1000.581 | Y8: 96.607 | Z8: 1041.337 | AA8: =H8*x_c_F+I8*x_c_CC+J8*x_c_DC+K8*x_c_HCC+L8*x_c_PLT+M8*x_c_SVRn+N8*x_c_SVRcc+O8*x_c_LT+P8*x_c_LT1 -> 3.8353921e+08 | AB8: =C8*x_c_DAA -> 0 | AC8: =C8*x_c_MON -> 0 | AD8: =D8*(1-x_testy) -> 0 | AE8: =E8*(1-x_testy) -> 0 | AF8: =F8*x_NAV -> 0 | AG8: =G8*x_FIX*(1-x_testy) -> 0 | AH8: =x_z_F*U8+(1-x_AGRI)*x_EMP*x_WLOSS*(x_PEN_K74*Q8+x_PEN_C22*R8) -> 60943939 | AI8: =x_AGRI*x_EMP*x_WLOSS*(x_PEN_K74*Q8+x_PEN_C22*R8) -> 1890354.5 | AJ8: =x_EMP*x_WAGE*(x_WLOSS*(Q8+R8)+S8)+U8*x_ABS_D*x_WAGE/365 -> 5.021767e+08 | AK8: =AJ8*x_R_FUS -> 1.5888871e+08 | AL8: =AJ8*x_R_NFZ -> 38999545 | AM8: =AJ8*x_R_PIT -> 33386803 | AN8: =AJ8*x_R_FP -> 12805506 | AO8: =AA8+AB8+AC8+AD8+AF8 -> 3.8353921e+08 | AP8: =AO8+AE8+AG8+AH8+AI8+AK8+AL8+AM8+AN8 -> 6.9045406e+08 | AQ8: =AO8+AE8+AG8+AJ8 -> 8.8571591e+08 | AR8: =AB8+AC8+AD8+AF8 -> 0 | AS8: =AR8+AE8+AG8 -> 0
A9: 2032 | B9: 6 | C9: 0 | D9: 0 | E9: 0 | F9: 0 | G9: 0 | H9: 25432.989 | I9: 3330.304 | J9: 1804.567 | K9: 3145.499 | L9: 1426.504 | M9: 0 | N9: 0 | O9: 100.735 | P9: 98.671 | Q9: 2397.549 | R9: 2287.456 | S9: 4387.053 | T9: 28763.293 | U9: 18384.376 | V9: 118509.01 | W9: 403.184 | X9: 1056.289 | Y9: 100.735 | Z9: 1088.803 | AA9: =H9*x_c_F+I9*x_c_CC+J9*x_c_DC+K9*x_c_HCC+L9*x_c_PLT+M9*x_c_SVRn+N9*x_c_SVRcc+O9*x_c_LT+P9*x_c_LT1 -> 4.0828099e+08 | AB9: =C9*x_c_DAA -> 0 | AC9: =C9*x_c_MON -> 0 | AD9: =D9*(1-x_testy) -> 0 | AE9: =E9*(1-x_testy) -> 0 | AF9: =F9*x_NAV -> 0 | AG9: =G9*x_FIX*(1-x_testy) -> 0 | AH9: =x_z_F*U9+(1-x_AGRI)*x_EMP*x_WLOSS*(x_PEN_K74*Q9+x_PEN_C22*R9) -> 67854710 | AI9: =x_AGRI*x_EMP*x_WLOSS*(x_PEN_K74*Q9+x_PEN_C22*R9) -> 1986786 | AJ9: =x_EMP*x_WAGE*(x_WLOSS*(Q9+R9)+S9)+U9*x_ABS_D*x_WAGE/365 -> 5.8139174e+08 | AK9: =AJ9*x_R_FUS -> 1.8395235e+08 | AL9: =AJ9*x_R_NFZ -> 45151464 | AM9: =AJ9*x_R_PIT -> 38653350 | AN9: =AJ9*x_R_FP -> 14825489 | AO9: =AA9+AB9+AC9+AD9+AF9 -> 4.0828099e+08 | AP9: =AO9+AE9+AG9+AH9+AI9+AK9+AL9+AM9+AN9 -> 7.6070513e+08 | AQ9: =AO9+AE9+AG9+AJ9 -> 9.8967273e+08 | AR9: =AB9+AC9+AD9+AF9 -> 0 | AS9: =AR9+AE9+AG9 -> 0
A10: 2033 | B10: 7 | C10: 0 | D10: 0 | E10: 0 | F10: 0 | G10: 0 | H10: 28448.565 | I10: 3922.675 | J10: 1886.63 | K10: 3310.279 | L10: 1418.816 | M10: 0 | N10: 0 | O10: 105.362 | P10: 103.048 | Q10: 2486.734 | R10: 2441.78 | S10: 5180.749 | T10: 32371.24 | U10: 21075.291 | V10: 119440.68 | W10: 426.424 | X10: 1109.922 | Y10: 105.362 | Z10: 1140.041 | AA10: =H10*x_c_F+I10*x_c_CC+J10*x_c_DC+K10*x_c_HCC+L10*x_c_PLT+M10*x_c_SVRn+N10*x_c_SVRcc+O10*x_c_LT+P10*x_c_LT1 -> 4.3380952e+08 | AB10: =C10*x_c_DAA -> 0 | AC10: =C10*x_c_MON -> 0 | AD10: =D10*(1-x_testy) -> 0 | AE10: =E10*(1-x_testy) -> 0 | AF10: =F10*x_NAV -> 0 | AG10: =G10*x_FIX*(1-x_testy) -> 0 | AH10: =x_z_F*U10+(1-x_AGRI)*x_EMP*x_WLOSS*(x_PEN_K74*Q10+x_PEN_C22*R10) -> 74978373 | AI10: =x_AGRI*x_EMP*x_WLOSS*(x_PEN_K74*Q10+x_PEN_C22*R10) -> 2091974.1 | AJ10: =x_EMP*x_WAGE*(x_WLOSS*(Q10+R10)+S10)+U10*x_ABS_D*x_WAGE/365 -> 6.6493735e+08 | AK10: =AJ10*x_R_FUS -> 2.1038618e+08 | AL10: =AJ10*x_R_NFZ -> 51639700 | AM10: =AJ10*x_R_PIT -> 44207811 | AN10: =AJ10*x_R_FP -> 16955903 | AO10: =AA10+AB10+AC10+AD10+AF10 -> 4.3380952e+08 | AP10: =AO10+AE10+AG10+AH10+AI10+AK10+AL10+AM10+AN10 -> 8.3406946e+08 | AQ10: =AO10+AE10+AG10+AJ10 -> 1.0987469e+09 | AR10: =AB10+AC10+AD10+AF10 -> 0 | AS10: =AR10+AE10+AG10 -> 0
A11: 2034 | B11: 8 | C11: 0 | D11: 0 | E11: 0 | F11: 0 | G11: 0 | H11: 31387.97 | I11: 4535.147 | J11: 1975.074 | K11: 3477.337 | L11: 1413.799 | M11: 0 | N11: 0 | O11: 110.329 | P11: 107.846 | Q11: 2586.013 | R11: 2602.146 | S11: 6018.334 | T11: 35923.118 | U11: 23797.9 | V11: 120350.01 | W11: 448.725 | X11: 1160.8 | Y11: 110.329 | Z11: 1193.323 | AA11: =H11*x_c_F+I11*x_c_CC+J11*x_c_DC+K11*x_c_HCC+L11*x_c_PLT+M11*x_c_SVRn+N11*x_c_SVRcc+O11*x_c_LT+P11*x_c_LT1 -> 4.5970142e+08 | AB11: =C11*x_c_DAA -> 0 | AC11: =C11*x_c_MON -> 0 | AD11: =D11*(1-x_testy) -> 0 | AE11: =E11*(1-x_testy) -> 0 | AF11: =F11*x_NAV -> 0 | AG11: =G11*x_FIX*(1-x_testy) -> 0 | AH11: =x_z_F*U11+(1-x_AGRI)*x_EMP*x_WLOSS*(x_PEN_K74*Q11+x_PEN_C22*R11) -> 82269215 | AI11: =x_AGRI*x_EMP*x_WLOSS*(x_PEN_K74*Q11+x_PEN_C22*R11) -> 2203905.3 | AJ11: =x_EMP*x_WAGE*(x_WLOSS*(Q11+R11)+S11)+U11*x_ABS_D*x_WAGE/365 -> 7.5284621e+08 | AK11: =AJ11*x_R_FUS -> 2.3820054e+08 | AL11: =AJ11*x_R_NFZ -> 58466790 | AM11: =AJ11*x_R_PIT -> 50052359 | AN11: =AJ11*x_R_FP -> 19197578 | AO11: =AA11+AB11+AC11+AD11+AF11 -> 4.5970142e+08 | AP11: =AO11+AE11+AG11+AH11+AI11+AK11+AL11+AM11+AN11 -> 9.1009181e+08 | AQ11: =AO11+AE11+AG11+AJ11 -> 1.2125476e+09 | AR11: =AB11+AC11+AD11+AF11 -> 0 | AS11: =AR11+AE11+AG11 -> 0
A12: 2035 | B12: 9 | C12: 0 | D12: 0 | E12: 0 | F12: 0 | G12: 0 | H12: 34255.495 | I12: 5160.983 | J12: 2067.424 | K12: 3642.667 | L12: 1411.557 | M12: 0 | N12: 0 | O12: 115.493 | P12: 112.911 | Q12: 2693.882 | R12: 2765.866 | S12: 6900.983 | T12: 39416.478 | U12: 26545.074 | V12: 121231.05 | W12: 469.801 | X12: 1208.437 | Y12: 115.493 | Z12: 1247.2 | AA12: =H12*x_c_F+I12*x_c_CC+J12*x_c_DC+K12*x_c_HCC+L12*x_c_PLT+M12*x_c_SVRn+N12*x_c_SVRcc+O12*x_c_LT+P12*x_c_LT1 -> 4.8558325e+08 | AB12: =C12*x_c_DAA -> 0 | AC12: =C12*x_c_MON -> 0 | AD12: =D12*(1-x_testy) -> 0 | AE12: =E12*(1-x_testy) -> 0 | AF12: =F12*x_NAV -> 0 | AG12: =G12*x_FIX*(1-x_testy) -> 0 | AH12: =x_z_F*U12+(1-x_AGRI)*x_EMP*x_WLOSS*(x_PEN_K74*Q12+x_PEN_C22*R12) -> 89685156 | AI12: =x_AGRI*x_EMP*x_WLOSS*(x_PEN_K74*Q12+x_PEN_C22*R12) -> 2320767.3 | AJ12: =x_EMP*x_WAGE*(x_WLOSS*(Q12+R12)+S12)+U12*x_ABS_D*x_WAGE/365 -> 8.4506036e+08 | AK12: =AJ12*x_R_FUS -> 2.673771e+08 | AL12: =AJ12*x_R_NFZ -> 65628232 | AM12: =AJ12*x_R_PIT -> 56183140 | AN12: =AJ12*x_R_FP -> 21549039 | AO12: =AA12+AB12+AC12+AD12+AF12 -> 4.8558325e+08 | AP12: =AO12+AE12+AG12+AH12+AI12+AK12+AL12+AM12+AN12 -> 9.8832668e+08 | AQ12: =AO12+AE12+AG12+AJ12 -> 1.3306436e+09 | AR12: =AB12+AC12+AD12+AF12 -> 0 | AS12: =AR12+AE12+AG12 -> 0
A13: 2036 | B13: 10 | C13: 0 | D13: 0 | E13: 0 | F13: 0 | G13: 0 | H13: 37055.021 | I13: 5793.425 | J13: 2161.34 | K13: 3802.909 | L13: 1412.022 | M13: 0 | N13: 0 | O13: 120.712 | P13: 118.103 | Q13: 2808.825 | R13: 2930.691 | S13: 7828.732 | T13: 42848.446 | U13: 29310 | V13: 122078.4 | W13: 489.41 | X13: 1252.407 | Y13: 120.712 | Z13: 1300.336 | AA13: =H13*x_c_F+I13*x_c_CC+J13*x_c_DC+K13*x_c_HCC+L13*x_c_PLT+M13*x_c_SVRn+N13*x_c_SVRcc+O13*x_c_LT+P13*x_c_LT1 -> 5.1111886e+08 | AB13: =C13*x_c_DAA -> 0 | AC13: =C13*x_c_MON -> 0 | AD13: =D13*(1-x_testy) -> 0 | AE13: =E13*(1-x_testy) -> 0 | AF13: =F13*x_NAV -> 0 | AG13: =G13*x_FIX*(1-x_testy) -> 0 | AH13: =x_z_F*U13+(1-x_AGRI)*x_EMP*x_WLOSS*(x_PEN_K74*Q13+x_PEN_C22*R13) -> 97187698 | AI13: =x_AGRI*x_EMP*x_WLOSS*(x_PEN_K74*Q13+x_PEN_C22*R13) -> 2440941 | AJ13: =x_EMP*x_WAGE*(x_WLOSS*(Q13+R13)+S13)+U13*x_ABS_D*x_WAGE/365 -> 9.414396e+08 | AK13: =AJ13*x_R_FUS -> 2.9787149e+08 | AL13: =AJ13*x_R_NFZ -> 73113141 | AM13: =AJ13*x_R_PIT -> 62590834 | AN13: =AJ13*x_R_FP -> 24006710 | AO13: =AA13+AB13+AC13+AD13+AF13 -> 5.1111886e+08 | AP13: =AO13+AE13+AG13+AH13+AI13+AK13+AL13+AM13+AN13 -> 1.0683297e+09 | AQ13: =AO13+AE13+AG13+AJ13 -> 1.4525585e+09 | AR13: =AB13+AC13+AD13+AF13 -> 0 | AS13: =AR13+AE13+AG13 -> 0
A14: 2037 | B14: 11 | C14: 0 | D14: 0 | E14: 0 | F14: 0 | G14: 0 | H14: 39789.75 | I14: 6425.845 | J14: 2254.637 | K14: 3955.249 | L14: 1414.96 | M14: 0 | N14: 0 | O14: 125.864 | P14: 123.288 | Q14: 2929.329 | R14: 3094.738 | S14: 8800.523 | T14: 46215.596 | U14: 32085.95 | V14: 122886.15 | W14: 507.378 | X14: 1292.419 | Y14: 125.864 | Z14: 1351.636 | AA14: =H14*x_c_F+I14*x_c_CC+J14*x_c_DC+K14*x_c_HCC+L14*x_c_PLT+M14*x_c_SVRn+N14*x_c_SVRcc+O14*x_c_LT+P14*x_c_LT1 -> 5.3600979e+08 | AB14: =C14*x_c_DAA -> 0 | AC14: =C14*x_c_MON -> 0 | AD14: =D14*(1-x_testy) -> 0 | AE14: =E14*(1-x_testy) -> 0 | AF14: =F14*x_NAV -> 0 | AG14: =G14*x_FIX*(1-x_testy) -> 0 | AH14: =x_z_F*U14+(1-x_AGRI)*x_EMP*x_WLOSS*(x_PEN_K74*Q14+x_PEN_C22*R14) -> 1.0474104e+08 | AI14: =x_AGRI*x_EMP*x_WLOSS*(x_PEN_K74*Q14+x_PEN_C22*R14) -> 2562974.2 | AJ14: =x_EMP*x_WAGE*(x_WLOSS*(Q14+R14)+S14)+U14*x_ABS_D*x_WAGE/365 -> 1.0417628e+09 | AK14: =AJ14*x_R_FUS -> 3.2961376e+08 | AL14: =AJ14*x_R_NFZ -> 80904343 | AM14: =AJ14*x_R_PIT -> 69260741 | AN14: =AJ14*x_R_FP -> 26564952 | AO14: =AA14+AB14+AC14+AD14+AF14 -> 5.3600979e+08 | AP14: =AO14+AE14+AG14+AH14+AI14+AK14+AL14+AM14+AN14 -> 1.1496576e+09 | AQ14: =AO14+AE14+AG14+AJ14 -> 1.5777726e+09 | AR14: =AB14+AC14+AD14+AF14 -> 0 | AS14: =AR14+AE14+AG14 -> 0
... A52: 2075 | B52: 49 | C52: 0 | D52: 0 | E52: 0 | F52: 0 | G52: 0 | H52: 122772.93 | I52: 26173.44 | J52: 3894.03 | K52: 6428.11 | L52: 1779.538 | M52: 0 | N52: 0 | O52: 215.938 | P52: 214.343 | Q52: 1721.925 | R52: 2600.045 | S52: 6026.219 | T52: 148946.37 | U52: 94187.972 | V52: 150638.68 | W52: 794.766 | X52: 1973.453 | Y52: 215.938 | Z52: 2220.765 | AA52: =H52*x_c_F+I52*x_c_CC+J52*x_c_DC+K52*x_c_HCC+L52*x_c_PLT+M52*x_c_SVRn+N52*x_c_SVRcc+O52*x_c_LT+P52*x_c_LT1 -> 1.1205084e+09 | AB52: =C52*x_c_DAA -> 0 | AC52: =C52*x_c_MON -> 0 | AD52: =D52*(1-x_testy) -> 0 | AE52: =E52*(1-x_testy) -> 0 | AF52: =F52*x_NAV -> 0 | AG52: =G52*x_FIX*(1-x_testy) -> 0 | AH52: =x_z_F*U52+(1-x_AGRI)*x_EMP*x_WLOSS*(x_PEN_K74*Q52+x_PEN_C22*R52) -> 2.2177274e+08 | AI52: =x_AGRI*x_EMP*x_WLOSS*(x_PEN_K74*Q52+x_PEN_C22*R52) -> 1859409.6 | AJ52: =x_EMP*x_WAGE*(x_WLOSS*(Q52+R52)+S52)+U52*x_ABS_D*x_WAGE/365 -> 9.3193037e+08 | AK52: =AJ52*x_R_FUS -> 2.9486277e+08 | AL52: =AJ52*x_R_NFZ -> 72374645 | AM52: =AJ52*x_R_PIT -> 61958621 | AN52: =AJ52*x_R_FP -> 23764225 | AO52: =AA52+AB52+AC52+AD52+AF52 -> 1.1205084e+09 | AP52: =AO52+AE52+AG52+AH52+AI52+AK52+AL52+AM52+AN52 -> 1.7971008e+09 | AQ52: =AO52+AE52+AG52+AJ52 -> 2.0524388e+09 | AR52: =AB52+AC52+AD52+AF52 -> 0 | AS52: =AR52+AE52+AG52 -> 0

Sheet L_I1
A1: I1: Celowane testowanie w szpitalach i laboratoriach (+50 mln zł/rok) – liczebności (silnik, wartości) i koszty (formuły), zł/rok, niezdyskontowane. Szacunek modelu.
A2: rok | B2: t | C2: treated | D2: NFZ_diag | E2: MZ_SW | F2: nNAV | G2: FIXon | H2: cF03 | I2: cF4 | J2: cDC | K2: cHCC | L2: cPLT | M2: cSVn | N2: cSVc | O2: cLTn | P2: cLT1 | Q2: wAdv | R2: wHCC | S2: wGH | T2: cAbs | U2: cAbsW | V2: QALY | W2: newDC | X2: newHCC | Y2: LT | Z2: liverD | AA2: NFZ_med | AB2: NFZ_DAA | AC2: NFZ_mon | AD2: NFZ_diag_k | AE2: MZ_SW_k | AF2: NAV_k | AG2: FIX_k | AH2: ZUS | AI2: KRUS | AJ2: lostw | AK2: lost_FUS | AL2: lost_NFZ | AM2: lost_PIT | AN2: lost_FP | AO2: NFZ | AP2: PUBLIC | AQ2: SOCIETAL | AR2: INV_NFZ | AS2: INV_PUB
A3: 2026 | B3: 0 | C3: 5213.16 | D3: 16666667 | E3: 0 | F3: 0 | G3: 1 | H3: 2581.318 | I3: 231.61 | J3: 1579.158 | K3: 2524.378 | L3: 1540.438 | M3: 7100.45 | N3: 627.462 | O3: 89.046 | P3: 44.523 | Q3: 2134.589 | R3: 1702.999 | S3: 312.377 | T3: 2812.928 | U3: 1558.451 | V3: 113433.47 | W3: 265.352 | X3: 710.662 | Y3: 89.046 | Z3: 922.327 | AA3: =H3*x_c_F+I3*x_c_CC+J3*x_c_DC+K3*x_c_HCC+L3*x_c_PLT+M3*x_c_SVRn+N3*x_c_SVRcc+O3*x_c_LT+P3*x_c_LT1 -> 2.8383355e+08 | AB3: =C3*x_c_DAA -> 1.1865152e+08 | AC3: =C3*x_c_MON -> 30054545 | AD3: =D3*(1-x_testy) -> 16666667 | AE3: =E3*(1-x_testy) -> 0 | AF3: =F3*x_NAV -> 0 | AG3: =G3*x_FIX*(1-x_testy) -> 1223620.5 | AH3: =x_z_F*U3+(1-x_AGRI)*x_EMP*x_WLOSS*(x_PEN_K74*Q3+x_PEN_C22*R3) -> 27685181 | AI3: =x_AGRI*x_EMP*x_WLOSS*(x_PEN_K74*Q3+x_PEN_C22*R3) -> 1618157.1 | AJ3: =x_EMP*x_WAGE*(x_WLOSS*(Q3+R3)+S3)+U3*x_ABS_D*x_WAGE/365 -> 1.5682123e+08 | AK3: =AJ3*x_R_FUS -> 49618236 | AL3: =AJ3*x_R_NFZ -> 12178893 | AM3: =AJ3*x_R_PIT -> 10426130 | AN3: =AJ3*x_R_FP -> 3998941.2 | AO3: =AA3+AB3+AC3+AD3+AF3 -> 4.4920628e+08 | AP3: =AO3+AE3+AG3+AH3+AI3+AK3+AL3+AM3+AN3 -> 5.5595544e+08 | AQ3: =AO3+AE3+AG3+AJ3 -> 6.0725112e+08 | AR3: =AB3+AC3+AD3+AF3 -> 1.6537273e+08 | AS3: =AR3+AE3+AG3 -> 1.6659635e+08
A4: 2027 | B4: 1 | C4: 5576.635 | D4: 33333333 | E4: 0 | F4: 0 | G4: 1 | H4: 2728.1 | I4: 259.776 | J4: 1563.329 | K4: 2519.58 | L4: 1489.389 | M4: 12106.359 | N4: 1093.455 | O4: 87.89 | P4: 88.468 | Q4: 2137.52 | R4: 1715.76 | S4: 939.875 | T4: 2987.876 | U4: 1705.223 | V4: 114593.88 | W4: 274.078 | X4: 738.717 | Y4: 87.89 | Z4: 925.455 | AA4: =H4*x_c_F+I4*x_c_CC+J4*x_c_DC+K4*x_c_HCC+L4*x_c_PLT+M4*x_c_SVRn+N4*x_c_SVRcc+O4*x_c_LT+P4*x_c_LT1 -> 2.8824558e+08 | AB4: =C4*x_c_DAA -> 1.2692421e+08 | AC4: =C4*x_c_MON -> 32150025 | AD4: =D4*(1-x_testy) -> 33333333 | AE4: =E4*(1-x_testy) -> 0 | AF4: =F4*x_NAV -> 0 | AG4: =G4*x_FIX*(1-x_testy) -> 1223620.5 | AH4: =x_z_F*U4+(1-x_AGRI)*x_EMP*x_WLOSS*(x_PEN_K74*Q4+x_PEN_C22*R4) -> 28091794 | AI4: =x_AGRI*x_EMP*x_WLOSS*(x_PEN_K74*Q4+x_PEN_C22*R4) -> 1625088.4 | AJ4: =x_EMP*x_WAGE*(x_WLOSS*(Q4+R4)+S4)+U4*x_ABS_D*x_WAGE/365 -> 2.1126676e+08 | AK4: =AJ4*x_R_FUS -> 66844804 | AL4: =AJ4*x_R_NFZ -> 16407188 | AM4: =AJ4*x_R_PIT -> 14045896 | AN4: =AJ4*x_R_FP -> 5387302.5 | AO4: =AA4+AB4+AC4+AD4+AF4 -> 4.8065315e+08 | AP4: =AO4+AE4+AG4+AH4+AI4+AK4+AL4+AM4+AN4 -> 6.1427884e+08 | AQ4: =AO4+AE4+AG4+AJ4 -> 6.9314353e+08 | AR4: =AB4+AC4+AD4+AF4 -> 1.9240757e+08 | AS4: =AR4+AE4+AG4 -> 1.9363119e+08
A5: 2028 | B5: 2 | C5: 5921.215 | D5: 50000000 | E5: 0 | F5: 0 | G5: 1 | H5: 2782.017 | I5: 281.64 | J5: 1558.707 | K5: 2542.654 | L5: 1475.757 | M5: 17159.078 | N5: 1586.693 | O5: 87.523 | P5: 87.707 | Q5: 2145.234 | R5: 1751.363 | S5: 1572.496 | T5: 3063.657 | U5: 1797.2 | V5: 115841.09 | W5: 283.892 | X5: 766.181 | Y5: 87.523 | Z5: 926.072 | AA5: =H5*x_c_F+I5*x_c_CC+J5*x_c_DC+K5*x_c_HCC+L5*x_c_PLT+M5*x_c_SVRn+N5*x_c_SVRcc+O5*x_c_LT+P5*x_c_LT1 -> 2.9374143e+08 | AB5: =C5*x_c_DAA -> 1.3476685e+08 | AC5: =C5*x_c_MON -> 34136574 | AD5: =D5*(1-x_testy) -> 50000000 | AE5: =E5*(1-x_testy) -> 0 | AF5: =F5*x_NAV -> 0 | AG5: =G5*x_FIX*(1-x_testy) -> 1223620.5 | AH5: =x_z_F*U5+(1-x_AGRI)*x_EMP*x_WLOSS*(x_PEN_K74*Q5+x_PEN_C22*R5) -> 28570668 | AI5: =x_AGRI*x_EMP*x_WLOSS*(x_PEN_K74*Q5+x_PEN_C22*R5) -> 1644242.2 | AJ5: =x_EMP*x_WAGE*(x_WLOSS*(Q5+R5)+S5)+U5*x_ABS_D*x_WAGE/365 -> 2.6689234e+08 | AK5: =AJ5*x_R_FUS -> 84444737 | AL5: =AJ5*x_R_NFZ -> 20727126 | AM5: =AJ5*x_R_PIT -> 17744117 | AN5: =AJ5*x_R_FP -> 6805754.7 | AO5: =AA5+AB5+AC5+AD5+AF5 -> 5.1264486e+08 | AP5: =AO5+AE5+AG5+AH5+AI5+AK5+AL5+AM5+AN5 -> 6.7380513e+08 | AQ5: =AO5+AE5+AG5+AJ5 -> 7.8076082e+08 | AR5: =AB5+AC5+AD5+AF5 -> 2.1890343e+08 | AS5: =AR5+AE5+AG5 -> 2.2012705e+08
A6: 2029 | B6: 3 | C6: 5892.245 | D6: 50000000 | E6: 0 | F6: 0 | G6: 1 | H6: 2750.261 | I6: 295.954 | J6: 1564.041 | K6: 2584.625 | L6: 1461.15 | M6: 22088.431 | N6: 2091.139 | O6: 87.808 | P6: 87.666 | Q6: 2161.57 | R6: 1803.154 | S6: 2212.729 | T6: 3046.215 | U6: 1834.537 | V6: 117143.13 | W6: 294.143 | X6: 792.343 | Y6: 87.808 | Z6: 934.044 | AA6: =H6*x_c_F+I6*x_c_CC+J6*x_c_DC+K6*x_c_HCC+L6*x_c_PLT+M6*x_c_SVRn+N6*x_c_SVRcc+O6*x_c_LT+P6*x_c_LT1 -> 3.0049275e+08 | AB6: =C6*x_c_DAA -> 1.341075e+08 | AC6: =C6*x_c_MON -> 33969558 | AD6: =D6*(1-x_testy) -> 50000000 | AE6: =E6*(1-x_testy) -> 0 | AF6: =F6*x_NAV -> 0 | AG6: =G6*x_FIX*(1-x_testy) -> 1223620.5 | AH6: =x_z_F*U6+(1-x_AGRI)*x_EMP*x_WLOSS*(x_PEN_K74*Q6+x_PEN_C22*R6) -> 29099729 | AI6: =x_AGRI*x_EMP*x_WLOSS*(x_PEN_K74*Q6+x_PEN_C22*R6) -> 1674138.3 | AJ6: =x_EMP*x_WAGE*(x_WLOSS*(Q6+R6)+S6)+U6*x_ABS_D*x_WAGE/365 -> 3.238185e+08 | AK6: =AJ6*x_R_FUS -> 1.0245617e+08 | AL6: =AJ6*x_R_NFZ -> 25148068 | AM6: =AJ6*x_R_PIT -> 21528805 | AN6: =AJ6*x_R_FP -> 8257371.6 | AO6: =AA6+AB6+AC6+AD6+AF6 -> 5.1856981e+08 | AP6: =AO6+AE6+AG6+AH6+AI6+AK6+AL6+AM6+AN6 -> 7.0795771e+08 | AQ6: =AO6+AE6+AG6+AJ6 -> 8.4361192e+08 | AR6: =AB6+AC6+AD6+AF6 -> 2.1807705e+08 | AS6: =AR6+AE6+AG6 -> 2.1930067e+08
A7: 2030 | B7: 4 | C7: 5864.531 | D7: 50000000 | E7: 0 | F7: 0 | G7: 1 | H7: 2719.483 | I7: 309.91 | J7: 1577.536 | K7: 2638.027 | L7: 1446.187 | M7: 26894.042 | N7: 2605.141 | O7: 88.61 | P7: 88.209 | Q7: 2185.593 | R7: 1865.614 | S7: 2865.368 | T7: 3029.393 | U7: 1870.053 | V7: 118486.3 | W7: 303.985 | X7: 815.855 | Y7: 88.61 | Z7: 947.075 | AA7: =H7*x_c_F+I7*x_c_CC+J7*x_c_DC+K7*x_c_HCC+L7*x_c_PLT+M7*x_c_SVRn+N7*x_c_SVRcc+O7*x_c_LT+P7*x_c_LT1 -> 3.0825528e+08 | AB7: =C7*x_c_DAA -> 1.3347673e+08 | AC7: =C7*x_c_MON -> 33809783 | AD7: =D7*(1-x_testy) -> 50000000 | AE7: =E7*(1-x_testy) -> 0 | AF7: =F7*x_NAV -> 0 | AG7: =G7*x_FIX*(1-x_testy) -> 1223620.5 | AH7: =x_z_F*U7+(1-x_AGRI)*x_EMP*x_WLOSS*(x_PEN_K74*Q7+x_PEN_C22*R7) -> 29744215 | AI7: =x_AGRI*x_EMP*x_WLOSS*(x_PEN_K74*Q7+x_PEN_C22*R7) -> 1711911.3 | AJ7: =x_EMP*x_WAGE*(x_WLOSS*(Q7+R7)+S7)+U7*x_ABS_D*x_WAGE/365 -> 3.8239786e+08 | AK7: =AJ7*x_R_FUS -> 1.2099068e+08 | AL7: =AJ7*x_R_NFZ -> 29697400 | AM7: =AJ7*x_R_PIT -> 25423406 | AN7: =AJ7*x_R_FP -> 9751145.4 | AO7: =AA7+AB7+AC7+AD7+AF7 -> 5.2554179e+08 | AP7: =AO7+AE7+AG7+AH7+AI7+AK7+AL7+AM7+AN7 -> 7.4408417e+08 | AQ7: =AO7+AE7+AG7+AJ7 -> 9.0916327e+08 | AR7: =AB7+AC7+AD7+AF7 -> 2.1728651e+08 | AS7: =AR7+AE7+AG7 -> 2.1851013e+08
A8: 2031 | B8: 5 | C8: 5837.956 | D8: 50000000 | E8: 0 | F8: 0 | G8: 1 | H8: 2690.204 | I8: 322.932 | J8: 1596.984 | K8: 2696.394 | L8: 1431.36 | M8: 31576.919 | N8: 3125.977 | O8: 89.777 | P8: 89.193 | Q8: 2215.991 | R8: 1933.958 | S8: 3533.522 | T8: 3013.136 | U8: 1903.771 | V8: 119860.72 | W8: 312.807 | X8: 835.793 | Y8: 89.777 | Z8: 963.061 | AA8: =H8*x_c_F+I8*x_c_CC+J8*x_c_DC+K8*x_c_HCC+L8*x_c_PLT+M8*x_c_SVRn+N8*x_c_SVRcc+O8*x_c_LT+P8*x_c_LT1 -> 3.1653087e+08 | AB8: =C8*x_c_DAA -> 1.3287188e+08 | AC8: =C8*x_c_MON -> 33656575 | AD8: =D8*(1-x_testy) -> 50000000 | AE8: =E8*(1-x_testy) -> 0 | AF8: =F8*x_NAV -> 0 | AG8: =G8*x_FIX*(1-x_testy) -> 1223620.5 | AH8: =x_z_F*U8+(1-x_AGRI)*x_EMP*x_WLOSS*(x_PEN_K74*Q8+x_PEN_C22*R8) -> 30463573 | AI8: =x_AGRI*x_EMP*x_WLOSS*(x_PEN_K74*Q8+x_PEN_C22*R8) -> 1754877.5 | AJ8: =x_EMP*x_WAGE*(x_WLOSS*(Q8+R8)+S8)+U8*x_ABS_D*x_WAGE/365 -> 4.4269601e+08 | AK8: =AJ8*x_R_FUS -> 1.4006902e+08 | AL8: =AJ8*x_R_NFZ -> 34380215 | AM8: =AJ8*x_R_PIT -> 29432279 | AN8: =AJ8*x_R_FP -> 11288748 | AO8: =AA8+AB8+AC8+AD8+AF8 -> 5.3305932e+08 | AP8: =AO8+AE8+AG8+AH8+AI8+AK8+AL8+AM8+AN8 -> 7.8167166e+08 | AQ8: =AO8+AE8+AG8+AJ8 -> 9.7697896e+08 | AR8: =AB8+AC8+AD8+AF8 -> 2.1652845e+08 | AS8: =AR8+AE8+AG8 -> 2.1775207e+08
A9: 2032 | B9: 6 | C9: 5812.447 | D9: 50000000 | E9: 0 | F9: 0 | G9: 1 | H9: 2662.817 | I9: 334.582 | J9: 1620.016 | K9: 2754.305 | L9: 1416.993 | M9: 36138.643 | N9: 3650.07 | O9: 91.153 | P9: 90.465 | Q9: 2251.22 | R9: 2004.149 | S9: 4218.711 | T9: 2997.399 | U9: 1935.739 | V9: 121256.47 | W9: 320.177 | X9: 851.541 | Y9: 91.153 | Z9: 980.102 | AA9: =H9*x_c_F+I9*x_c_CC+J9*x_c_DC+K9*x_c_HCC+L9*x_c_PLT+M9*x_c_SVRn+N9*x_c_SVRcc+O9*x_c_LT+P9*x_c_LT1 -> 3.2487536e+08 | AB9: =C9*x_c_DAA -> 1.3229129e+08 | AC9: =C9*x_c_MON -> 33509512 | AD9: =D9*(1-x_testy) -> 50000000 | AE9: =E9*(1-x_testy) -> 0 | AF9: =F9*x_NAV -> 0 | AG9: =G9*x_FIX*(1-x_testy) -> 1223620.5 | AH9: =x_z_F*U9+(1-x_AGRI)*x_EMP*x_WLOSS*(x_PEN_K74*Q9+x_PEN_C22*R9) -> 31221018 | AI9: =x_AGRI*x_EMP*x_WLOSS*(x_PEN_K74*Q9+x_PEN_C22*R9) -> 1800599 | AJ9: =x_EMP*x_WAGE*(x_WLOSS*(Q9+R9)+S9)+U9*x_ABS_D*x_WAGE/365 -> 5.0466002e+08 | AK9: =AJ9*x_R_FUS -> 1.5967443e+08 | AL9: =AJ9*x_R_NFZ -> 39192402 | AM9: =AJ9*x_R_PIT -> 33551905 | AN9: =AJ9*x_R_FP -> 12868831 | AO9: =AA9+AB9+AC9+AD9+AF9 -> 5.4067617e+08 | AP9: =AO9+AE9+AG9+AH9+AI9+AK9+AL9+AM9+AN9 -> 8.2020898e+08 | AQ9: =AO9+AE9+AG9+AJ9 -> 1.0465598e+09 | AR9: =AB9+AC9+AD9+AF9 -> 2.1580081e+08 | AS9: =AR9+AE9+AG9 -> 2.1702443e+08
A10: 2033 | B10: 7 | C10: 5787.908 | D10: 50000000 | E10: 0 | F10: 0 | G10: 1 | H10: 2637.604 | I10: 344.541 | J10: 1644.32 | K10: 2807.41 | L10: 1403.264 | M10: 40581.419 | N10: 4173.275 | O10: 92.597 | P10: 91.875 | Q10: 2289.652 | R10: 2072.888 | S10: 4921.085 | T10: 2982.145 | U10: 1965.997 | V10: 122665 | W10: 325.824 | X10: 862.768 | Y10: 92.597 | Z10: 996.632 | AA10: =H10*x_c_F+I10*x_c_CC+J10*x_c_DC+K10*x_c_HCC+L10*x_c_PLT+M10*x_c_SVRn+N10*x_c_SVRcc+O10*x_c_LT+P10*x_c_LT1 -> 3.3291277e+08 | AB10: =C10*x_c_DAA -> 1.3173279e+08 | AC10: =C10*x_c_MON -> 33368041 | AD10: =D10*(1-x_testy) -> 50000000 | AE10: =E10*(1-x_testy) -> 0 | AF10: =F10*x_NAV -> 0 | AG10: =G10*x_FIX*(1-x_testy) -> 1223620.5 | AH10: =x_z_F*U10+(1-x_AGRI)*x_EMP*x_WLOSS*(x_PEN_K74*Q10+x_PEN_C22*R10) -> 31984288 | AI10: =x_AGRI*x_EMP*x_WLOSS*(x_PEN_K74*Q10+x_PEN_C22*R10) -> 1846937.8 | AJ10: =x_EMP*x_WAGE*(x_WLOSS*(Q10+R10)+S10)+U10*x_ABS_D*x_WAGE/365 -> 5.6814152e+08 | AK10: =AJ10*x_R_FUS -> 1.7975998e+08 | AL10: =AJ10*x_R_NFZ -> 44122439 | AM10: =AJ10*x_R_PIT -> 37772420 | AN10: =AJ10*x_R_FP -> 14487609 | AO10: =AA10+AB10+AC10+AD10+AF10 -> 5.480136e+08 | AP10: =AO10+AE10+AG10+AH10+AI10+AK10+AL10+AM10+AN10 -> 8.5921089e+08 | AQ10: =AO10+AE10+AG10+AJ10 -> 1.1173787e+09 | AR10: =AB10+AC10+AD10+AF10 -> 2.1510083e+08 | AS10: =AR10+AE10+AG10 -> 2.1632445e+08
A11: 2034 | B11: 8 | C11: 5764.307 | D11: 50000000 | E11: 0 | F11: 0 | G11: 1 | H11: 2614.751 | I11: 352.597 | J11: 1667.77 | K11: 2852.363 | L11: 1390.202 | M11: 44907.583 | N11: 4691.051 | O11: 93.976 | P11: 93.286 | Q11: 2329.669 | R11: 2137.573 | S11: 5639.581 | T11: 2967.348 | U11: 1994.584 | V11: 124078.8 | W11: 329.595 | X11: 869.342 | Y11: 93.976 | Z11: 1011.33 | AA11: =H11*x_c_F+I11*x_c_CC+J11*x_c_DC+K11*x_c_HCC+L11*x_c_PLT+M11*x_c_SVRn+N11*x_c_SVRcc+O11*x_c_LT+P11*x_c_LT1 -> 3.403315e+08 | AB11: =C11*x_c_DAA -> 1.3119563e+08 | AC11: =C11*x_c_MON -> 33231979 | AD11: =D11*(1-x_testy) -> 50000000 | AE11: =E11*(1-x_testy) -> 0 | AF11: =F11*x_NAV -> 0 | AG11: =G11*x_FIX*(1-x_testy) -> 1223620.5 | AH11: =x_z_F*U11+(1-x_AGRI)*x_EMP*x_WLOSS*(x_PEN_K74*Q11+x_PEN_C22*R11) -> 32725944 | AI11: =x_AGRI*x_EMP*x_WLOSS*(x_PEN_K74*Q11+x_PEN_C22*R11) -> 1892075.1 | AJ11: =x_EMP*x_WAGE*(x_WLOSS*(Q11+R11)+S11)+U11*x_ABS_D*x_WAGE/365 -> 6.3291187e+08 | AK11: =AJ11*x_R_FUS -> 2.0025332e+08 | AL11: =AJ11*x_R_NFZ -> 49152569 | AM11: =AJ11*x_R_PIT -> 42078623 | AN11: =AJ11*x_R_FP -> 16139253 | AO11: =AA11+AB11+AC11+AD11+AF11 -> 5.547591e+08 | AP11: =AO11+AE11+AG11+AH11+AI11+AK11+AL11+AM11+AN11 -> 8.982245e+08 | AQ11: =AO11+AE11+AG11+AJ11 -> 1.1888946e+09 | AR11: =AB11+AC11+AD11+AF11 -> 2.1442761e+08 | AS11: =AR11+AE11+AG11 -> 2.1565123e+08
A12: 2035 | B12: 9 | C12: 5741.579 | D12: 50000000 | E12: 0 | F12: 0 | G12: 1 | H12: 2401.903 | I12: 331.735 | J12: 1688.516 | K12: 2886.756 | L12: 1377.714 | M12: 48741.965 | N12: 5145.901 | O12: 95.185 | P12: 94.581 | Q12: 2369.737 | R12: 2196.226 | S12: 6372.126 | T12: 2733.637 | U12: 1870.026 | V12: 125467.85 | W12: 331.444 | X12: 871.328 | Y12: 95.185 | Z12: 1023.22 | AA12: =H12*x_c_F+I12*x_c_CC+J12*x_c_DC+K12*x_c_HCC+L12*x_c_PLT+M12*x_c_SVRn+N12*x_c_SVRcc+O12*x_c_LT+P12*x_c_LT1 -> 3.4579923e+08 | AB12: =C12*x_c_DAA -> 1.3067834e+08 | AC12: =C12*x_c_MON -> 33100949 | AD12: =D12*(1-x_testy) -> 50000000 | AE12: =E12*(1-x_testy) -> 0 | AF12: =F12*x_NAV -> 0 | AG12: =G12*x_FIX*(1-x_testy) -> 1223620.5 | AH12: =x_z_F*U12+(1-x_AGRI)*x_EMP*x_WLOSS*(x_PEN_K74*Q12+x_PEN_C22*R12) -> 33111820 | AI12: =x_AGRI*x_EMP*x_WLOSS*(x_PEN_K74*Q12+x_PEN_C22*R12) -> 1934507.2 | AJ12: =x_EMP*x_WAGE*(x_WLOSS*(Q12+R12)+S12)+U12*x_ABS_D*x_WAGE/365 -> 6.9823442e+08 | AK12: =AJ12*x_R_FUS -> 2.2092137e+08 | AL12: =AJ12*x_R_NFZ -> 54225584 | AM12: =AJ12*x_R_PIT -> 46421539 | AN12: =AJ12*x_R_FP -> 17804978 | AO12: =AA12+AB12+AC12+AD12+AF12 -> 5.5957851e+08 | AP12: =AO12+AE12+AG12+AH12+AI12+AK12+AL12+AM12+AN12 -> 9.3522193e+08 | AQ12: =AO12+AE12+AG12+AJ12 -> 1.2590366e+09 | AR12: =AB12+AC12+AD12+AF12 -> 2.1377929e+08 | AS12: =AR12+AE12+AG12 -> 2.1500291e+08
A13: 2036 | B13: 10 | C13: 4832 | D13: 0 | E13: 0 | F13: 0 | G13: 0 | H13: 2197.105 | I13: 309.251 | J13: 1705.908 | K13: 2911.047 | L13: 1365.586 | M13: 52100.495 | N13: 5535.595 | O13: 96.13 | P13: 95.658 | Q13: 2409.161 | R13: 2249.068 | S13: 7115.807 | T13: 2506.356 | U13: 1745.465 | V13: 126825.32 | W13: 333.187 | X13: 873.034 | Y13: 96.13 | Z13: 1031.517 | AA13: =H13*x_c_F+I13*x_c_CC+J13*x_c_DC+K13*x_c_HCC+L13*x_c_PLT+M13*x_c_SVRn+N13*x_c_SVRcc+O13*x_c_LT+P13*x_c_LT1 -> 3.5002687e+08 | AB13: =C13*x_c_DAA -> 109976320 | AC13: =C13*x_c_MON -> 27857108 | AD13: =D13*(1-x_testy) -> 0 | AE13: =E13*(1-x_testy) -> 0 | AF13: =F13*x_NAV -> 0 | AG13: =G13*x_FIX*(1-x_testy) -> 0 | AH13: =x_z_F*U13+(1-x_AGRI)*x_EMP*x_WLOSS*(x_PEN_K74*Q13+x_PEN_C22*R13) -> 33454094 | AI13: =x_AGRI*x_EMP*x_WLOSS*(x_PEN_K74*Q13+x_PEN_C22*R13) -> 1974057.6 | AJ13: =x_EMP*x_WAGE*(x_WLOSS*(Q13+R13)+S13)+U13*x_ABS_D*x_WAGE/365 -> 7.6429515e+08 | AK13: =AJ13*x_R_FUS -> 2.4182299e+08 | AL13: =AJ13*x_R_NFZ -> 59355926 | AM13: =AJ13*x_R_PIT -> 50813532 | AN13: =AJ13*x_R_FP -> 19489526 | AO13: =AA13+AB13+AC13+AD13+AF13 -> 4.878603e+08 | AP13: =AO13+AE13+AG13+AH13+AI13+AK13+AL13+AM13+AN13 -> 8.9477042e+08 | AQ13: =AO13+AE13+AG13+AJ13 -> 1.2521554e+09 | AR13: =AB13+AC13+AD13+AF13 -> 1.3783343e+08 | AS13: =AR13+AE13+AG13 -> 1.3783343e+08
A14: 2037 | B14: 11 | C14: 4832 | D14: 0 | E14: 0 | F14: 0 | G14: 0 | H14: 2192.396 | I14: 312.245 | J14: 1719.478 | K14: 2925.845 | L14: 1353.496 | M14: 55375.24 | N14: 5911.053 | O14: 96.856 | P14: 96.493 | Q14: 2447.363 | R14: 2296.446 | S14: 7867.498 | T14: 2504.64 | U14: 1772.488 | V14: 128166.75 | W14: 333.194 | X14: 870.786 | Y14: 96.856 | Z14: 1037.02 | AA14: =H14*x_c_F+I14*x_c_CC+J14*x_c_DC+K14*x_c_HCC+L14*x_c_PLT+M14*x_c_SVRn+N14*x_c_SVRcc+O14*x_c_LT+P14*x_c_LT1 -> 3.5414316e+08 | AB14: =C14*x_c_DAA -> 109976320 | AC14: =C14*x_c_MON -> 27857108 | AD14: =D14*(1-x_testy) -> 0 | AE14: =E14*(1-x_testy) -> 0 | AF14: =F14*x_NAV -> 0 | AG14: =G14*x_FIX*(1-x_testy) -> 0 | AH14: =x_z_F*U14+(1-x_AGRI)*x_EMP*x_WLOSS*(x_PEN_K74*Q14+x_PEN_C22*R14) -> 34063308 | AI14: =x_AGRI*x_EMP*x_WLOSS*(x_PEN_K74*Q14+x_PEN_C22*R14) -> 2010653.2 | AJ14: =x_EMP*x_WAGE*(x_WLOSS*(Q14+R14)+S14)+U14*x_ABS_D*x_WAGE/365 -> 8.3126523e+08 | AK14: =AJ14*x_R_FUS -> 2.6301232e+08 | AL14: =AJ14*x_R_NFZ -> 64556889 | AM14: =AJ14*x_R_PIT -> 55265982 | AN14: =AJ14*x_R_FP -> 21197263 | AO14: =AA14+AB14+AC14+AD14+AF14 -> 4.9197659e+08 | AP14: =AO14+AE14+AG14+AH14+AI14+AK14+AL14+AM14+AN14 -> 9.32083e+08 | AQ14: =AO14+AE14+AG14+AJ14 -> 1.3232418e+09 | AR14: =AB14+AC14+AD14+AF14 -> 1.3783343e+08 | AS14: =AR14+AE14+AG14 -> 1.3783343e+08
... A52: 2075 | B52: 49 | C52: 4832 | D52: 0 | E52: 0 | F52: 0 | G52: 0 | H52: 2275.333 | I52: 198.088 | J52: 998.311 | K52: 1726.201 | L52: 623.744 | M52: 148024.4 | N52: 7675.367 | O52: 56.743 | P52: 56.826 | Q52: 603.504 | R52: 890.852 | S52: 2482.983 | T52: 2473.42 | U52: 1837.38 | V52: 180765.24 | W52: 184.898 | X52: 502.526 | Y52: 56.743 | Z52: 604.432 | AA52: =H52*x_c_F+I52*x_c_CC+J52*x_c_DC+K52*x_c_HCC+L52*x_c_PLT+M52*x_c_SVRn+N52*x_c_SVRcc+O52*x_c_LT+P52*x_c_LT1 -> 2.880617e+08 | AB52: =C52*x_c_DAA -> 109976320 | AC52: =C52*x_c_MON -> 27857108 | AD52: =D52*(1-x_testy) -> 0 | AE52: =E52*(1-x_testy) -> 0 | AF52: =F52*x_NAV -> 0 | AG52: =G52*x_FIX*(1-x_testy) -> 0 | AH52: =x_z_F*U52+(1-x_AGRI)*x_EMP*x_WLOSS*(x_PEN_K74*Q52+x_PEN_C22*R52) -> 13497348 | AI52: =x_AGRI*x_EMP*x_WLOSS*(x_PEN_K74*Q52+x_PEN_C22*R52) -> 642464.53 | AJ52: =x_EMP*x_WAGE*(x_WLOSS*(Q52+R52)+S52)+U52*x_ABS_D*x_WAGE/365 -> 2.6600998e+08 | AK52: =AJ52*x_R_FUS -> 84165557 | AL52: =AJ52*x_R_NFZ -> 20658601 | AM52: =AJ52*x_R_PIT -> 17685454 | AN52: =AJ52*x_R_FP -> 6783254.5 | AO52: =AA52+AB52+AC52+AD52+AF52 -> 4.2589513e+08 | AP52: =AO52+AE52+AG52+AH52+AI52+AK52+AL52+AM52+AN52 -> 5.6932781e+08 | AQ52: =AO52+AE52+AG52+AJ52 -> 6.9190511e+08 | AR52: =AB52+AC52+AD52+AF52 -> 1.3783343e+08 | AS52: =AR52+AE52+AG52 -> 1.3783343e+08

Sheet L_I2
A1: I2: Szerokie testowanie w POZ (+50 mln zł/rok) – liczebności (silnik, wartości) i koszty (formuły), zł/rok, niezdyskontowane. Szacunek modelu.
A2: rok | B2: t | C2: treated | D2: NFZ_diag | E2: MZ_SW | F2: nNAV | G2: FIXon | H2: cF03 | I2: cF4 | J2: cDC | K2: cHCC | L2: cPLT | M2: cSVn | N2: cSVc | O2: cLTn | P2: cLT1 | Q2: wAdv | R2: wHCC | S2: wGH | T2: cAbs | U2: cAbsW | V2: QALY | W2: newDC | X2: newHCC | Y2: LT | Z2: liverD | AA2: NFZ_med | AB2: NFZ_DAA | AC2: NFZ_mon | AD2: NFZ_diag_k | AE2: MZ_SW_k | AF2: NAV_k | AG2: FIX_k | AH2: ZUS | AI2: KRUS | AJ2: lostw | AK2: lost_FUS | AL2: lost_NFZ | AM2: lost_PIT | AN2: lost_FP | AO2: NFZ | AP2: PUBLIC | AQ2: SOCIETAL | AR2: INV_NFZ | AS2: INV_PUB
A3: 2026 | B3: 0 | C3: 4951.32 | D3: 16666667 | E3: 0 | F3: 0 | G3: 1 | H3: 2402.721 | I3: 215.462 | J3: 1579.333 | K3: 2524.799 | L3: 1540.438 | M3: 6641.203 | N3: 586.5 | O3: 89.046 | P3: 44.523 | Q3: 2134.707 | R3: 1703.283 | S3: 312.377 | T3: 2618.183 | U3: 1450.052 | V3: 113405.63 | W3: 265.701 | X3: 711.503 | Y3: 89.046 | Z3: 922.327 | AA3: =H3*x_c_F+I3*x_c_CC+J3*x_c_DC+K3*x_c_HCC+L3*x_c_PLT+M3*x_c_SVRn+N3*x_c_SVRcc+O3*x_c_LT+P3*x_c_LT1 -> 2.8285355e+08 | AB3: =C3*x_c_DAA -> 1.1269204e+08 | AC3: =C3*x_c_MON -> 28545003 | AD3: =D3*(1-x_testy) -> 16666667 | AE3: =E3*(1-x_testy) -> 0 | AF3: =F3*x_NAV -> 0 | AG3: =G3*x_FIX*(1-x_testy) -> 1223620.5 | AH3: =x_z_F*U3+(1-x_AGRI)*x_EMP*x_WLOSS*(x_PEN_K74*Q3+x_PEN_C22*R3) -> 27464974 | AI3: =x_AGRI*x_EMP*x_WLOSS*(x_PEN_K74*Q3+x_PEN_C22*R3) -> 1618332.4 | AJ3: =x_EMP*x_WAGE*(x_WLOSS*(Q3+R3)+S3)+U3*x_ABS_D*x_WAGE/365 -> 1.5651597e+08 | AK3: =AJ3*x_R_FUS -> 49521654 | AL3: =AJ3*x_R_NFZ -> 12155187 | AM3: =AJ3*x_R_PIT -> 10405835 | AN3: =AJ3*x_R_FP -> 3991157.3 | AO3: =AA3+AB3+AC3+AD3+AF3 -> 4.4075727e+08 | AP3: =AO3+AE3+AG3+AH3+AI3+AK3+AL3+AM3+AN3 -> 5.4713803e+08 | AQ3: =AO3+AE3+AG3+AJ3 -> 5.9849686e+08 | AR3: =AB3+AC3+AD3+AF3 -> 1.5790371e+08 | AS3: =AR3+AE3+AG3 -> 1.5912733e+08
A4: 2027 | B4: 1 | C4: 5065.485 | D4: 33333333 | E4: 0 | F4: 0 | G4: 1 | H4: 2440.372 | I4: 232.287 | J4: 1564.197 | K4: 2521.646 | L4: 1489.389 | M4: 11095.842 | N4: 1000.523 | O4: 87.912 | P4: 88.479 | Q4: 2138.122 | R4: 1717.174 | S4: 939.965 | T4: 2672.659 | U4: 1524.788 | V4: 114531.37 | W4: 275.18 | X4: 741.411 | Y4: 87.912 | Z4: 925.718 | AA4: =H4*x_c_F+I4*x_c_CC+J4*x_c_DC+K4*x_c_HCC+L4*x_c_PLT+M4*x_c_SVRn+N4*x_c_SVRcc+O4*x_c_LT+P4*x_c_LT1 -> 2.8652513e+08 | AB4: =C4*x_c_DAA -> 1.1529044e+08 | AC4: =C4*x_c_MON -> 29203179 | AD4: =D4*(1-x_testy) -> 33333333 | AE4: =E4*(1-x_testy) -> 0 | AF4: =F4*x_NAV -> 0 | AG4: =G4*x_FIX*(1-x_testy) -> 1223620.5 | AH4: =x_z_F*U4+(1-x_AGRI)*x_EMP*x_WLOSS*(x_PEN_K74*Q4+x_PEN_C22*R4) -> 27734123 | AI4: =x_AGRI*x_EMP*x_WLOSS*(x_PEN_K74*Q4+x_PEN_C22*R4) -> 1625966.6 | AJ4: =x_EMP*x_WAGE*(x_WLOSS*(Q4+R4)+S4)+U4*x_ABS_D*x_WAGE/365 -> 2.1081041e+08 | AK4: =AJ4*x_R_FUS -> 66700415 | AL4: =AJ4*x_R_NFZ -> 16371748 | AM4: =AJ4*x_R_PIT -> 14015556 | AN4: =AJ4*x_R_FP -> 5375665.6 | AO4: =AA4+AB4+AC4+AD4+AF4 -> 4.6435208e+08 | AP4: =AO4+AE4+AG4+AH4+AI4+AK4+AL4+AM4+AN4 -> 5.9739918e+08 | AQ4: =AO4+AE4+AG4+AJ4 -> 6.7638612e+08 | AR4: =AB4+AC4+AD4+AF4 -> 1.7782695e+08 | AS4: =AR4+AE4+AG4 -> 1.7905057e+08
A5: 2028 | B5: 2 | C5: 5174.648 | D5: 50000000 | E5: 0 | F5: 0 | G5: 1 | H5: 2448.272 | I5: 247.995 | J5: 1561.132 | K5: 2548.335 | L5: 1475.766 | M5: 15512.573 | N5: 1431.227 | O5: 87.611 | P5: 87.762 | Q5: 2146.956 | R5: 1755.295 | S5: 1573.033 | T5: 2696.266 | U5: 1581.369 | V5: 115736.44 | W5: 286.218 | X5: 771.912 | Y5: 87.611 | Z5: 927.107 | AA5: =H5*x_c_F+I5*x_c_CC+J5*x_c_DC+K5*x_c_HCC+L5*x_c_PLT+M5*x_c_SVRn+N5*x_c_SVRcc+O5*x_c_LT+P5*x_c_LT1 -> 2.9157105e+08 | AB5: =C5*x_c_DAA -> 1.1777499e+08 | AC5: =C5*x_c_MON -> 29832518 | AD5: =D5*(1-x_testy) -> 50000000 | AE5: =E5*(1-x_testy) -> 0 | AF5: =F5*x_NAV -> 0 | AG5: =G5*x_FIX*(1-x_testy) -> 1223620.5 | AH5: =x_z_F*U5+(1-x_AGRI)*x_EMP*x_WLOSS*(x_PEN_K74*Q5+x_PEN_C22*R5) -> 28164176 | AI5: =x_AGRI*x_EMP*x_WLOSS*(x_PEN_K74*Q5+x_PEN_C22*R5) -> 1646703.4 | AJ5: =x_EMP*x_WAGE*(x_WLOSS*(Q5+R5)+S5)+U5*x_ABS_D*x_WAGE/365 -> 2.6648921e+08 | AK5: =AJ5*x_R_FUS -> 84317186 | AL5: =AJ5*x_R_NFZ -> 20695819 | AM5: =AJ5*x_R_PIT -> 17717315 | AN5: =AJ5*x_R_FP -> 6795474.9 | AO5: =AA5+AB5+AC5+AD5+AF5 -> 4.8917855e+08 | AP5: =AO5+AE5+AG5+AH5+AI5+AK5+AL5+AM5+AN5 -> 6.4973885e+08 | AQ5: =AO5+AE5+AG5+AJ5 -> 7.5689139e+08 | AR5: =AB5+AC5+AD5+AF5 -> 1.9760751e+08 | AS5: =AR5+AE5+AG5 -> 1.9883113e+08
A6: 2029 | B6: 3 | C6: 5167.173 | D6: 50000000 | E6: 0 | F6: 0 | G6: 1 | H6: 2428.835 | I6: 261.666 | J6: 1569.042 | K6: 2596.108 | L6: 1461.203 | M6: 19836.052 | N6: 1873.657 | O6: 88.025 | P6: 87.818 | Q6: 2165.214 | R6: 1811.194 | S6: 2214.515 | T6: 2690.501 | U6: 1619.665 | V6: 116994.96 | W6: 297.852 | X6: 801.512 | Y6: 88.025 | Z6: 936.592 | AA6: =H6*x_c_F+I6*x_c_CC+J6*x_c_DC+K6*x_c_HCC+L6*x_c_PLT+M6*x_c_SVRn+N6*x_c_SVRcc+O6*x_c_LT+P6*x_c_LT1 -> 2.9827599e+08 | AB6: =C6*x_c_DAA -> 1.1760486e+08 | AC6: =C6*x_c_MON -> 29789423 | AD6: =D6*(1-x_testy) -> 50000000 | AE6: =E6*(1-x_testy) -> 0 | AF6: =F6*x_NAV -> 0 | AG6: =G6*x_FIX*(1-x_testy) -> 1223620.5 | AH6: =x_z_F*U6+(1-x_AGRI)*x_EMP*x_WLOSS*(x_PEN_K74*Q6+x_PEN_C22*R6) -> 28734851 | AI6: =x_AGRI*x_EMP*x_WLOSS*(x_PEN_K74*Q6+x_PEN_C22*R6) -> 1679219.8 | AJ6: =x_EMP*x_WAGE*(x_WLOSS*(Q6+R6)+S6)+U6*x_ABS_D*x_WAGE/365 -> 3.2372204e+08 | AK6: =AJ6*x_R_FUS -> 1.0242565e+08 | AL6: =AJ6*x_R_NFZ -> 25140577 | AM6: =AJ6*x_R_PIT -> 21522392 | AN6: =AJ6*x_R_FP -> 8254912 | AO6: =AA6+AB6+AC6+AD6+AF6 -> 4.9567027e+08 | AP6: =AO6+AE6+AG6+AH6+AI6+AK6+AL6+AM6+AN6 -> 6.846515e+08 | AQ6: =AO6+AE6+AG6+AJ6 -> 8.2061594e+08 | AR6: =AB6+AC6+AD6+AF6 -> 1.9739428e+08 | AS6: =AR6+AE6+AG6 -> 1.986179e+08
A7: 2030 | B7: 4 | C7: 5160.008 | D7: 50000000 | E7: 0 | F7: 0 | G7: 1 | H7: 2409.73 | I7: 275.159 | J7: 1586.102 | K7: 2657.245 | L7: 1446.36 | M7: 24064.753 | N7: 2326.552 | O7: 89.016 | P7: 88.521 | Q7: 2192.001 | R7: 1879.23 | S7: 2869.718 | T7: 2684.889 | U7: 1656.317 | V7: 118292.78 | W7: 309.232 | X7: 828.828 | Y7: 89.016 | Z7: 951.804 | AA7: =H7*x_c_F+I7*x_c_CC+J7*x_c_DC+K7*x_c_HCC+L7*x_c_PLT+M7*x_c_SVRn+N7*x_c_SVRcc+O7*x_c_LT+P7*x_c_LT1 -> 3.0617683e+08 | AB7: =C7*x_c_DAA -> 1.1744178e+08 | AC7: =C7*x_c_MON -> 29748116 | AD7: =D7*(1-x_testy) -> 50000000 | AE7: =E7*(1-x_testy) -> 0 | AF7: =F7*x_NAV -> 0 | AG7: =G7*x_FIX*(1-x_testy) -> 1223620.5 | AH7: =x_z_F*U7+(1-x_AGRI)*x_EMP*x_WLOSS*(x_PEN_K74*Q7+x_PEN_C22*R7) -> 29436416 | AI7: =x_AGRI*x_EMP*x_WLOSS*(x_PEN_K74*Q7+x_PEN_C22*R7) -> 1720611.2 | AJ7: =x_EMP*x_WAGE*(x_WLOSS*(Q7+R7)+S7)+U7*x_ABS_D*x_WAGE/365 -> 3.8279633e+08 | AK7: =AJ7*x_R_FUS -> 1.2111676e+08 | AL7: =AJ7*x_R_NFZ -> 29728346 | AM7: =AJ7*x_R_PIT -> 25449898 | AN7: =AJ7*x_R_FP -> 9761306.4 | AO7: =AA7+AB7+AC7+AD7+AF7 -> 5.0336673e+08 | AP7: =AO7+AE7+AG7+AH7+AI7+AK7+AL7+AM7+AN7 -> 7.2180369e+08 | AQ7: =AO7+AE7+AG7+AJ7 -> 8.8738668e+08 | AR7: =AB7+AC7+AD7+AF7 -> 1.971899e+08 | AS7: =AR7+AE7+AG7 -> 1.9841352e+08
A8: 2031 | B8: 5 | C8: 5153.118 | D8: 50000000 | E8: 0 | F8: 0 | G8: 1 | H8: 2391.444 | I8: 287.967 | J8: 1610.067 | K8: 2725.054 | L8: 1431.774 | M8: 28198.412 | N8: 2787.705 | O8: 90.429 | P8: 89.722 | Q8: 2226.042 | R8: 1954.511 | S8: 3542.23 | T8: 2679.411 | U8: 1691.356 | V8: 119619.75 | W8: 319.731 | X8: 852.885 | Y8: 90.429 | Z8: 970.572 | AA8: =H8*x_c_F+I8*x_c_CC+J8*x_c_DC+K8*x_c_HCC+L8*x_c_PLT+M8*x_c_SVRn+N8*x_c_SVRcc+O8*x_c_LT+P8*x_c_LT1 -> 3.1476156e+08 | AB8: =C8*x_c_DAA -> 1.1728497e+08 | AC8: =C8*x_c_MON -> 29708395 | AD8: =D8*(1-x_testy) -> 50000000 | AE8: =E8*(1-x_testy) -> 0 | AF8: =F8*x_NAV -> 0 | AG8: =G8*x_FIX*(1-x_testy) -> 1223620.5 | AH8: =x_z_F*U8+(1-x_AGRI)*x_EMP*x_WLOSS*(x_PEN_K74*Q8+x_PEN_C22*R8) -> 30227823 | AI8: =x_AGRI*x_EMP*x_WLOSS*(x_PEN_K74*Q8+x_PEN_C22*R8) -> 1768160.2 | AJ8: =x_EMP*x_WAGE*(x_WLOSS*(Q8+R8)+S8)+U8*x_ABS_D*x_WAGE/365 -> 4.4381623e+08 | AK8: =AJ8*x_R_FUS -> 1.4042346e+08 | AL8: =AJ8*x_R_NFZ -> 34467212 | AM8: =AJ8*x_R_PIT -> 29506755 | AN8: =AJ8*x_R_FP -> 11317314 | AO8: =AA8+AB8+AC8+AD8+AF8 -> 5.1175492e+08 | AP8: =AO8+AE8+AG8+AH8+AI8+AK8+AL8+AM8+AN8 -> 7.6068927e+08 | AQ8: =AO8+AE8+AG8+AJ8 -> 9.5679478e+08 | AR8: =AB8+AC8+AD8+AF8 -> 1.9699336e+08 | AS8: =AR8+AE8+AG8 -> 1.9821698e+08
A9: 2032 | B9: 6 | C9: 5146.482 | D9: 50000000 | E9: 0 | F9: 0 | G9: 1 | H9: 2374.35 | I9: 299.701 | J9: 1638.517 | K9: 2793.887 | L9: 1417.81 | M9: 32237.304 | N9: 3254.145 | O9: 92.103 | P9: 91.266 | Q9: 2265.816 | R9: 2032.893 | S9: 4234.018 | T9: 2674.052 | U9: 1724.833 | V9: 120965.78 | W9: 328.896 | X9: 873.001 | Y9: 92.103 | Z9: 990.933 | AA9: =H9*x_c_F+I9*x_c_CC+J9*x_c_DC+K9*x_c_HCC+L9*x_c_PLT+M9*x_c_SVRn+N9*x_c_SVRcc+O9*x_c_LT+P9*x_c_LT1 -> 3.2357139e+08 | AB9: =C9*x_c_DAA -> 1.1713393e+08 | AC9: =C9*x_c_MON -> 29670137 | AD9: =D9*(1-x_testy) -> 50000000 | AE9: =E9*(1-x_testy) -> 0 | AF9: =F9*x_NAV -> 0 | AG9: =G9*x_FIX*(1-x_testy) -> 1223620.5 | AH9: =x_z_F*U9+(1-x_AGRI)*x_EMP*x_WLOSS*(x_PEN_K74*Q9+x_PEN_C22*R9) -> 31071702 | AI9: =x_AGRI*x_EMP*x_WLOSS*(x_PEN_K74*Q9+x_PEN_C22*R9) -> 1819389.7 | AJ9: =x_EMP*x_WAGE*(x_WLOSS*(Q9+R9)+S9)+U9*x_ABS_D*x_WAGE/365 -> 5.0676417e+08 | AK9: =AJ9*x_R_FUS -> 1.6034018e+08 | AL9: =AJ9*x_R_NFZ -> 39355812 | AM9: =AJ9*x_R_PIT -> 33691797 | AN9: =AJ9*x_R_FP -> 12922486 | AO9: =AA9+AB9+AC9+AD9+AF9 -> 5.2037546e+08 | AP9: =AO9+AE9+AG9+AH9+AI9+AK9+AL9+AM9+AN9 -> 8.0080045e+08 | AQ9: =AO9+AE9+AG9+AJ9 -> 1.0283633e+09 | AR9: =AB9+AC9+AD9+AF9 -> 1.9680407e+08 | AS9: =AR9+AE9+AG9 -> 1.9802769e+08
A10: 2033 | B10: 7 | C10: 5140.07 | D10: 50000000 | E10: 0 | F10: 0 | G10: 1 | H10: 2358.728 | I10: 310.071 | J10: 1669.071 | K10: 2859.164 | L10: 1404.678 | M10: 36182.299 | N10: 3722.374 | O10: 93.893 | P10: 92.998 | Q10: 2309.698 | R10: 2110.961 | S10: 4945.645 | T10: 2668.798 | U10: 1756.792 | V10: 122322.28 | W10: 336.427 | X10: 888.774 | Y10: 93.893 | Z10: 1011.253 | AA10: =H10*x_c_F+I10*x_c_CC+J10*x_c_DC+K10*x_c_HCC+L10*x_c_PLT+M10*x_c_SVRn+N10*x_c_SVRcc+O10*x_c_LT+P10*x_c_LT1 -> 3.3221513e+08 | AB10: =C10*x_c_DAA -> 1.1698799e+08 | AC10: =C10*x_c_MON -> 29633171 | AD10: =D10*(1-x_testy) -> 50000000 | AE10: =E10*(1-x_testy) -> 0 | AF10: =F10*x_NAV -> 0 | AG10: =G10*x_FIX*(1-x_testy) -> 1223620.5 | AH10: =x_z_F*U10+(1-x_AGRI)*x_EMP*x_WLOSS*(x_PEN_K74*Q10+x_PEN_C22*R10) -> 31935023 | AI10: =x_AGRI*x_EMP*x_WLOSS*(x_PEN_K74*Q10+x_PEN_C22*R10) -> 1872110.6 | AJ10: =x_EMP*x_WAGE*(x_WLOSS*(Q10+R10)+S10)+U10*x_ABS_D*x_WAGE/365 -> 5.7152332e+08 | AK10: =AJ10*x_R_FUS -> 1.8082998e+08 | AL10: =AJ10*x_R_NFZ -> 44385073 | AM10: =AJ10*x_R_PIT -> 37997256 | AN10: =AJ10*x_R_FP -> 14573845 | AO10: =AA10+AB10+AC10+AD10+AF10 -> 5.288363e+08 | AP10: =AO10+AE10+AG10+AH10+AI10+AK10+AL10+AM10+AN10 -> 8.416532e+08 | AQ10: =AO10+AE10+AG10+AJ10 -> 1.1015832e+09 | AR10: =AB10+AC10+AD10+AF10 -> 1.9662116e+08 | AS10: =AR10+AE10+AG10 -> 1.9784478e+08
A11: 2034 | B11: 8 | C11: 5133.875 | D11: 50000000 | E11: 0 | F11: 0 | G11: 1 | H11: 2344.772 | I11: 318.872 | J11: 1699.512 | K11: 2917.301 | L11: 1392.434 | M11: 40034.421 | N11: 4188.506 | O11: 95.661 | P11: 94.777 | Q11: 2356.062 | R11: 2185.986 | S11: 5676.421 | T11: 2663.643 | U11: 1787.272 | V11: 123681.74 | W11: 342.137 | X11: 899.994 | Y11: 95.661 | Z11: 1030.138 | AA11: =H11*x_c_F+I11*x_c_CC+J11*x_c_DC+K11*x_c_HCC+L11*x_c_PLT+M11*x_c_SVRn+N11*x_c_SVRcc+O11*x_c_LT+P11*x_c_LT1 -> 3.4036459e+08 | AB11: =C11*x_c_DAA -> 116846995 | AC11: =C11*x_c_MON -> 29597456 | AD11: =D11*(1-x_testy) -> 50000000 | AE11: =E11*(1-x_testy) -> 0 | AF11: =F11*x_NAV -> 0 | AG11: =G11*x_FIX*(1-x_testy) -> 1223620.5 | AH11: =x_z_F*U11+(1-x_AGRI)*x_EMP*x_WLOSS*(x_PEN_K74*Q11+x_PEN_C22*R11) -> 32789431 | AI11: =x_AGRI*x_EMP*x_WLOSS*(x_PEN_K74*Q11+x_PEN_C22*R11) -> 1924443.4 | AJ11: =x_EMP*x_WAGE*(x_WLOSS*(Q11+R11)+S11)+U11*x_ABS_D*x_WAGE/365 -> 6.3789242e+08 | AK11: =AJ11*x_R_FUS -> 2.0182916e+08 | AL11: =AJ11*x_R_NFZ -> 49539363 | AM11: =AJ11*x_R_PIT -> 42409751 | AN11: =AJ11*x_R_FP -> 16266257 | AO11: =AA11+AB11+AC11+AD11+AF11 -> 5.3680904e+08 | AP11: =AO11+AE11+AG11+AH11+AI11+AK11+AL11+AM11+AN11 -> 8.8279106e+08 | AQ11: =AO11+AE11+AG11+AJ11 -> 1.1759251e+09 | AR11: =AB11+AC11+AD11+AF11 -> 1.9644445e+08 | AS11: =AR11+AE11+AG11 -> 1.9766807e+08
A12: 2035 | B12: 9 | C12: 5127.878 | D12: 50000000 | E12: 0 | F12: 0 | G12: 1 | H12: 2269.251 | I12: 317.016 | J12: 1727.884 | K12: 2965.639 | L12: 1381.007 | M12: 43671.709 | N12: 4631.029 | O12: 97.294 | P12: 96.478 | Q12: 2403.341 | R12: 2255.853 | S12: 6424.6 | T12: 2586.267 | U12: 1766.458 | V12: 125030.19 | W12: 345.95 | X12: 906.654 | Y12: 97.294 | Z12: 1046.534 | AA12: =H12*x_c_F+I12*x_c_CC+J12*x_c_DC+K12*x_c_HCC+L12*x_c_PLT+M12*x_c_SVRn+N12*x_c_SVRcc+O12*x_c_LT+P12*x_c_LT1 -> 3.4740028e+08 | AB12: =C12*x_c_DAA -> 1.167105e+08 | AC12: =C12*x_c_MON -> 29562883 | AD12: =D12*(1-x_testy) -> 50000000 | AE12: =E12*(1-x_testy) -> 0 | AF12: =F12*x_NAV -> 0 | AG12: =G12*x_FIX*(1-x_testy) -> 1223620.5 | AH12: =x_z_F*U12+(1-x_AGRI)*x_EMP*x_WLOSS*(x_PEN_K74*Q12+x_PEN_C22*R12) -> 33508627 | AI12: =x_AGRI*x_EMP*x_WLOSS*(x_PEN_K74*Q12+x_PEN_C22*R12) -> 1974809.4 | AJ12: =x_EMP*x_WAGE*(x_WLOSS*(Q12+R12)+S12)+U12*x_ABS_D*x_WAGE/365 -> 7.0545575e+08 | AK12: =AJ12*x_R_FUS -> 2.232062e+08 | AL12: =AJ12*x_R_NFZ -> 54786399 | AM12: =AJ12*x_R_PIT -> 46901643 | AN12: =AJ12*x_R_FP -> 17989122 | AO12: =AA12+AB12+AC12+AD12+AF12 -> 5.4367366e+08 | AP12: =AO12+AE12+AG12+AH12+AI12+AK12+AL12+AM12+AN12 -> 9.2326409e+08 | AQ12: =AO12+AE12+AG12+AJ12 -> 1.250353e+09 | AR12: =AB12+AC12+AD12+AF12 -> 1.9627339e+08 | AS12: =AR12+AE12+AG12 -> 1.9749701e+08
A13: 2036 | B13: 10 | C13: 4832 | D13: 0 | E13: 0 | F13: 0 | G13: 0 | H13: 2197.122 | I13: 313.48 | J13: 1752.808 | K13: 3002.99 | L13: 1370.197 | M13: 47099.1 | N13: 5046.437 | O13: 98.692 | P13: 97.993 | Q13: 2450.32 | R13: 2319.538 | S13: 7187.543 | T13: 2510.602 | U13: 1744.505 | V13: 126361.26 | W13: 348.442 | X13: 910.205 | Y13: 98.692 | Z13: 1059.573 | AA13: =H13*x_c_F+I13*x_c_CC+J13*x_c_DC+K13*x_c_HCC+L13*x_c_PLT+M13*x_c_SVRn+N13*x_c_SVRcc+O13*x_c_LT+P13*x_c_LT1 -> 3.5341115e+08 | AB13: =C13*x_c_DAA -> 109976320 | AC13: =C13*x_c_MON -> 27857108 | AD13: =D13*(1-x_testy) -> 0 | AE13: =E13*(1-x_testy) -> 0 | AF13: =F13*x_NAV -> 0 | AG13: =G13*x_FIX*(1-x_testy) -> 0 | AH13: =x_z_F*U13+(1-x_AGRI)*x_EMP*x_WLOSS*(x_PEN_K74*Q13+x_PEN_C22*R13) -> 34181418 | AI13: =x_AGRI*x_EMP*x_WLOSS*(x_PEN_K74*Q13+x_PEN_C22*R13) -> 2022262.8 | AJ13: =x_EMP*x_WAGE*(x_WLOSS*(Q13+R13)+S13)+U13*x_ABS_D*x_WAGE/365 -> 7.7406236e+08 | AK13: =AJ13*x_R_FUS -> 2.4491333e+08 | AL13: =AJ13*x_R_NFZ -> 60114457 | AM13: =AJ13*x_R_PIT -> 51462897 | AN13: =AJ13*x_R_FP -> 19738590 | AO13: =AA13+AB13+AC13+AD13+AF13 -> 4.9124457e+08 | AP13: =AO13+AE13+AG13+AH13+AI13+AK13+AL13+AM13+AN13 -> 9.0367753e+08 | AQ13: =AO13+AE13+AG13+AJ13 -> 1.2653069e+09 | AR13: =AB13+AC13+AD13+AF13 -> 1.3783343e+08 | AS13: =AR13+AE13+AG13 -> 1.3783343e+08
A14: 2037 | B14: 11 | C14: 4832 | D14: 0 | E14: 0 | F14: 0 | G14: 0 | H14: 2191.641 | I14: 317.272 | J14: 1773.162 | K14: 3028.659 | L14: 1359.685 | M14: 50443.854 | N14: 5448.712 | O14: 99.815 | P14: 99.254 | Q14: 2495.901 | R14: 2376.368 | S14: 7961.997 | T14: 2508.913 | U14: 1771.303 | V14: 127675.31 | W14: 349.101 | X14: 909.555 | Y14: 99.815 | Z14: 1069.102 | AA14: =H14*x_c_F+I14*x_c_CC+J14*x_c_DC+K14*x_c_HCC+L14*x_c_PLT+M14*x_c_SVRn+N14*x_c_SVRcc+O14*x_c_LT+P14*x_c_LT1 -> 3.5865842e+08 | AB14: =C14*x_c_DAA -> 109976320 | AC14: =C14*x_c_MON -> 27857108 | AD14: =D14*(1-x_testy) -> 0 | AE14: =E14*(1-x_testy) -> 0 | AF14: =F14*x_NAV -> 0 | AG14: =G14*x_FIX*(1-x_testy) -> 0 | AH14: =x_z_F*U14+(1-x_AGRI)*x_EMP*x_WLOSS*(x_PEN_K74*Q14+x_PEN_C22*R14) -> 34899167 | AI14: =x_AGRI*x_EMP*x_WLOSS*(x_PEN_K74*Q14+x_PEN_C22*R14) -> 2066063 | AJ14: =x_EMP*x_WAGE*(x_WLOSS*(Q14+R14)+S14)+U14*x_ABS_D*x_WAGE/365 -> 8.4352347e+08 | AK14: =AJ14*x_R_FUS -> 2.6689083e+08 | AL14: =AJ14*x_R_NFZ -> 65508876 | AM14: =AJ14*x_R_PIT -> 56080961 | AN14: =AJ14*x_R_FP -> 21509849 | AO14: =AA14+AB14+AC14+AD14+AF14 -> 4.9649185e+08 | AP14: =AO14+AE14+AG14+AH14+AI14+AK14+AL14+AM14+AN14 -> 9.4344759e+08 | AQ14: =AO14+AE14+AG14+AJ14 -> 1.3400153e+09 | AR14: =AB14+AC14+AD14+AF14 -> 1.3783343e+08 | AS14: =AR14+AE14+AG14 -> 1.3783343e+08
... A52: 2075 | B52: 49 | C52: 4832 | D52: 0 | E52: 0 | F52: 0 | G52: 0 | H52: 2271.489 | I52: 204.107 | J52: 1044.371 | K52: 1799.285 | L52: 653.433 | M52: 145579.1 | N52: 7858.827 | O52: 59.309 | P52: 59.421 | Q52: 619.875 | R52: 914.784 | S52: 2543.413 | T52: 2475.596 | U52: 1832.581 | V52: 180081.99 | W52: 192.859 | X52: 522.913 | Y52: 59.309 | Z52: 630.688 | AA52: =H52*x_c_F+I52*x_c_CC+J52*x_c_DC+K52*x_c_HCC+L52*x_c_PLT+M52*x_c_SVRn+N52*x_c_SVRcc+O52*x_c_LT+P52*x_c_LT1 -> 2.9446164e+08 | AB52: =C52*x_c_DAA -> 109976320 | AC52: =C52*x_c_MON -> 27857108 | AD52: =D52*(1-x_testy) -> 0 | AE52: =E52*(1-x_testy) -> 0 | AF52: =F52*x_NAV -> 0 | AG52: =G52*x_FIX*(1-x_testy) -> 0 | AH52: =x_z_F*U52+(1-x_AGRI)*x_EMP*x_WLOSS*(x_PEN_K74*Q52+x_PEN_C22*R52) -> 13749551 | AI52: =x_AGRI*x_EMP*x_WLOSS*(x_PEN_K74*Q52+x_PEN_C22*R52) -> 659786.77 | AJ52: =x_EMP*x_WAGE*(x_WLOSS*(Q52+R52)+S52)+U52*x_ABS_D*x_WAGE/365 -> 2.7246735e+08 | AK52: =AJ52*x_R_FUS -> 86208670 | AL52: =AJ52*x_R_NFZ -> 21160087 | AM52: =AJ52*x_R_PIT -> 18114767 | AN52: =AJ52*x_R_FP -> 6947917.5 | AO52: =AA52+AB52+AC52+AD52+AF52 -> 4.3229507e+08 | AP52: =AO52+AE52+AG52+AH52+AI52+AK52+AL52+AM52+AN52 -> 5.7913585e+08 | AQ52: =AO52+AE52+AG52+AJ52 -> 7.0476242e+08 | AR52: =AB52+AC52+AD52+AF52 -> 1.3783343e+08 | AS52: =AR52+AE52+AG52 -> 1.3783343e+08

Sheet L_I3
A1: I3: Populacje kluczowe: OST, redukcja szkód, więzienia (+2 mln zł/rok) – liczebności (silnik, wartości) i koszty (formuły), zł/rok, niezdyskontowane. Szacunek modelu.
A2: rok | B2: t | C2: treated | D2: NFZ_diag | E2: MZ_SW | F2: nNAV | G2: FIXon | H2: cF03 | I2: cF4 | J2: cDC | K2: cHCC | L2: cPLT | M2: cSVn | N2: cSVc | O2: cLTn | P2: cLT1 | Q2: wAdv | R2: wHCC | S2: wGH | T2: cAbs | U2: cAbsW | V2: QALY | W2: newDC | X2: newHCC | Y2: LT | Z2: liverD | AA2: NFZ_med | AB2: NFZ_DAA | AC2: NFZ_mon | AD2: NFZ_diag_k | AE2: MZ_SW_k | AF2: NAV_k | AG2: FIX_k | AH2: ZUS | AI2: KRUS | AJ2: lostw | AK2: lost_FUS | AL2: lost_NFZ | AM2: lost_PIT | AN2: lost_FP | AO2: NFZ | AP2: PUBLIC | AQ2: SOCIETAL | AR2: INV_NFZ | AS2: INV_PUB
A3: 2026 | B3: 0 | C3: 5255.342 | D3: 0 | E3: 666666.67 | F3: 0 | G3: 0 | H3: 2598.107 | I3: 233.09 | J3: 1579.13 | K3: 2524.31 | L3: 1540.438 | M3: 7115.529 | N3: 631.905 | O3: 89.046 | P3: 44.523 | Q3: 2134.57 | R3: 1702.953 | S3: 312.377 | T3: 2831.198 | U3: 1568.309 | V3: 113437.83 | W3: 265.295 | X3: 710.527 | Y3: 89.046 | Z3: 922.327 | AA3: =H3*x_c_F+I3*x_c_CC+J3*x_c_DC+K3*x_c_HCC+L3*x_c_PLT+M3*x_c_SVRn+N3*x_c_SVRcc+O3*x_c_LT+P3*x_c_LT1 -> 2.8390788e+08 | AB3: =C3*x_c_DAA -> 1.1961158e+08 | AC3: =C3*x_c_MON -> 30297729 | AD3: =D3*(1-x_testy) -> 0 | AE3: =E3*(1-x_testy) -> 666666.67 | AF3: =F3*x_NAV -> 0 | AG3: =G3*x_FIX*(1-x_testy) -> 0 | AH3: =x_z_F*U3+(1-x_AGRI)*x_EMP*x_WLOSS*(x_PEN_K74*Q3+x_PEN_C22*R3) -> 27705020 | AI3: =x_AGRI*x_EMP*x_WLOSS*(x_PEN_K74*Q3+x_PEN_C22*R3) -> 1618128.8 | AJ3: =x_EMP*x_WAGE*(x_WLOSS*(Q3+R3)+S3)+U3*x_ABS_D*x_WAGE/365 -> 1.5684805e+08 | AK3: =AJ3*x_R_FUS -> 49626724 | AL3: =AJ3*x_R_NFZ -> 12180977 | AM3: =AJ3*x_R_PIT -> 10427913 | AN3: =AJ3*x_R_FP -> 3999625.4 | AO3: =AA3+AB3+AC3+AD3+AF3 -> 4.3381719e+08 | AP3: =AO3+AE3+AG3+AH3+AI3+AK3+AL3+AM3+AN3 -> 5.4004225e+08 | AQ3: =AO3+AE3+AG3+AJ3 -> 5.9133192e+08 | AR3: =AB3+AC3+AD3+AF3 -> 1.4990931e+08 | AS3: =AR3+AE3+AG3 -> 1.5057598e+08
A4: 2027 | B4: 1 | C4: 5606.997 | D4: 0 | E4: 1333333.3 | F4: 0 | G4: 0 | H4: 2707.185 | I4: 257.606 | J4: 1563.283 | K4: 2519.483 | L4: 1489.389 | M4: 11955.248 | N4: 1093.52 | O4: 87.887 | P4: 88.466 | Q4: 2137.46 | R4: 1715.624 | S4: 939.861 | T4: 2964.79 | U4: 1690.615 | V4: 114603.63 | W4: 274.089 | X4: 738.756 | Y4: 87.887 | Z4: 925.413 | AA4: =H4*x_c_F+I4*x_c_CC+J4*x_c_DC+K4*x_c_HCC+L4*x_c_PLT+M4*x_c_SVRn+N4*x_c_SVRcc+O4*x_c_LT+P4*x_c_LT1 -> 2.8807147e+08 | AB4: =C4*x_c_DAA -> 1.2761525e+08 | AC4: =C4*x_c_MON -> 32325066 | AD4: =D4*(1-x_testy) -> 0 | AE4: =E4*(1-x_testy) -> 1333333.3 | AF4: =F4*x_NAV -> 0 | AG4: =G4*x_FIX*(1-x_testy) -> 0 | AH4: =x_z_F*U4+(1-x_AGRI)*x_EMP*x_WLOSS*(x_PEN_K74*Q4+x_PEN_C22*R4) -> 28060470 | AI4: =x_AGRI*x_EMP*x_WLOSS*(x_PEN_K74*Q4+x_PEN_C22*R4) -> 1625003.1 | AJ4: =x_EMP*x_WAGE*(x_WLOSS*(Q4+R4)+S4)+U4*x_ABS_D*x_WAGE/365 -> 2.1121624e+08 | AK4: =AJ4*x_R_FUS -> 66828820 | AL4: =AJ4*x_R_NFZ -> 16403265 | AM4: =AJ4*x_R_PIT -> 14042538 | AN4: =AJ4*x_R_FP -> 5386014.2 | AO4: =AA4+AB4+AC4+AD4+AF4 -> 4.4801179e+08 | AP4: =AO4+AE4+AG4+AH4+AI4+AK4+AL4+AM4+AN4 -> 5.8169123e+08 | AQ4: =AO4+AE4+AG4+AJ4 -> 6.6056136e+08 | AR4: =AB4+AC4+AD4+AF4 -> 1.5994032e+08 | AS4: =AR4+AE4+AG4 -> 1.6127365e+08
A5: 2028 | B5: 2 | C5: 5797.642 | D5: 0 | E5: 2000000 | F5: 0 | G5: 0 | H5: 2677.754 | I5: 270.762 | J5: 1558.935 | K5: 2543.268 | L5: 1475.755 | M5: 16573.871 | N5: 1565.518 | O5: 87.521 | P5: 87.704 | Q5: 2145.232 | R5: 1751.394 | S5: 1572.438 | T5: 2948.516 | U5: 1726.425 | V5: 115858.78 | W5: 284.414 | X5: 767.511 | Y5: 87.521 | Z5: 926.051 | AA5: =H5*x_c_F+I5*x_c_CC+J5*x_c_DC+K5*x_c_HCC+L5*x_c_PLT+M5*x_c_SVRn+N5*x_c_SVRcc+O5*x_c_LT+P5*x_c_LT1 -> 2.9299924e+08 | AB5: =C5*x_c_DAA -> 1.3195433e+08 | AC5: =C5*x_c_MON -> 33424159 | AD5: =D5*(1-x_testy) -> 0 | AE5: =E5*(1-x_testy) -> 2000000 | AF5: =F5*x_NAV -> 0 | AG5: =G5*x_FIX*(1-x_testy) -> 0 | AH5: =x_z_F*U5+(1-x_AGRI)*x_EMP*x_WLOSS*(x_PEN_K74*Q5+x_PEN_C22*R5) -> 28425361 | AI5: =x_AGRI*x_EMP*x_WLOSS*(x_PEN_K74*Q5+x_PEN_C22*R5) -> 1644255.4 | AJ5: =x_EMP*x_WAGE*(x_WLOSS*(Q5+R5)+S5)+U5*x_ABS_D*x_WAGE/365 -> 2.6668045e+08 | AK5: =AJ5*x_R_FUS -> 84377695 | AL5: =AJ5*x_R_NFZ -> 20710671 | AM5: =AJ5*x_R_PIT -> 17730030 | AN5: =AJ5*x_R_FP -> 6800351.5 | AO5: =AA5+AB5+AC5+AD5+AF5 -> 4.5837774e+08 | AP5: =AO5+AE5+AG5+AH5+AI5+AK5+AL5+AM5+AN5 -> 6.200661e+08 | AQ5: =AO5+AE5+AG5+AJ5 -> 7.2705819e+08 | AR5: =AB5+AC5+AD5+AF5 -> 1.6537849e+08 | AS5: =AR5+AE5+AG5 -> 1.6737849e+08
A6: 2029 | B6: 3 | C6: 5552.364 | D6: 0 | E6: 2000000 | F6: 0 | G6: 0 | H6: 2563.507 | I6: 275.508 | J6: 1565.332 | K6: 2587.857 | L6: 1461.147 | M6: 20839.819 | N6: 2030.629 | O6: 87.84 | P6: 87.68 | Q6: 2161.989 | R6: 1804.222 | S6: 2212.679 | T6: 2839.015 | U6: 1704.469 | V6: 117171.5 | W6: 295.843 | X6: 796.633 | Y6: 87.84 | Z6: 934.429 | AA6: =H6*x_c_F+I6*x_c_CC+J6*x_c_DC+K6*x_c_HCC+L6*x_c_PLT+M6*x_c_SVRn+N6*x_c_SVRcc+O6*x_c_LT+P6*x_c_LT1 -> 2.9913671e+08 | AB6: =C6*x_c_DAA -> 1.263718e+08 | AC6: =C6*x_c_MON -> 32010100 | AD6: =D6*(1-x_testy) -> 0 | AE6: =E6*(1-x_testy) -> 2000000 | AF6: =F6*x_NAV -> 0 | AG6: =G6*x_FIX*(1-x_testy) -> 0 | AH6: =x_z_F*U6+(1-x_AGRI)*x_EMP*x_WLOSS*(x_PEN_K74*Q6+x_PEN_C22*R6) -> 28842142 | AI6: =x_AGRI*x_EMP*x_WLOSS*(x_PEN_K74*Q6+x_PEN_C22*R6) -> 1674787.4 | AJ6: =x_EMP*x_WAGE*(x_WLOSS*(Q6+R6)+S6)+U6*x_ABS_D*x_WAGE/365 -> 3.2348084e+08 | AK6: =AJ6*x_R_FUS -> 1.0234934e+08 | AL6: =AJ6*x_R_NFZ -> 25121846 | AM6: =AJ6*x_R_PIT -> 21506357 | AN6: =AJ6*x_R_FP -> 8248761.5 | AO6: =AA6+AB6+AC6+AD6+AF6 -> 4.5751861e+08 | AP6: =AO6+AE6+AG6+AH6+AI6+AK6+AL6+AM6+AN6 -> 6.4726185e+08 | AQ6: =AO6+AE6+AG6+AJ6 -> 7.8299946e+08 | AR6: =AB6+AC6+AD6+AF6 -> 1.583819e+08 | AS6: =AR6+AE6+AG6 -> 1.603819e+08
A7: 2030 | B7: 4 | C7: 5369.388 | D7: 0 | E7: 2000000 | F7: 0 | G7: 0 | H7: 2475.175 | I7: 281.769 | J7: 1581.138 | K7: 2646.738 | L7: 1446.195 | M7: 24856.949 | N7: 2491.337 | O7: 88.741 | P7: 88.29 | Q7: 2187.098 | R7: 1869.186 | S7: 2865.652 | T7: 2756.945 | U7: 1694.364 | V7: 118525.41 | W7: 307.422 | X7: 824.495 | Y7: 88.741 | Z7: 948.66 | AA7: =H7*x_c_F+I7*x_c_CC+J7*x_c_DC+K7*x_c_HCC+L7*x_c_PLT+M7*x_c_SVRn+N7*x_c_SVRcc+O7*x_c_LT+P7*x_c_LT1 -> 3.0648199e+08 | AB7: =C7*x_c_DAA -> 1.2220727e+08 | AC7: =C7*x_c_MON -> 30955219 | AD7: =D7*(1-x_testy) -> 0 | AE7: =E7*(1-x_testy) -> 2000000 | AF7: =F7*x_NAV -> 0 | AG7: =G7*x_FIX*(1-x_testy) -> 0 | AH7: =x_z_F*U7+(1-x_AGRI)*x_EMP*x_WLOSS*(x_PEN_K74*Q7+x_PEN_C22*R7) -> 29416485 | AI7: =x_AGRI*x_EMP*x_WLOSS*(x_PEN_K74*Q7+x_PEN_C22*R7) -> 1714123.6 | AJ7: =x_EMP*x_WAGE*(x_WLOSS*(Q7+R7)+S7)+U7*x_ABS_D*x_WAGE/365 -> 3.8207218e+08 | AK7: =AJ7*x_R_FUS -> 1.2088764e+08 | AL7: =AJ7*x_R_NFZ -> 29672108 | AM7: =AJ7*x_R_PIT -> 25401753 | AN7: =AJ7*x_R_FP -> 9742840.7 | AO7: =AA7+AB7+AC7+AD7+AF7 -> 4.5964448e+08 | AP7: =AO7+AE7+AG7+AH7+AI7+AK7+AL7+AM7+AN7 -> 6.7847943e+08 | AQ7: =AO7+AE7+AG7+AJ7 -> 8.4371667e+08 | AR7: =AB7+AC7+AD7+AF7 -> 1.5316249e+08 | AS7: =AR7+AE7+AG7 -> 1.5516249e+08
A8: 2031 | B8: 5 | C8: 5232.888 | D8: 0 | E8: 2000000 | F8: 0 | G8: 0 | H8: 2406.594 | I8: 288.76 | J8: 1604.414 | K8: 2713.844 | L8: 1431.431 | M8: 28691.697 | N8: 2948.544 | O8: 90.094 | P8: 89.418 | Q8: 2219.499 | R8: 1941.889 | S8: 3534.934 | T8: 2695.355 | U8: 1693.33 | V8: 119905.41 | W8: 318.443 | X8: 849.906 | Y8: 90.094 | Z8: 966.845 | AA8: =H8*x_c_F+I8*x_c_CC+J8*x_c_DC+K8*x_c_HCC+L8*x_c_PLT+M8*x_c_SVRn+N8*x_c_SVRcc+O8*x_c_LT+P8*x_c_LT1 -> 3.1460607e+08 | AB8: =C8*x_c_DAA -> 1.1910053e+08 | AC8: =C8*x_c_MON -> 30168279 | AD8: =D8*(1-x_testy) -> 0 | AE8: =E8*(1-x_testy) -> 2000000 | AF8: =F8*x_NAV -> 0 | AG8: =G8*x_FIX*(1-x_testy) -> 0 | AH8: =x_z_F*U8+(1-x_AGRI)*x_EMP*x_WLOSS*(x_PEN_K74*Q8+x_PEN_C22*R8) -> 30106243 | AI8: =x_AGRI*x_EMP*x_WLOSS*(x_PEN_K74*Q8+x_PEN_C22*R8) -> 1759855.7 | AJ8: =x_EMP*x_WAGE*(x_WLOSS*(Q8+R8)+S8)+U8*x_ABS_D*x_WAGE/365 -> 4.4257267e+08 | AK8: =AJ8*x_R_FUS -> 1.4002999e+08 | AL8: =AJ8*x_R_NFZ -> 34370636 | AM8: =AJ8*x_R_PIT -> 29424078 | AN8: =AJ8*x_R_FP -> 11285603 | AO8: =AA8+AB8+AC8+AD8+AF8 -> 4.6387488e+08 | AP8: =AO8+AE8+AG8+AH8+AI8+AK8+AL8+AM8+AN8 -> 7.1285129e+08 | AQ8: =AO8+AE8+AG8+AJ8 -> 9.0844755e+08 | AR8: =AB8+AC8+AD8+AF8 -> 1.4926881e+08 | AS8: =AR8+AE8+AG8 -> 1.5126881e+08
A9: 2032 | B9: 6 | C9: 5131.06 | D9: 0 | E9: 2000000 | F9: 0 | G9: 0 | H9: 2353.167 | I9: 295.878 | J9: 1632.909 | K9: 2783.763 | L9: 1417.236 | M9: 32386.413 | N9: 3401.9 | O9: 91.753 | P9: 90.924 | Q9: 2257.849 | R9: 2018.512 | S9: 4222.64 | T9: 2649.045 | U9: 1699.155 | V9: 121296.75 | W9: 328.379 | X9: 871.99 | Y9: 91.753 | Z9: 987.155 | AA9: =H9*x_c_F+I9*x_c_CC+J9*x_c_DC+K9*x_c_HCC+L9*x_c_PLT+M9*x_c_SVRn+N9*x_c_SVRcc+O9*x_c_LT+P9*x_c_LT1 -> 3.2309149e+08 | AB9: =C9*x_c_DAA -> 1.1678293e+08 | AC9: =C9*x_c_MON -> 29581227 | AD9: =D9*(1-x_testy) -> 0 | AE9: =E9*(1-x_testy) -> 2000000 | AF9: =F9*x_NAV -> 0 | AG9: =G9*x_FIX*(1-x_testy) -> 0 | AH9: =x_z_F*U9+(1-x_AGRI)*x_EMP*x_WLOSS*(x_PEN_K74*Q9+x_PEN_C22*R9) -> 30872681 | AI9: =x_AGRI*x_EMP*x_WLOSS*(x_PEN_K74*Q9+x_PEN_C22*R9) -> 1809724.3 | AJ9: =x_EMP*x_WAGE*(x_WLOSS*(Q9+R9)+S9)+U9*x_ABS_D*x_WAGE/365 -> 5.0498717e+08 | AK9: =AJ9*x_R_FUS -> 1.5977794e+08 | AL9: =AJ9*x_R_NFZ -> 39217809 | AM9: =AJ9*x_R_PIT -> 33573655 | AN9: =AJ9*x_R_FP -> 12877173 | AO9: =AA9+AB9+AC9+AD9+AF9 -> 4.6945565e+08 | AP9: =AO9+AE9+AG9+AH9+AI9+AK9+AL9+AM9+AN9 -> 7.4958463e+08 | AQ9: =AO9+AE9+AG9+AJ9 -> 9.7644282e+08 | AR9: =AB9+AC9+AD9+AF9 -> 1.4636415e+08 | AS9: =AR9+AE9+AG9 -> 1.4836415e+08
A10: 2033 | B10: 7 | C10: 5055.097 | D10: 0 | E10: 2000000 | F10: 0 | G10: 0 | H10: 2311.468 | I10: 302.661 | J10: 1664.312 | K10: 2851.9 | L10: 1403.852 | M10: 35967.6 | N10: 3850.137 | O10: 93.575 | P10: 92.664 | Q10: 2300.67 | R10: 2095.841 | S10: 4929.589 | T10: 2614.129 | U10: 1710.082 | V10: 122686.7 | W10: 336.864 | X10: 890.174 | Y10: 93.575 | Z10: 1007.992 | AA10: =H10*x_c_F+I10*x_c_CC+J10*x_c_DC+K10*x_c_HCC+L10*x_c_PLT+M10*x_c_SVRn+N10*x_c_SVRcc+O10*x_c_LT+P10*x_c_LT1 -> 3.3155952e+08 | AB10: =C10*x_c_DAA -> 1.1505401e+08 | AC10: =C10*x_c_MON -> 29143291 | AD10: =D10*(1-x_testy) -> 0 | AE10: =E10*(1-x_testy) -> 2000000 | AF10: =F10*x_NAV -> 0 | AG10: =G10*x_FIX*(1-x_testy) -> 0 | AH10: =x_z_F*U10+(1-x_AGRI)*x_EMP*x_WLOSS*(x_PEN_K74*Q10+x_PEN_C22*R10) -> 31681329 | AI10: =x_AGRI*x_EMP*x_WLOSS*(x_PEN_K74*Q10+x_PEN_C22*R10) -> 1861689.5 | AJ10: =x_EMP*x_WAGE*(x_WLOSS*(Q10+R10)+S10)+U10*x_ABS_D*x_WAGE/365 -> 5.6922678e+08 | AK10: =AJ10*x_R_FUS -> 1.8010335e+08 | AL10: =AJ10*x_R_NFZ -> 44206721 | AM10: =AJ10*x_R_PIT -> 37844572 | AN10: =AJ10*x_R_FP -> 14515283 | AO10: =AA10+AB10+AC10+AD10+AF10 -> 4.7575682e+08 | AP10: =AO10+AE10+AG10+AH10+AI10+AK10+AL10+AM10+AN10 -> 7.8796976e+08 | AQ10: =AO10+AE10+AG10+AJ10 -> 1.0469836e+09 | AR10: =AB10+AC10+AD10+AF10 -> 1.441973e+08 | AS10: =AR10+AE10+AG10 -> 1.461973e+08
A11: 2034 | B11: 8 | C11: 4998.429 | D11: 0 | E11: 2000000 | F11: 0 | G11: 0 | H11: 2278.948 | I11: 308.756 | J11: 1696.398 | K11: 2914.495 | L11: 1391.371 | M11: 39451.348 | N11: 4291.263 | O11: 95.423 | P11: 94.499 | Q11: 2346.449 | R11: 2171.246 | S11: 5655.42 | T11: 2587.705 | U11: 1724.72 | V11: 124064.59 | W11: 343.652 | X11: 904.088 | Y11: 95.423 | Z11: 1027.941 | AA11: =H11*x_c_F+I11*x_c_CC+J11*x_c_DC+K11*x_c_HCC+L11*x_c_PLT+M11*x_c_SVRn+N11*x_c_SVRcc+O11*x_c_LT+P11*x_c_LT1 -> 3.3967782e+08 | AB11: =C11*x_c_DAA -> 1.1376424e+08 | AC11: =C11*x_c_MON -> 28816592 | AD11: =D11*(1-x_testy) -> 0 | AE11: =E11*(1-x_testy) -> 2000000 | AF11: =F11*x_NAV -> 0 | AG11: =G11*x_FIX*(1-x_testy) -> 0 | AH11: =x_z_F*U11+(1-x_AGRI)*x_EMP*x_WLOSS*(x_PEN_K74*Q11+x_PEN_C22*R11) -> 32502246 | AI11: =x_AGRI*x_EMP*x_WLOSS*(x_PEN_K74*Q11+x_PEN_C22*R11) -> 1913961.3 | AJ11: =x_EMP*x_WAGE*(x_WLOSS*(Q11+R11)+S11)+U11*x_ABS_D*x_WAGE/365 -> 6.3512101e+08 | AK11: =AJ11*x_R_FUS -> 2.0095229e+08 | AL11: =AJ11*x_R_NFZ -> 49324133 | AM11: =AJ11*x_R_PIT -> 42225496 | AN11: =AJ11*x_R_FP -> 16195586 | AO11: =AA11+AB11+AC11+AD11+AF11 -> 4.8225866e+08 | AP11: =AO11+AE11+AG11+AH11+AI11+AK11+AL11+AM11+AN11 -> 8.2737237e+08 | AQ11: =AO11+AE11+AG11+AJ11 -> 1.1193797e+09 | AR11: =AB11+AC11+AD11+AF11 -> 1.4258084e+08 | AS11: =AR11+AE11+AG11 -> 1.4458084e+08
A12: 2035 | B12: 9 | C12: 4956.155 | D12: 0 | E12: 2000000 | F12: 0 | G12: 0 | H12: 2233.411 | I12: 311.045 | J12: 1727.151 | K12: 2968.625 | L12: 1379.757 | M12: 42808.232 | N12: 4717.248 | O12: 97.182 | P12: 96.303 | Q12: 2393.702 | R12: 2242.639 | S12: 6398.749 | T12: 2544.456 | U12: 1726.125 | V12: 125419.77 | W12: 348.614 | X12: 913.592 | Y12: 97.182 | Z12: 1045.883 | AA12: =H12*x_c_F+I12*x_c_CC+J12*x_c_DC+K12*x_c_HCC+L12*x_c_PLT+M12*x_c_SVRn+N12*x_c_SVRcc+O12*x_c_LT+P12*x_c_LT1 -> 3.4705703e+08 | AB12: =C12*x_c_DAA -> 1.1280209e+08 | AC12: =C12*x_c_MON -> 28572877 | AD12: =D12*(1-x_testy) -> 0 | AE12: =E12*(1-x_testy) -> 2000000 | AF12: =F12*x_NAV -> 0 | AG12: =G12*x_FIX*(1-x_testy) -> 0 | AH12: =x_z_F*U12+(1-x_AGRI)*x_EMP*x_WLOSS*(x_PEN_K74*Q12+x_PEN_C22*R12) -> 33277398 | AI12: =x_AGRI*x_EMP*x_WLOSS*(x_PEN_K74*Q12+x_PEN_C22*R12) -> 1965006.5 | AJ12: =x_EMP*x_WAGE*(x_WLOSS*(Q12+R12)+S12)+U12*x_ABS_D*x_WAGE/365 -> 7.023852e+08 | AK12: =AJ12*x_R_FUS -> 2.2223468e+08 | AL12: =AJ12*x_R_NFZ -> 54547937 | AM12: =AJ12*x_R_PIT -> 46697500 | AN12: =AJ12*x_R_FP -> 17910823 | AO12: =AA12+AB12+AC12+AD12+AF12 -> 4.8843199e+08 | AP12: =AO12+AE12+AG12+AH12+AI12+AK12+AL12+AM12+AN12 -> 8.6706533e+08 | AQ12: =AO12+AE12+AG12+AJ12 -> 1.1928172e+09 | AR12: =AB12+AC12+AD12+AF12 -> 1.4137497e+08 | AS12: =AR12+AE12+AG12 -> 1.4337497e+08
A13: 2036 | B13: 10 | C13: 4832 | D13: 0 | E13: 0 | F13: 0 | G13: 0 | H13: 2198.942 | I13: 312.9 | J13: 1754.89 | K13: 3012.321 | L13: 1368.839 | M13: 46062.489 | N13: 5126.734 | O13: 98.744 | P13: 97.963 | Q13: 2441.11 | R13: 2308.595 | S13: 7157.314 | T13: 2511.842 | U13: 1733.198 | V13: 126745.52 | W13: 351.872 | X13: 919.084 | Y13: 98.744 | Z13: 1060.862 | AA13: =H13*x_c_F+I13*x_c_CC+J13*x_c_DC+K13*x_c_HCC+L13*x_c_PLT+M13*x_c_SVRn+N13*x_c_SVRcc+O13*x_c_LT+P13*x_c_LT1 -> 3.5359581e+08 | AB13: =C13*x_c_DAA -> 109976320 | AC13: =C13*x_c_MON -> 27857108 | AD13: =D13*(1-x_testy) -> 0 | AE13: =E13*(1-x_testy) -> 0 | AF13: =F13*x_NAV -> 0 | AG13: =G13*x_FIX*(1-x_testy) -> 0 | AH13: =x_z_F*U13+(1-x_AGRI)*x_EMP*x_WLOSS*(x_PEN_K74*Q13+x_PEN_C22*R13) -> 34027968 | AI13: =x_AGRI*x_EMP*x_WLOSS*(x_PEN_K74*Q13+x_PEN_C22*R13) -> 2013656.6 | AJ13: =x_EMP*x_WAGE*(x_WLOSS*(Q13+R13)+S13)+U13*x_ABS_D*x_WAGE/365 -> 7.7079217e+08 | AK13: =AJ13*x_R_FUS -> 2.4387864e+08 | AL13: =AJ13*x_R_NFZ -> 59860491 | AM13: =AJ13*x_R_PIT -> 51245481 | AN13: =AJ13*x_R_FP -> 19655200 | AO13: =AA13+AB13+AC13+AD13+AF13 -> 4.9142924e+08 | AP13: =AO13+AE13+AG13+AH13+AI13+AK13+AL13+AM13+AN13 -> 9.0211068e+08 | AQ13: =AO13+AE13+AG13+AJ13 -> 1.2622214e+09 | AR13: =AB13+AC13+AD13+AF13 -> 1.3783343e+08 | AS13: =AR13+AE13+AG13 -> 1.3783343e+08
A14: 2037 | B14: 11 | C14: 4832 | D14: 0 | E14: 0 | F14: 0 | G14: 0 | H14: 2193.393 | I14: 316.901 | J14: 1778.137 | K14: 3044.075 | L14: 1358.326 | M14: 49266.657 | N14: 5523.249 | O14: 100.037 | P14: 99.39 | Q14: 2487.421 | R14: 2368.003 | S14: 7928.112 | T14: 2510.293 | U14: 1760.208 | V14: 128036.8 | W14: 353.153 | X14: 920.007 | Y14: 100.037 | Z14: 1072.33 | AA14: =H14*x_c_F+I14*x_c_CC+J14*x_c_DC+K14*x_c_HCC+L14*x_c_PLT+M14*x_c_SVRn+N14*x_c_SVRcc+O14*x_c_LT+P14*x_c_LT1 -> 3.5924314e+08 | AB14: =C14*x_c_DAA -> 109976320 | AC14: =C14*x_c_MON -> 27857108 | AD14: =D14*(1-x_testy) -> 0 | AE14: =E14*(1-x_testy) -> 0 | AF14: =F14*x_NAV -> 0 | AG14: =G14*x_FIX*(1-x_testy) -> 0 | AH14: =x_z_F*U14+(1-x_AGRI)*x_EMP*x_WLOSS*(x_PEN_K74*Q14+x_PEN_C22*R14) -> 34768167 | AI14: =x_AGRI*x_EMP*x_WLOSS*(x_PEN_K74*Q14+x_PEN_C22*R14) -> 2058911.9 | AJ14: =x_EMP*x_WAGE*(x_WLOSS*(Q14+R14)+S14)+U14*x_ABS_D*x_WAGE/365 -> 8.4005047e+08 | AK14: =AJ14*x_R_FUS -> 2.6579197e+08 | AL14: =AJ14*x_R_NFZ -> 65239159 | AM14: =AJ14*x_R_PIT -> 55850061 | AN14: =AJ14*x_R_FP -> 21421287 | AO14: =AA14+AB14+AC14+AD14+AF14 -> 4.9707657e+08 | AP14: =AO14+AE14+AG14+AH14+AI14+AK14+AL14+AM14+AN14 -> 9.4220612e+08 | AQ14: =AO14+AE14+AG14+AJ14 -> 1.337127e+09 | AR14: =AB14+AC14+AD14+AF14 -> 1.3783343e+08 | AS14: =AR14+AE14+AG14 -> 1.3783343e+08
... A52: 2075 | B52: 49 | C52: 4832 | D52: 0 | E52: 0 | F52: 0 | G52: 0 | H52: 2269.909 | I52: 206.584 | J52: 1062.729 | K52: 1828.829 | L52: 662.44 | M52: 144454.98 | N52: 7916.399 | O52: 60.334 | P52: 60.454 | Q52: 626.588 | R52: 924.601 | S52: 2568.132 | T52: 2476.493 | U52: 1830.387 | V52: 179707.1 | W52: 196.122 | X52: 531.219 | Y52: 60.334 | Z52: 641.121 | AA52: =H52*x_c_F+I52*x_c_CC+J52*x_c_DC+K52*x_c_HCC+L52*x_c_PLT+M52*x_c_SVRn+N52*x_c_SVRcc+O52*x_c_LT+P52*x_c_LT1 -> 2.9681556e+08 | AB52: =C52*x_c_DAA -> 109976320 | AC52: =C52*x_c_MON -> 27857108 | AD52: =D52*(1-x_testy) -> 0 | AE52: =E52*(1-x_testy) -> 0 | AF52: =F52*x_NAV -> 0 | AG52: =G52*x_FIX*(1-x_testy) -> 0 | AH52: =x_z_F*U52+(1-x_AGRI)*x_EMP*x_WLOSS*(x_PEN_K74*Q52+x_PEN_C22*R52) -> 13852527 | AI52: =x_AGRI*x_EMP*x_WLOSS*(x_PEN_K74*Q52+x_PEN_C22*R52) -> 666891.45 | AJ52: =x_EMP*x_WAGE*(x_WLOSS*(Q52+R52)+S52)+U52*x_ABS_D*x_WAGE/365 -> 2.7510951e+08 | AK52: =AJ52*x_R_FUS -> 87044650 | AL52: =AJ52*x_R_NFZ -> 21365280 | AM52: =AJ52*x_R_PIT -> 18290429 | AN52: =AJ52*x_R_FP -> 7015292.6 | AO52: =AA52+AB52+AC52+AD52+AF52 -> 4.3464899e+08 | AP52: =AO52+AE52+AG52+AH52+AI52+AK52+AL52+AM52+AN52 -> 5.8288406e+08 | AQ52: =AO52+AE52+AG52+AJ52 -> 7.097585e+08 | AR52: =AB52+AC52+AD52+AF52 -> 1.3783343e+08 | AS52: =AR52+AE52+AG52 -> 1.3783343e+08

Sheet L_I4
A1: I4: Pakiet eliminacyjny WHO (test refleksyjny + 3 kanały) – liczebności (silnik, wartości) i koszty (formuły), zł/rok, niezdyskontowane. Szacunek modelu.
A2: rok | B2: t | C2: treated | D2: NFZ_diag | E2: MZ_SW | F2: nNAV | G2: FIXon | H2: cF03 | I2: cF4 | J2: cDC | K2: cHCC | L2: cPLT | M2: cSVn | N2: cSVc | O2: cLTn | P2: cLT1 | Q2: wAdv | R2: wHCC | S2: wGH | T2: cAbs | U2: cAbsW | V2: QALY | W2: newDC | X2: newHCC | Y2: LT | Z2: liverD | AA2: NFZ_med | AB2: NFZ_DAA | AC2: NFZ_mon | AD2: NFZ_diag_k | AE2: MZ_SW_k | AF2: NAV_k | AG2: FIX_k | AH2: ZUS | AI2: KRUS | AJ2: lostw | AK2: lost_FUS | AL2: lost_NFZ | AM2: lost_PIT | AN2: lost_FP | AO2: NFZ | AP2: PUBLIC | AQ2: SOCIETAL | AR2: INV_NFZ | AS2: INV_PUB
A3: 2026 | B3: 0 | C3: 6604.08 | D3: 83333333 | E3: 666666.67 | F3: 3087.2475 | G3: 1 | H3: 3495.035 | I3: 314.13 | J3: 1578.231 | K3: 2522.145 | L3: 1540.438 | M3: 9464.322 | N3: 841.774 | O3: 89.046 | P3: 44.523 | Q3: 2133.961 | R3: 1701.486 | S3: 312.377 | T3: 3809.166 | U3: 2112.518 | V3: 113580.74 | W3: 263.497 | X3: 706.196 | Y3: 89.046 | Z3: 922.327 | AA3: =H3*x_c_F+I3*x_c_CC+J3*x_c_DC+K3*x_c_HCC+L3*x_c_PLT+M3*x_c_SVRn+N3*x_c_SVRcc+O3*x_c_LT+P3*x_c_LT1 -> 2.8886299e+08 | AB3: =C3*x_c_DAA -> 1.5030886e+08 | AC3: =C3*x_c_MON -> 38073379 | AD3: =D3*(1-x_testy) -> 83333333 | AE3: =E3*(1-x_testy) -> 666666.67 | AF3: =F3*x_NAV -> 6195901.8 | AG3: =G3*x_FIX*(1-x_testy) -> 1223620.5 | AH3: =x_z_F*U3+(1-x_AGRI)*x_EMP*x_WLOSS*(x_PEN_K74*Q3+x_PEN_C22*R3) -> 28810171 | AI3: =x_AGRI*x_EMP*x_WLOSS*(x_PEN_K74*Q3+x_PEN_C22*R3) -> 1617223.8 | AJ3: =x_EMP*x_WAGE*(x_WLOSS*(Q3+R3)+S3)+U3*x_ABS_D*x_WAGE/365 -> 1.5837866e+08 | AK3: =AJ3*x_R_FUS -> 50111009 | AL3: =AJ3*x_R_NFZ -> 12299845 | AM3: =AJ3*x_R_PIT -> 10529674 | AN3: =AJ3*x_R_FP -> 4038655.9 | AO3: =AA3+AB3+AC3+AD3+AF3 -> 5.6677446e+08 | AP3: =AO3+AE3+AG3+AH3+AI3+AK3+AL3+AM3+AN3 -> 6.7607133e+08 | AQ3: =AO3+AE3+AG3+AJ3 -> 7.2704341e+08 | AR3: =AB3+AC3+AD3+AF3 -> 2.7791147e+08 | AS3: =AR3+AE3+AG3 -> 2.7980176e+08
A4: 2027 | B4: 1 | C4: 8213.934 | D4: 1.6666667e+08 | E4: 1333333.3 | F4: 5891.8719 | G4: 1 | H4: 4116.374 | I4: 391.935 | J4: 1558.839 | K4: 2508.909 | L4: 1489.389 | M4: 17064.208 | N4: 1564.733 | O4: 87.773 | P4: 88.409 | Q4: 2134.377 | R4: 1708.38 | S4: 939.398 | T4: 4508.309 | U4: 2573.588 | V4: 114922.5 | W4: 268.47 | X4: 725.015 | Y4: 87.773 | Z4: 924.058 | AA4: =H4*x_c_F+I4*x_c_CC+J4*x_c_DC+K4*x_c_HCC+L4*x_c_PLT+M4*x_c_SVRn+N4*x_c_SVRcc+O4*x_c_LT+P4*x_c_LT1 -> 2.9660343e+08 | AB4: =C4*x_c_DAA -> 1.8694914e+08 | AC4: =C4*x_c_MON -> 47354396 | AD4: =D4*(1-x_testy) -> 1.6666667e+08 | AE4: =E4*(1-x_testy) -> 1333333.3 | AF4: =F4*x_NAV -> 11824598 | AG4: =G4*x_FIX*(1-x_testy) -> 1223620.5 | AH4: =x_z_F*U4+(1-x_AGRI)*x_EMP*x_WLOSS*(x_PEN_K74*Q4+x_PEN_C22*R4) -> 29807717 | AI4: =x_AGRI*x_EMP*x_WLOSS*(x_PEN_K74*Q4+x_PEN_C22*R4) -> 1620504.2 | AJ4: =x_EMP*x_WAGE*(x_WLOSS*(Q4+R4)+S4)+U4*x_ABS_D*x_WAGE/365 -> 2.1343239e+08 | AK4: =AJ4*x_R_FUS -> 67530009 | AL4: =AJ4*x_R_NFZ -> 16575373 | AM4: =AJ4*x_R_PIT -> 14189876 | AN4: =AJ4*x_R_FP -> 5442526 | AO4: =AA4+AB4+AC4+AD4+AF4 -> 7.0939822e+08 | AP4: =AO4+AE4+AG4+AH4+AI4+AK4+AL4+AM4+AN4 -> 8.4712118e+08 | AQ4: =AO4+AE4+AG4+AJ4 -> 9.2538757e+08 | AR4: =AB4+AC4+AD4+AF4 -> 4.127948e+08 | AS4: =AR4+AE4+AG4 -> 4.1535175e+08
A5: 2028 | B5: 2 | C5: 9529.999 | D5: 250000000 | E5: 2000000 | F5: 8184.668 | G5: 1 | H5: 4271.595 | I5: 430.674 | J5: 1546.642 | K5: 2514.484 | L5: 1475.709 | M5: 24784.803 | N5: 2343.371 | O5: 87.074 | P5: 87.423 | Q5: 2136.479 | R5: 1731.424 | S5: 1569.682 | T5: 4702.269 | U5: 2755.558 | V5: 116388.8 | W5: 272.721 | X5: 738.709 | Y5: 87.074 | Z5: 920.763 | AA5: =H5*x_c_F+I5*x_c_CC+J5*x_c_DC+K5*x_c_HCC+L5*x_c_PLT+M5*x_c_SVRn+N5*x_c_SVRcc+O5*x_c_LT+P5*x_c_LT1 -> 3.035431e+08 | AB5: =C5*x_c_DAA -> 2.1690278e+08 | AC5: =C5*x_c_MON -> 54941682 | AD5: =D5*(1-x_testy) -> 250000000 | AE5: =E5*(1-x_testy) -> 2000000 | AF5: =F5*x_NAV -> 16426088 | AG5: =G5*x_FIX*(1-x_testy) -> 1223620.5 | AH5: =x_z_F*U5+(1-x_AGRI)*x_EMP*x_WLOSS*(x_PEN_K74*Q5+x_PEN_C22*R5) -> 30352000 | AI5: =x_AGRI*x_EMP*x_WLOSS*(x_PEN_K74*Q5+x_PEN_C22*R5) -> 1631752.1 | AJ5: =x_EMP*x_WAGE*(x_WLOSS*(Q5+R5)+S5)+U5*x_ABS_D*x_WAGE/365 -> 2.685283e+08 | AK5: =AJ5*x_R_FUS -> 84962354 | AL5: =AJ5*x_R_NFZ -> 20854176 | AM5: =AJ5*x_R_PIT -> 17852882 | AN5: =AJ5*x_R_FP -> 6847471.6 | AO5: =AA5+AB5+AC5+AD5+AF5 -> 8.4181365e+08 | AP5: =AO5+AE5+AG5+AH5+AI5+AK5+AL5+AM5+AN5 -> 1.0075379e+09 | AQ5: =AO5+AE5+AG5+AJ5 -> 1.1135656e+09 | AR5: =AB5+AC5+AD5+AF5 -> 5.3827055e+08 | AS5: =AR5+AE5+AG5 -> 5.4149417e+08
A6: 2029 | B6: 3 | C6: 9077.689 | D6: 250000000 | E6: 2000000 | F6: 7396.6702 | G6: 1 | H6: 4061.567 | I6: 433.853 | J6: 1540.259 | K6: 2530.349 | L6: 1460.876 | M6: 31916.153 | N6: 3102.976 | O6: 86.744 | P6: 86.909 | Q6: 2143.653 | R6: 1763.817 | S6: 2203.578 | T6: 4495.42 | U6: 2703.279 | V6: 117916.44 | W6: 277.503 | X6: 751.298 | Y6: 86.744 | Z6: 921.558 | AA6: =H6*x_c_F+I6*x_c_CC+J6*x_c_DC+K6*x_c_HCC+L6*x_c_PLT+M6*x_c_SVRn+N6*x_c_SVRcc+O6*x_c_LT+P6*x_c_LT1 -> 3.0966025e+08 | AB6: =C6*x_c_DAA -> 2.066082e+08 | AC6: =C6*x_c_MON -> 52334056 | AD6: =D6*(1-x_testy) -> 250000000 | AE6: =E6*(1-x_testy) -> 2000000 | AF6: =F6*x_NAV -> 14844629 | AG6: =G6*x_FIX*(1-x_testy) -> 1223620.5 | AH6: =x_z_F*U6+(1-x_AGRI)*x_EMP*x_WLOSS*(x_PEN_K74*Q6+x_PEN_C22*R6) -> 30509106 | AI6: =x_AGRI*x_EMP*x_WLOSS*(x_PEN_K74*Q6+x_PEN_C22*R6) -> 1649240.8 | AJ6: =x_EMP*x_WAGE*(x_WLOSS*(Q6+R6)+S6)+U6*x_ABS_D*x_WAGE/365 -> 3.2371611e+08 | AK6: =AJ6*x_R_FUS -> 1.0242378e+08 | AL6: =AJ6*x_R_NFZ -> 25140117 | AM6: =AJ6*x_R_PIT -> 21521998 | AN6: =AJ6*x_R_FP -> 8254760.7 | AO6: =AA6+AB6+AC6+AD6+AF6 -> 8.3344713e+08 | AP6: =AO6+AE6+AG6+AH6+AI6+AK6+AL6+AM6+AN6 -> 1.0261698e+09 | AQ6: =AO6+AE6+AG6+AJ6 -> 1.1603869e+09 | AR6: =AB6+AC6+AD6+AF6 -> 5.2378689e+08 | AS6: =AR6+AE6+AG6 -> 5.2701051e+08
A7: 2030 | B7: 4 | C7: 8714.493 | D7: 250000000 | E7: 2000000 | F7: 6763.9258 | G7: 1 | H7: 3888.759 | I7: 437.961 | J7: 1538.692 | K7: 2551.668 | L7: 1445.316 | M7: 38594.608 | N7: 3845.07 | O7: 86.713 | P7: 86.728 | Q7: 2155.19 | R7: 1801.538 | S7: 2843.664 | T7: 4326.72 | U7: 2666.051 | V7: 119491.05 | W7: 281.868 | X7: 761.307 | Y7: 86.713 | Z7: 925.074 | AA7: =H7*x_c_F+I7*x_c_CC+J7*x_c_DC+K7*x_c_HCC+L7*x_c_PLT+M7*x_c_SVRn+N7*x_c_SVRcc+O7*x_c_LT+P7*x_c_LT1 -> 3.1609239e+08 | AB7: =C7*x_c_DAA -> 1.9834186e+08 | AC7: =C7*x_c_MON -> 50240184 | AD7: =D7*(1-x_testy) -> 250000000 | AE7: =E7*(1-x_testy) -> 2000000 | AF7: =F7*x_NAV -> 13574752 | AG7: =G7*x_FIX*(1-x_testy) -> 1223620.5 | AH7: =x_z_F*U7+(1-x_AGRI)*x_EMP*x_WLOSS*(x_PEN_K74*Q7+x_PEN_C22*R7) -> 30759821 | AI7: =x_AGRI*x_EMP*x_WLOSS*(x_PEN_K74*Q7+x_PEN_C22*R7) -> 1670871.5 | AJ7: =x_EMP*x_WAGE*(x_WLOSS*(Q7+R7)+S7)+U7*x_ABS_D*x_WAGE/365 -> 3.7979309e+08 | AK7: =AJ7*x_R_FUS -> 1.2016653e+08 | AL7: =AJ7*x_R_NFZ -> 29495111 | AM7: =AJ7*x_R_PIT -> 25250230 | AN7: =AJ7*x_R_FP -> 9684723.7 | AO7: =AA7+AB7+AC7+AD7+AF7 -> 8.2824918e+08 | AP7: =AO7+AE7+AG7+AH7+AI7+AK7+AL7+AM7+AN7 -> 1.0485001e+09 | AQ7: =AO7+AE7+AG7+AJ7 -> 1.2112659e+09 | AR7: =AB7+AC7+AD7+AF7 -> 5.121568e+08 | AS7: =AR7+AE7+AG7 -> 5.1538042e+08
A8: 2031 | B8: 5 | C8: 8418.221 | D8: 250000000 | E8: 2000000 | F8: 6247.7724 | G8: 1 | H8: 3744.928 | I8: 441.818 | J8: 1540.326 | K8: 2573.768 | L8: 1429.341 | M8: 44910.926 | N8: 4568.819 | O8: 86.88 | P8: 86.796 | Q8: 2169.987 | R8: 1840.956 | S8: 3491.288 | T8: 4186.746 | U8: 2640.169 | V8: 121098.25 | W8: 285.178 | X8: 767.784 | Y8: 86.88 | Z8: 929.846 | AA8: =H8*x_c_F+I8*x_c_CC+J8*x_c_DC+K8*x_c_HCC+L8*x_c_PLT+M8*x_c_SVRn+N8*x_c_SVRcc+O8*x_c_LT+P8*x_c_LT1 -> 3.2251033e+08 | AB8: =C8*x_c_DAA -> 1.9159871e+08 | AC8: =C8*x_c_MON -> 48532137 | AD8: =D8*(1-x_testy) -> 250000000 | AE8: =E8*(1-x_testy) -> 2000000 | AF8: =F8*x_NAV -> 12538867 | AG8: =G8*x_FIX*(1-x_testy) -> 1223620.5 | AH8: =x_z_F*U8+(1-x_AGRI)*x_EMP*x_WLOSS*(x_PEN_K74*Q8+x_PEN_C22*R8) -> 31065072 | AI8: =x_AGRI*x_EMP*x_WLOSS*(x_PEN_K74*Q8+x_PEN_C22*R8) -> 1694565.1 | AJ8: =x_EMP*x_WAGE*(x_WLOSS*(Q8+R8)+S8)+U8*x_ABS_D*x_WAGE/365 -> 4.3670834e+08 | AK8: =AJ8*x_R_FUS -> 1.3817452e+08 | AL8: =AJ8*x_R_NFZ -> 33915206 | AM8: =AJ8*x_R_PIT -> 29034193 | AN8: =AJ8*x_R_FP -> 11136063 | AO8: =AA8+AB8+AC8+AD8+AF8 -> 8.2518005e+08 | AP8: =AO8+AE8+AG8+AH8+AI8+AK8+AL8+AM8+AN8 -> 1.0734233e+09 | AQ8: =AO8+AE8+AG8+AJ8 -> 1.265112e+09 | AR8: =AB8+AC8+AD8+AF8 -> 5.0266971e+08 | AS8: =AR8+AE8+AG8 -> 5.0589333e+08
A9: 2032 | B9: 6 | C9: 8172.548 | D9: 250000000 | E9: 2000000 | F9: 5819.7695 | G9: 1 | H9: 3623.954 | I9: 444.568 | J9: 1543.272 | K9: 2592.517 | L9: 1413.155 | M9: 50926.171 | N9: 5271.635 | O9: 87.122 | P9: 87.001 | Q9: 2186.711 | R9: 1878.964 | S9: 4146.575 | T9: 4068.522 | U9: 2622.723 | V9: 122723.43 | W9: 287.013 | X9: 770.15 | Y9: 87.122 | Z9: 934.437 | AA9: =H9*x_c_F+I9*x_c_CC+J9*x_c_DC+K9*x_c_HCC+L9*x_c_PLT+M9*x_c_SVRn+N9*x_c_SVRcc+O9*x_c_LT+P9*x_c_LT1 -> 3.285867e+08 | AB9: =C9*x_c_DAA -> 1.8600719e+08 | AC9: =C9*x_c_MON -> 47115801 | AD9: =D9*(1-x_testy) -> 250000000 | AE9: =E9*(1-x_testy) -> 2000000 | AF9: =F9*x_NAV -> 11679893 | AG9: =G9*x_FIX*(1-x_testy) -> 1223620.5 | AH9: =x_z_F*U9+(1-x_AGRI)*x_EMP*x_WLOSS*(x_PEN_K74*Q9+x_PEN_C22*R9) -> 31389618 | AI9: =x_AGRI*x_EMP*x_WLOSS*(x_PEN_K74*Q9+x_PEN_C22*R9) -> 1718387.8 | AJ9: =x_EMP*x_WAGE*(x_WLOSS*(Q9+R9)+S9)+U9*x_ABS_D*x_WAGE/365 -> 4.9431865e+08 | AK9: =AJ9*x_R_FUS -> 1.5640242e+08 | AL9: =AJ9*x_R_NFZ -> 38389280 | AM9: =AJ9*x_R_PIT -> 32864367 | AN9: =AJ9*x_R_FP -> 12605125 | AO9: =AA9+AB9+AC9+AD9+AF9 -> 8.2338959e+08 | AP9: =AO9+AE9+AG9+AH9+AI9+AK9+AL9+AM9+AN9 -> 1.0999824e+09 | AQ9: =AO9+AE9+AG9+AJ9 -> 1.3209319e+09 | AR9: =AB9+AC9+AD9+AF9 -> 4.9480289e+08 | AS9: =AR9+AE9+AG9 -> 4.9802651e+08
A10: 2033 | B10: 7 | C10: 7965.32 | D10: 250000000 | E10: 2000000 | F10: 5458.7465 | G10: 1 | H10: 3521.292 | I10: 445.611 | J10: 1545.645 | K10: 2604.55 | L10: 1396.853 | M10: 56681.808 | N10: 5949.773 | O10: 87.326 | P10: 87.224 | Q10: 2203.965 | R10: 1913.056 | S10: 4808.585 | T10: 3966.902 | U10: 2611.423 | V10: 124353.7 | W10: 287.143 | X10: 768.159 | Y10: 87.326 | Z10: 937.628 | AA10: =H10*x_c_F+I10*x_c_CC+J10*x_c_DC+K10*x_c_HCC+L10*x_c_PLT+M10*x_c_SVRn+N10*x_c_SVRcc+O10*x_c_LT+P10*x_c_LT1 -> 3.3403292e+08 | AB10: =C10*x_c_DAA -> 1.8129068e+08 | AC10: =C10*x_c_MON -> 45921104 | AD10: =D10*(1-x_testy) -> 250000000 | AE10: =E10*(1-x_testy) -> 2000000 | AF10: =F10*x_NAV -> 10955344 | AG10: =G10*x_FIX*(1-x_testy) -> 1223620.5 | AH10: =x_z_F*U10+(1-x_AGRI)*x_EMP*x_WLOSS*(x_PEN_K74*Q10+x_PEN_C22*R10) -> 31703219 | AI10: =x_AGRI*x_EMP*x_WLOSS*(x_PEN_K74*Q10+x_PEN_C22*R10) -> 1740651.8 | AJ10: =x_EMP*x_WAGE*(x_WLOSS*(Q10+R10)+S10)+U10*x_ABS_D*x_WAGE/365 -> 5.5240938e+08 | AK10: =AJ10*x_R_FUS -> 1.7478233e+08 | AL10: =AJ10*x_R_NFZ -> 42900665 | AM10: =AJ10*x_R_PIT -> 36726481 | AN10: =AJ10*x_R_FP -> 14086439 | AO10: =AA10+AB10+AC10+AD10+AF10 -> 8.2220005e+08 | AP10: =AO10+AE10+AG10+AH10+AI10+AK10+AL10+AM10+AN10 -> 1.1273635e+09 | AQ10: =AO10+AE10+AG10+AJ10 -> 1.3778331e+09 | AR10: =AB10+AC10+AD10+AF10 -> 4.8816713e+08 | AS10: =AR10+AE10+AG10 -> 4.9139075e+08
A11: 2034 | B11: 8 | C11: 7787.68 | D11: 250000000 | E11: 2000000 | F11: 5149.2682 | G11: 1 | H11: 3433.541 | I11: 444.551 | J11: 1545.724 | K11: 2607.337 | L11: 1380.416 | M11: 62206.216 | N11: 6598.711 | O11: 87.388 | P11: 87.357 | Q11: 2220.393 | R11: 1941.325 | S11: 5475.437 | T11: 3878.093 | U11: 2604.48 | V11: 125977.98 | W11: 285.468 | X11: 761.785 | Y11: 87.388 | Z11: 938.388 | AA11: =H11*x_c_F+I11*x_c_CC+J11*x_c_DC+K11*x_c_HCC+L11*x_c_PLT+M11*x_c_SVRn+N11*x_c_SVRcc+O11*x_c_LT+P11*x_c_LT1 -> 3.3861022e+08 | AB11: =C11*x_c_DAA -> 1.772476e+08 | AC11: =C11*x_c_MON -> 44896987 | AD11: =D11*(1-x_testy) -> 250000000 | AE11: =E11*(1-x_testy) -> 2000000 | AF11: =F11*x_NAV -> 10334241 | AG11: =G11*x_FIX*(1-x_testy) -> 1223620.5 | AH11: =x_z_F*U11+(1-x_AGRI)*x_EMP*x_WLOSS*(x_PEN_K74*Q11+x_PEN_C22*R11) -> 31981004 | AI11: =x_AGRI*x_EMP*x_WLOSS*(x_PEN_K74*Q11+x_PEN_C22*R11) -> 1759956.3 | AJ11: =x_EMP*x_WAGE*(x_WLOSS*(Q11+R11)+S11)+U11*x_ABS_D*x_WAGE/365 -> 6.1070812e+08 | AK11: =AJ11*x_R_FUS -> 1.9322805e+08 | AL11: =AJ11*x_R_NFZ -> 47428203 | AM11: =AJ11*x_R_PIT -> 40602425 | AN11: =AJ11*x_R_FP -> 15573057 | AO11: =AA11+AB11+AC11+AD11+AF11 -> 8.2108904e+08 | AP11: =AO11+AE11+AG11+AH11+AI11+AK11+AL11+AM11+AN11 -> 1.1548854e+09 | AQ11: =AO11+AE11+AG11+AJ11 -> 1.4350208e+09 | AR11: =AB11+AC11+AD11+AF11 -> 4.8247882e+08 | AS11: =AR11+AE11+AG11 -> 4.8570245e+08
A12: 2035 | B12: 9 | C12: 7632.985 | D12: 250000000 | E12: 2000000 | F12: 4879.7654 | G12: 1 | H12: 2796.276 | I12: 366.965 | J12: 1542.062 | K12: 2599.173 | L12: 1363.732 | M12: 66378.419 | N12: 7062.811 | O12: 87.224 | P12: 87.306 | Q12: 2234.749 | R12: 1962.42 | S12: 6144.487 | T12: 3163.241 | U12: 2161.065 | V12: 127516.56 | W12: 282.009 | X12: 751.22 | Y12: 87.224 | Z12: 935.989 | AA12: =H12*x_c_F+I12*x_c_CC+J12*x_c_DC+K12*x_c_HCC+L12*x_c_PLT+M12*x_c_SVRn+N12*x_c_SVRcc+O12*x_c_LT+P12*x_c_LT1 -> 3.3896168e+08 | AB12: =C12*x_c_DAA -> 1.7372674e+08 | AC12: =C12*x_c_MON -> 44005150 | AD12: =D12*(1-x_testy) -> 250000000 | AE12: =E12*(1-x_testy) -> 2000000 | AF12: =F12*x_NAV -> 9793366.9 | AG12: =G12*x_FIX*(1-x_testy) -> 1223620.5 | AH12: =x_z_F*U12+(1-x_AGRI)*x_EMP*x_WLOSS*(x_PEN_K74*Q12+x_PEN_C22*R12) -> 31299939 | AI12: =x_AGRI*x_EMP*x_WLOSS*(x_PEN_K74*Q12+x_PEN_C22*R12) -> 1775195.6 | AJ12: =x_EMP*x_WAGE*(x_WLOSS*(Q12+R12)+S12)+U12*x_ABS_D*x_WAGE/365 -> 6.6760953e+08 | AK12: =AJ12*x_R_FUS -> 2.1123165e+08 | AL12: =AJ12*x_R_NFZ -> 51847224 | AM12: =AJ12*x_R_PIT -> 44385468 | AN12: =AJ12*x_R_FP -> 17024043 | AO12: =AA12+AB12+AC12+AD12+AF12 -> 8.1648694e+08 | AP12: =AO12+AE12+AG12+AH12+AI12+AK12+AL12+AM12+AN12 -> 1.1772741e+09 | AQ12: =AO12+AE12+AG12+AJ12 -> 1.4873201e+09 | AR12: =AB12+AC12+AD12+AF12 -> 4.7752526e+08 | AS12: =AR12+AE12+AG12 -> 4.8074888e+08
A13: 2036 | B13: 10 | C13: 4832 | D13: 0 | E13: 0 | F13: 0 | G13: 0 | H13: 2198.346 | I13: 290.88 | J13: 1536.081 | K13: 2585.016 | L13: 1346.591 | M13: 69287.214 | N13: 7349.548 | O13: 86.764 | P13: 86.994 | Q13: 2247.943 | R13: 1980.121 | S13: 6812.487 | T13: 2489.226 | U13: 1734.75 | V13: 128961.65 | W13: 281.984 | X13: 748.618 | Y13: 86.764 | Z13: 929.883 | AA13: =H13*x_c_F+I13*x_c_CC+J13*x_c_DC+K13*x_c_HCC+L13*x_c_PLT+M13*x_c_SVRn+N13*x_c_SVRcc+O13*x_c_LT+P13*x_c_LT1 -> 3.37631e+08 | AB13: =C13*x_c_DAA -> 109976320 | AC13: =C13*x_c_MON -> 27857108 | AD13: =D13*(1-x_testy) -> 0 | AE13: =E13*(1-x_testy) -> 0 | AF13: =F13*x_NAV -> 0 | AG13: =G13*x_FIX*(1-x_testy) -> 0 | AH13: =x_z_F*U13+(1-x_AGRI)*x_EMP*x_WLOSS*(x_PEN_K74*Q13+x_PEN_C22*R13) -> 30623840 | AI13: =x_AGRI*x_EMP*x_WLOSS*(x_PEN_K74*Q13+x_PEN_C22*R13) -> 1788439.3 | AJ13: =x_EMP*x_WAGE*(x_WLOSS*(Q13+R13)+S13)+U13*x_ABS_D*x_WAGE/365 -> 7.2432252e+08 | AK13: =AJ13*x_R_FUS -> 2.2917564e+08 | AL13: =AJ13*x_R_NFZ -> 56251611 | AM13: =AJ13*x_R_PIT -> 48155984 | AN13: =AJ13*x_R_FP -> 18470224 | AO13: =AA13+AB13+AC13+AD13+AF13 -> 4.7546443e+08 | AP13: =AO13+AE13+AG13+AH13+AI13+AK13+AL13+AM13+AN13 -> 8.5993017e+08 | AQ13: =AO13+AE13+AG13+AJ13 -> 1.1997869e+09 | AR13: =AB13+AC13+AD13+AF13 -> 1.3783343e+08 | AS13: =AR13+AE13+AG13 -> 1.3783343e+08
A14: 2037 | B14: 11 | C14: 4832 | D14: 0 | E14: 0 | F14: 0 | G14: 0 | H14: 2196.777 | I14: 290.893 | J14: 1529.036 | K14: 2568.721 | L14: 1328.695 | M14: 72145.817 | N14: 7617.745 | O14: 86.283 | P14: 86.524 | Q14: 2260.898 | R14: 1997.498 | S14: 7477.152 | T14: 2487.67 | U14: 1763.022 | V14: 130374.83 | W14: 280.421 | X14: 742.572 | Y14: 86.283 | Z14: 923.492 | AA14: =H14*x_c_F+I14*x_c_CC+J14*x_c_DC+K14*x_c_HCC+L14*x_c_PLT+M14*x_c_SVRn+N14*x_c_SVRcc+O14*x_c_LT+P14*x_c_LT1 -> 3.3820391e+08 | AB14: =C14*x_c_DAA -> 109976320 | AC14: =C14*x_c_MON -> 27857108 | AD14: =D14*(1-x_testy) -> 0 | AE14: =E14*(1-x_testy) -> 0 | AF14: =F14*x_NAV -> 0 | AG14: =G14*x_FIX*(1-x_testy) -> 0 | AH14: =x_z_F*U14+(1-x_AGRI)*x_EMP*x_WLOSS*(x_PEN_K74*Q14+x_PEN_C22*R14) -> 30878676 | AI14: =x_AGRI*x_EMP*x_WLOSS*(x_PEN_K74*Q14+x_PEN_C22*R14) -> 1801441.6 | AJ14: =x_EMP*x_WAGE*(x_WLOSS*(Q14+R14)+S14)+U14*x_ABS_D*x_WAGE/365 -> 7.8206804e+08 | AK14: =AJ14*x_R_FUS -> 2.4744633e+08 | AL14: =AJ14*x_R_NFZ -> 60736186 | AM14: =AJ14*x_R_PIT -> 51995148 | AN14: =AJ14*x_R_FP -> 19942735 | AO14: =AA14+AB14+AC14+AD14+AF14 -> 4.7603734e+08 | AP14: =AO14+AE14+AG14+AH14+AI14+AK14+AL14+AM14+AN14 -> 8.8883786e+08 | AQ14: =AO14+AE14+AG14+AJ14 -> 1.2581054e+09 | AR14: =AB14+AC14+AD14+AF14 -> 1.3783343e+08 | AS14: =AR14+AE14+AG14 -> 1.3783343e+08
... A52: 2075 | B52: 49 | C52: 4832 | D52: 0 | E52: 0 | F52: 0 | G52: 0 | H52: 2287.551 | I52: 178.026 | J52: 850.206 | K52: 1489.635 | L52: 526.333 | M52: 155973.27 | N52: 7019.134 | O52: 48.475 | P52: 48.471 | Q52: 547.369 | R52: 808.915 | S52: 2273.855 | T52: 2465.576 | U52: 1852 | V52: 182839.4 | W52: 159.202 | X52: 436.314 | Y52: 48.475 | Z52: 519.481 | AA52: =H52*x_c_F+I52*x_c_CC+J52*x_c_DC+K52*x_c_HCC+L52*x_c_PLT+M52*x_c_SVRn+N52*x_c_SVRcc+O52*x_c_LT+P52*x_c_LT1 -> 2.67183e+08 | AB52: =C52*x_c_DAA -> 109976320 | AC52: =C52*x_c_MON -> 27857108 | AD52: =D52*(1-x_testy) -> 0 | AE52: =E52*(1-x_testy) -> 0 | AF52: =F52*x_NAV -> 0 | AG52: =G52*x_FIX*(1-x_testy) -> 0 | AH52: =x_z_F*U52+(1-x_AGRI)*x_EMP*x_WLOSS*(x_PEN_K74*Q52+x_PEN_C22*R52) -> 12629639 | AI52: =x_AGRI*x_EMP*x_WLOSS*(x_PEN_K74*Q52+x_PEN_C22*R52) -> 583123.89 | AJ52: =x_EMP*x_WAGE*(x_WLOSS*(Q52+R52)+S52)+U52*x_ABS_D*x_WAGE/365 -> 2.4370326e+08 | AK52: =AJ52*x_R_FUS -> 77107713 | AL52: =AJ52*x_R_NFZ -> 18926239 | AM52: =AJ52*x_R_PIT -> 16202410 | AN52: =AJ52*x_R_FP -> 6214433.2 | AO52: =AA52+AB52+AC52+AD52+AF52 -> 4.0501642e+08 | AP52: =AO52+AE52+AG52+AH52+AI52+AK52+AL52+AM52+AN52 -> 5.3667998e+08 | AQ52: =AO52+AE52+AG52+AJ52 -> 6.4871969e+08 | AR52: =AB52+AC52+AD52+AF52 -> 1.3783343e+08 | AS52: =AR52+AE52+AG52 -> 1.3783343e+08

Sheet L_I5
A1: I5: Cięcia: −30% leczonych – liczebności (silnik, wartości) i koszty (formuły), zł/rok, niezdyskontowane. Szacunek modelu.
A2: rok | B2: t | C2: treated | D2: NFZ_diag | E2: MZ_SW | F2: nNAV | G2: FIXon | H2: cF03 | I2: cF4 | J2: cDC | K2: cHCC | L2: cPLT | M2: cSVn | N2: cSVc | O2: cLTn | P2: cLT1 | Q2: wAdv | R2: wHCC | S2: wGH | T2: cAbs | U2: cAbsW | V2: QALY | W2: newDC | X2: newHCC | Y2: LT | Z2: liverD | AA2: NFZ_med | AB2: NFZ_DAA | AC2: NFZ_mon | AD2: NFZ_diag_k | AE2: MZ_SW_k | AF2: NAV_k | AG2: FIX_k | AH2: ZUS | AI2: KRUS | AJ2: lostw | AK2: lost_FUS | AL2: lost_NFZ | AM2: lost_PIT | AN2: lost_FP | AO2: NFZ | AP2: PUBLIC | AQ2: SOCIETAL | AR2: INV_NFZ | AS2: INV_PUB
A3: 2026 | B3: 0 | C3: 3382.4 | D3: 0 | E3: 0 | F3: 0 | G3: 0 | H3: 2481.186 | I3: 223.146 | J3: 1580.379 | K3: 2527.318 | L3: 1540.438 | M3: 4502.128 | N3: 397.514 | O3: 89.046 | P3: 44.523 | Q3: 2135.415 | R3: 1704.99 | S3: 312.377 | T3: 2704.332 | U3: 1499.75 | V3: 113275.6 | W3: 267.792 | X3: 716.541 | Y3: 89.046 | Z3: 922.327 | AA3: =H3*x_c_F+I3*x_c_CC+J3*x_c_DC+K3*x_c_HCC+L3*x_c_PLT+M3*x_c_SVRn+N3*x_c_SVRcc+O3*x_c_LT+P3*x_c_LT1 -> 2.8147689e+08 | AB3: =C3*x_c_DAA -> 76983424 | AC3: =C3*x_c_MON -> 19499975 | AD3: =D3*(1-x_testy) -> 0 | AE3: =E3*(1-x_testy) -> 0 | AF3: =F3*x_NAV -> 0 | AG3: =G3*x_FIX*(1-x_testy) -> 0 | AH3: =x_z_F*U3+(1-x_AGRI)*x_EMP*x_WLOSS*(x_PEN_K74*Q3+x_PEN_C22*R3) -> 27583076 | AI3: =x_AGRI*x_EMP*x_WLOSS*(x_PEN_K74*Q3+x_PEN_C22*R3) -> 1619385.2 | AJ3: =x_EMP*x_WAGE*(x_WLOSS*(Q3+R3)+S3)+U3*x_ABS_D*x_WAGE/365 -> 1.56741e+08 | AK3: =AJ3*x_R_FUS -> 49592853 | AL3: =AJ3*x_R_NFZ -> 12172663 | AM3: =AJ3*x_R_PIT -> 10420796 | AN3: =AJ3*x_R_FP -> 3996895.5 | AO3: =AA3+AB3+AC3+AD3+AF3 -> 3.7796029e+08 | AP3: =AO3+AE3+AG3+AH3+AI3+AK3+AL3+AM3+AN3 -> 4.8334596e+08 | AQ3: =AO3+AE3+AG3+AJ3 -> 5.347013e+08 | AR3: =AB3+AC3+AD3+AF3 -> 96483399 | AS3: =AR3+AE3+AG3 -> 96483399
A4: 2027 | B4: 1 | C4: 3382.4 | D4: 0 | E4: 0 | F4: 0 | G4: 0 | H4: 2960.678 | I4: 282.666 | J4: 1568.432 | K4: 2531.672 | L4: 1489.389 | M4: 7443.396 | N4: 670.859 | O4: 88.045 | P4: 88.546 | Q4: 2141.06 | R4: 1724.023 | S4: 940.503 | T4: 3243.344 | U4: 1851.393 | V4: 114303.36 | W4: 279.845 | X4: 752.844 | Y4: 88.045 | Z4: 927.293 | AA4: =H4*x_c_F+I4*x_c_CC+J4*x_c_DC+K4*x_c_HCC+L4*x_c_PLT+M4*x_c_SVRn+N4*x_c_SVRcc+O4*x_c_LT+P4*x_c_LT1 -> 2.8595381e+08 | AB4: =C4*x_c_DAA -> 76983424 | AC4: =C4*x_c_MON -> 19499975 | AD4: =D4*(1-x_testy) -> 0 | AE4: =E4*(1-x_testy) -> 0 | AF4: =F4*x_NAV -> 0 | AG4: =G4*x_FIX*(1-x_testy) -> 0 | AH4: =x_z_F*U4+(1-x_AGRI)*x_EMP*x_WLOSS*(x_PEN_K74*Q4+x_PEN_C22*R4) -> 28470084 | AI4: =x_AGRI*x_EMP*x_WLOSS*(x_PEN_K74*Q4+x_PEN_C22*R4) -> 1630229.4 | AJ4: =x_EMP*x_WAGE*(x_WLOSS*(Q4+R4)+S4)+U4*x_ABS_D*x_WAGE/365 -> 2.12136e+08 | AK4: =AJ4*x_R_FUS -> 67119829 | AL4: =AJ4*x_R_NFZ -> 16474694 | AM4: =AJ4*x_R_PIT -> 14103686 | AN4: =AJ4*x_R_FP -> 5409467.9 | AO4: =AA4+AB4+AC4+AD4+AF4 -> 3.8243721e+08 | AP4: =AO4+AE4+AG4+AH4+AI4+AK4+AL4+AM4+AN4 -> 5.156452e+08 | AQ4: =AO4+AE4+AG4+AJ4 -> 5.9457321e+08 | AR4: =AB4+AC4+AD4+AF4 -> 96483399 | AS4: =AR4+AE4+AG4 -> 96483399
A5: 2028 | B5: 2 | C5: 3382.4 | D5: 0 | E5: 0 | F5: 0 | G5: 0 | H5: 3382.55 | I5: 344.014 | J5: 1570.839 | K5: 2570.839 | L5: 1475.819 | M5: 10329.516 | N5: 952.649 | O5: 88.012 | P5: 88.029 | Q5: 2153.879 | R5: 1770.834 | S5: 1575.742 | T5: 3726.564 | U5: 2185.507 | V5: 115402.13 | W5: 294.036 | X5: 791.242 | Y5: 88.012 | Z5: 931.837 | AA5: =H5*x_c_F+I5*x_c_CC+J5*x_c_DC+K5*x_c_HCC+L5*x_c_PLT+M5*x_c_SVRn+N5*x_c_SVRcc+O5*x_c_LT+P5*x_c_LT1 -> 2.921135e+08 | AB5: =C5*x_c_DAA -> 76983424 | AC5: =C5*x_c_MON -> 19499975 | AD5: =D5*(1-x_testy) -> 0 | AE5: =E5*(1-x_testy) -> 0 | AF5: =F5*x_NAV -> 0 | AG5: =G5*x_FIX*(1-x_testy) -> 0 | AH5: =x_z_F*U5+(1-x_AGRI)*x_EMP*x_WLOSS*(x_PEN_K74*Q5+x_PEN_C22*R5) -> 29554093 | AI5: =x_AGRI*x_EMP*x_WLOSS*(x_PEN_K74*Q5+x_PEN_C22*R5) -> 1656477 | AJ5: =x_EMP*x_WAGE*(x_WLOSS*(Q5+R5)+S5)+U5*x_ABS_D*x_WAGE/365 -> 2.6922999e+08 | AK5: =AJ5*x_R_FUS -> 85184369 | AL5: =AJ5*x_R_NFZ -> 20908670 | AM5: =AJ5*x_R_PIT -> 17899533 | AN5: =AJ5*x_R_FP -> 6865364.7 | AO5: =AA5+AB5+AC5+AD5+AF5 -> 3.885969e+08 | AP5: =AO5+AE5+AG5+AH5+AI5+AK5+AL5+AM5+AN5 -> 5.5066541e+08 | AQ5: =AO5+AE5+AG5+AJ5 -> 6.5782689e+08 | AR5: =AB5+AC5+AD5+AF5 -> 96483399 | AS5: =AR5+AE5+AG5 -> 96483399
A6: 2029 | B6: 3 | C6: 3382.4 | D6: 0 | E6: 0 | F6: 0 | G6: 0 | H6: 3751.943 | I6: 406.368 | J6: 1586.611 | K6: 2635.939 | L6: 1461.47 | M6: 13158.115 | N6: 1243.075 | O6: 88.838 | P6: 88.425 | Q6: 2178.091 | R6: 1839.014 | S6: 2222.173 | T6: 4158.311 | U6: 2501.145 | V6: 116547.84 | W6: 309.291 | X6: 829.89 | Y6: 88.838 | Z6: 946.096 | AA6: =H6*x_c_F+I6*x_c_CC+J6*x_c_DC+K6*x_c_HCC+L6*x_c_PLT+M6*x_c_SVRn+N6*x_c_SVRcc+O6*x_c_LT+P6*x_c_LT1 -> 3.0029693e+08 | AB6: =C6*x_c_DAA -> 76983424 | AC6: =C6*x_c_MON -> 19499975 | AD6: =D6*(1-x_testy) -> 0 | AE6: =E6*(1-x_testy) -> 0 | AF6: =F6*x_NAV -> 0 | AG6: =G6*x_FIX*(1-x_testy) -> 0 | AH6: =x_z_F*U6+(1-x_AGRI)*x_EMP*x_WLOSS*(x_PEN_K74*Q6+x_PEN_C22*R6) -> 30814722 | AI6: =x_AGRI*x_EMP*x_WLOSS*(x_PEN_K74*Q6+x_PEN_C22*R6) -> 1696909.7 | AJ6: =x_EMP*x_WAGE*(x_WLOSS*(Q6+R6)+S6)+U6*x_ABS_D*x_WAGE/365 -> 3.282963e+08 | AK6: =AJ6*x_R_FUS -> 1.0387295e+08 | AL6: =AJ6*x_R_NFZ -> 25495819 | AM6: =AJ6*x_R_PIT -> 21826508 | AN6: =AJ6*x_R_FP -> 8371555.6 | AO6: =AA6+AB6+AC6+AD6+AF6 -> 3.9678033e+08 | AP6: =AO6+AE6+AG6+AH6+AI6+AK6+AL6+AM6+AN6 -> 5.8885879e+08 | AQ6: =AO6+AE6+AG6+AJ6 -> 7.2507662e+08 | AR6: =AB6+AC6+AD6+AF6 -> 96483399 | AS6: =AR6+AE6+AG6 -> 96483399
A7: 2030 | B7: 4 | C7: 3382.4 | D7: 0 | E7: 0 | F7: 0 | G7: 0 | H7: 4073.491 | I7: 468.558 | J7: 1613.946 | K7: 2718.953 | L7: 1447.102 | M7: 15927.63 | N7: 1541.544 | O7: 90.383 | P7: 89.611 | Q7: 2212.965 | R7: 1922.845 | S7: 2886.272 | T7: 4542.049 | U7: 2797.361 | V7: 117725.48 | W7: 324.759 | X7: 867.346 | Y7: 90.383 | Z7: 967.623 | AA7: =H7*x_c_F+I7*x_c_CC+J7*x_c_DC+K7*x_c_HCC+L7*x_c_PLT+M7*x_c_SVRn+N7*x_c_SVRcc+O7*x_c_LT+P7*x_c_LT1 -> 3.0994241e+08 | AB7: =C7*x_c_DAA -> 76983424 | AC7: =C7*x_c_MON -> 19499975 | AD7: =D7*(1-x_testy) -> 0 | AE7: =E7*(1-x_testy) -> 0 | AF7: =F7*x_NAV -> 0 | AG7: =G7*x_FIX*(1-x_testy) -> 0 | AH7: =x_z_F*U7+(1-x_AGRI)*x_EMP*x_WLOSS*(x_PEN_K74*Q7+x_PEN_C22*R7) -> 32206542 | AI7: =x_AGRI*x_EMP*x_WLOSS*(x_PEN_K74*Q7+x_PEN_C22*R7) -> 1748653.1 | AJ7: =x_EMP*x_WAGE*(x_WLOSS*(Q7+R7)+S7)+U7*x_ABS_D*x_WAGE/365 -> 3.896732e+08 | AK7: =AJ7*x_R_FUS -> 1.232926e+08 | AL7: =AJ7*x_R_NFZ -> 30262410 | AM7: =AJ7*x_R_PIT -> 25907101 | AN7: =AJ7*x_R_FP -> 9936666.6 | AO7: =AA7+AB7+AC7+AD7+AF7 -> 4.0642581e+08 | AP7: =AO7+AE7+AG7+AH7+AI7+AK7+AL7+AM7+AN7 -> 6.2977978e+08 | AQ7: =AO7+AE7+AG7+AJ7 -> 7.9609901e+08 | AR7: =AB7+AC7+AD7+AF7 -> 96483399 | AS7: =AR7+AE7+AG7 -> 96483399
A8: 2031 | B8: 5 | C8: 3382.4 | D8: 0 | E8: 0 | F8: 0 | G8: 0 | H8: 4351.442 | I8: 529.278 | J8: 1650.603 | K8: 2812.886 | L8: 1433.353 | M8: 18637.299 | N8: 1846.864 | O8: 92.488 | P8: 91.435 | Q8: 2257.376 | R8: 2017.356 | S8: 3572.774 | T8: 4880.72 | U8: 3073.326 | V8: 118924.35 | W8: 339.789 | X8: 902.532 | Y8: 92.488 | Z8: 994.173 | AA8: =H8*x_c_F+I8*x_c_CC+J8*x_c_DC+K8*x_c_HCC+L8*x_c_PLT+M8*x_c_SVRn+N8*x_c_SVRcc+O8*x_c_LT+P8*x_c_LT1 -> 3.2052994e+08 | AB8: =C8*x_c_DAA -> 76983424 | AC8: =C8*x_c_MON -> 19499975 | AD8: =D8*(1-x_testy) -> 0 | AE8: =E8*(1-x_testy) -> 0 | AF8: =F8*x_NAV -> 0 | AG8: =G8*x_FIX*(1-x_testy) -> 0 | AH8: =x_z_F*U8+(1-x_AGRI)*x_EMP*x_WLOSS*(x_PEN_K74*Q8+x_PEN_C22*R8) -> 33687101 | AI8: =x_AGRI*x_EMP*x_WLOSS*(x_PEN_K74*Q8+x_PEN_C22*R8) -> 1809013.9 | AJ8: =x_EMP*x_WAGE*(x_WLOSS*(Q8+R8)+S8)+U8*x_ABS_D*x_WAGE/365 -> 4.5356244e+08 | AK8: =AJ8*x_R_FUS -> 1.4350716e+08 | AL8: =AJ8*x_R_NFZ -> 35224113 | AM8: =AJ8*x_R_PIT -> 30154724 | AN8: =AJ8*x_R_FP -> 11565842 | AO8: =AA8+AB8+AC8+AD8+AF8 -> 4.1701334e+08 | AP8: =AO8+AE8+AG8+AH8+AI8+AK8+AL8+AM8+AN8 -> 6.7296129e+08 | AQ8: =AO8+AE8+AG8+AJ8 -> 8.7057578e+08 | AR8: =AB8+AC8+AD8+AF8 -> 96483399 | AS8: =AR8+AE8+AG8 -> 96483399
A9: 2032 | B9: 6 | C9: 3382.4 | D9: 0 | E9: 0 | F9: 0 | G9: 0 | H9: 4589.564 | I9: 587.216 | J9: 1694.123 | K9: 2911.749 | L9: 1420.677 | M9: 21286.685 | N9: 2157.352 | O9: 94.991 | P9: 93.74 | Q9: 2309.928 | R9: 2118.294 | S9: 4284.777 | T9: 5176.78 | U9: 3328.299 | V9: 120134.04 | W9: 353.878 | X9: 934.626 | Y9: 94.991 | Z9: 1023.696 | AA9: =H9*x_c_F+I9*x_c_CC+J9*x_c_DC+K9*x_c_HCC+L9*x_c_PLT+M9*x_c_SVRn+N9*x_c_SVRcc+O9*x_c_LT+P9*x_c_LT1 -> 3.3158912e+08 | AB9: =C9*x_c_DAA -> 76983424 | AC9: =C9*x_c_MON -> 19499975 | AD9: =D9*(1-x_testy) -> 0 | AE9: =E9*(1-x_testy) -> 0 | AF9: =F9*x_NAV -> 0 | AG9: =G9*x_FIX*(1-x_testy) -> 0 | AH9: =x_z_F*U9+(1-x_AGRI)*x_EMP*x_WLOSS*(x_PEN_K74*Q9+x_PEN_C22*R9) -> 35217405 | AI9: =x_AGRI*x_EMP*x_WLOSS*(x_PEN_K74*Q9+x_PEN_C22*R9) -> 1875515.4 | AJ9: =x_EMP*x_WAGE*(x_WLOSS*(Q9+R9)+S9)+U9*x_ABS_D*x_WAGE/365 -> 5.2004108e+08 | AK9: =AJ9*x_R_FUS -> 1.64541e+08 | AL9: =AJ9*x_R_NFZ -> 40386910 | AM9: =AJ9*x_R_PIT -> 34574502 | AN9: =AJ9*x_R_FP -> 13261048 | AO9: =AA9+AB9+AC9+AD9+AF9 -> 4.2807252e+08 | AP9: =AO9+AE9+AG9+AH9+AI9+AK9+AL9+AM9+AN9 -> 7.179289e+08 | AQ9: =AO9+AE9+AG9+AJ9 -> 9.481136e+08 | AR9: =AB9+AC9+AD9+AF9 -> 96483399 | AS9: =AR9+AE9+AG9 -> 96483399
A10: 2033 | B10: 7 | C10: 3382.4 | D10: 0 | E10: 0 | F10: 0 | G10: 0 | H10: 4791.213 | I10: 641.159 | J10: 1742.029 | K10: 3010.558 | L10: 1409.366 | M10: 23875.725 | N10: 2470.98 | O10: 97.739 | P10: 96.365 | Q10: 2369.079 | R10: 2222.092 | S10: 5023.933 | T10: 5432.372 | U10: 3561.64 | V10: 121345.82 | W10: 366.663 | X10: 963.068 | Y10: 97.739 | Z10: 1054.451 | AA10: =H10*x_c_F+I10*x_c_CC+J10*x_c_DC+K10*x_c_HCC+L10*x_c_PLT+M10*x_c_SVRn+N10*x_c_SVRcc+O10*x_c_LT+P10*x_c_LT1 -> 3.4270876e+08 | AB10: =C10*x_c_DAA -> 76983424 | AC10: =C10*x_c_MON -> 19499975 | AD10: =D10*(1-x_testy) -> 0 | AE10: =E10*(1-x_testy) -> 0 | AF10: =F10*x_NAV -> 0 | AG10: =G10*x_FIX*(1-x_testy) -> 0 | AH10: =x_z_F*U10+(1-x_AGRI)*x_EMP*x_WLOSS*(x_PEN_K74*Q10+x_PEN_C22*R10) -> 36762480 | AI10: =x_AGRI*x_EMP*x_WLOSS*(x_PEN_K74*Q10+x_PEN_C22*R10) -> 1945932.8 | AJ10: =x_EMP*x_WAGE*(x_WLOSS*(Q10+R10)+S10)+U10*x_ABS_D*x_WAGE/365 -> 5.8908087e+08 | AK10: =AJ10*x_R_FUS -> 1.8638519e+08 | AL10: =AJ10*x_R_NFZ -> 45748609 | AM10: =AJ10*x_R_PIT -> 39164555 | AN10: =AJ10*x_R_FP -> 15021562 | AO10: =AA10+AB10+AC10+AD10+AF10 -> 4.3919215e+08 | AP10: =AO10+AE10+AG10+AH10+AI10+AK10+AL10+AM10+AN10 -> 7.6422048e+08 | AQ10: =AO10+AE10+AG10+AJ10 -> 1.028273e+09 | AR10: =AB10+AC10+AD10+AF10 -> 96483399 | AS10: =AR10+AE10+AG10 -> 96483399
A11: 2034 | B11: 8 | C11: 3382.4 | D11: 0 | E11: 0 | F11: 0 | G11: 0 | H11: 4959.353 | I11: 690.048 | J11: 1791.954 | K11: 3105.268 | L11: 1399.546 | M11: 26404.443 | N11: 2785.456 | O11: 100.583 | P11: 99.161 | Q11: 2433.242 | R11: 2325.822 | S11: 5790.585 | T11: 5649.4 | U11: 3772.811 | V11: 122552.19 | W11: 377.886 | X11: 987.473 | Y11: 100.583 | Z11: 1084.911 | AA11: =H11*x_c_F+I11*x_c_CC+J11*x_c_DC+K11*x_c_HCC+L11*x_c_PLT+M11*x_c_SVRn+N11*x_c_SVRcc+O11*x_c_LT+P11*x_c_LT1 -> 3.5353436e+08 | AB11: =C11*x_c_DAA -> 76983424 | AC11: =C11*x_c_MON -> 19499975 | AD11: =D11*(1-x_testy) -> 0 | AE11: =E11*(1-x_testy) -> 0 | AF11: =F11*x_NAV -> 0 | AG11: =G11*x_FIX*(1-x_testy) -> 0 | AH11: =x_z_F*U11+(1-x_AGRI)*x_EMP*x_WLOSS*(x_PEN_K74*Q11+x_PEN_C22*R11) -> 38291658 | AI11: =x_AGRI*x_EMP*x_WLOSS*(x_PEN_K74*Q11+x_PEN_C22*R11) -> 2018312.2 | AJ11: =x_EMP*x_WAGE*(x_WLOSS*(Q11+R11)+S11)+U11*x_ABS_D*x_WAGE/365 -> 6.6056167e+08 | AK11: =AJ11*x_R_FUS -> 2.0900171e+08 | AL11: =AJ11*x_R_NFZ -> 51299880 | AM11: =AJ11*x_R_PIT -> 43916897 | AN11: =AJ11*x_R_FP -> 16844323 | AO11: =AA11+AB11+AC11+AD11+AF11 -> 4.5001776e+08 | AP11: =AO11+AE11+AG11+AH11+AI11+AK11+AL11+AM11+AN11 -> 8.1139054e+08 | AQ11: =AO11+AE11+AG11+AJ11 -> 1.1105794e+09 | AR11: =AB11+AC11+AD11+AF11 -> 96483399 | AS11: =AR11+AE11+AG11 -> 96483399
A12: 2035 | B12: 9 | C12: 3382.4 | D12: 0 | E12: 0 | F12: 0 | G12: 0 | H12: 5096.613 | I12: 733.024 | J12: 1841.734 | K12: 3192.708 | L12: 1391.204 | M12: 28873.036 | N12: 3098.339 | O12: 103.4 | P12: 101.992 | Q12: 2500.843 | R12: 2427.13 | S12: 6583.946 | T12: 5829.637 | U12: 3961.383 | V12: 123747.06 | W12: 387.39 | X12: 1007.655 | Y12: 103.4 | Z12: 1113.872 | AA12: =H12*x_c_F+I12*x_c_CC+J12*x_c_DC+K12*x_c_HCC+L12*x_c_PLT+M12*x_c_SVRn+N12*x_c_SVRcc+O12*x_c_LT+P12*x_c_LT1 -> 3.6377497e+08 | AB12: =C12*x_c_DAA -> 76983424 | AC12: =C12*x_c_MON -> 19499975 | AD12: =D12*(1-x_testy) -> 0 | AE12: =E12*(1-x_testy) -> 0 | AF12: =F12*x_NAV -> 0 | AG12: =G12*x_FIX*(1-x_testy) -> 0 | AH12: =x_z_F*U12+(1-x_AGRI)*x_EMP*x_WLOSS*(x_PEN_K74*Q12+x_PEN_C22*R12) -> 39778497 | AI12: =x_AGRI*x_EMP*x_WLOSS*(x_PEN_K74*Q12+x_PEN_C22*R12) -> 2090964.1 | AJ12: =x_EMP*x_WAGE*(x_WLOSS*(Q12+R12)+S12)+U12*x_ABS_D*x_WAGE/365 -> 7.3428658e+08 | AK12: =AJ12*x_R_FUS -> 2.3232827e+08 | AL12: =AJ12*x_R_NFZ -> 57025430 | AM12: =AJ12*x_R_PIT -> 48818436 | AN12: =AJ12*x_R_FP -> 18724308 | AO12: =AA12+AB12+AC12+AD12+AF12 -> 4.6025837e+08 | AP12: =AO12+AE12+AG12+AH12+AI12+AK12+AL12+AM12+AN12 -> 8.5902428e+08 | AQ12: =AO12+AE12+AG12+AJ12 -> 1.1945449e+09 | AR12: =AB12+AC12+AD12+AF12 -> 96483399 | AS12: =AR12+AE12+AG12 -> 96483399
A13: 2036 | B13: 10 | C13: 3382.4 | D13: 0 | E13: 0 | F13: 0 | G13: 0 | H13: 5205.286 | I13: 769.434 | J13: 1889.437 | K13: 3270.447 | L13: 1384.181 | M13: 31281.424 | N13: 3407.049 | O13: 106.074 | P13: 104.737 | Q13: 2570.382 | R13: 2524.174 | S13: 7402.236 | T13: 5974.72 | U13: 4127.049 | V13: 124924.61 | W13: 395.076 | X13: 1023.513 | Y13: 106.074 | Z13: 1140.287 | AA13: =H13*x_c_F+I13*x_c_CC+J13*x_c_DC+K13*x_c_HCC+L13*x_c_PLT+M13*x_c_SVRn+N13*x_c_SVRcc+O13*x_c_LT+P13*x_c_LT1 -> 3.7318839e+08 | AB13: =C13*x_c_DAA -> 76983424 | AC13: =C13*x_c_MON -> 19499975 | AD13: =D13*(1-x_testy) -> 0 | AE13: =E13*(1-x_testy) -> 0 | AF13: =F13*x_NAV -> 0 | AG13: =G13*x_FIX*(1-x_testy) -> 0 | AH13: =x_z_F*U13+(1-x_AGRI)*x_EMP*x_WLOSS*(x_PEN_K74*Q13+x_PEN_C22*R13) -> 41200753 | AI13: =x_AGRI*x_EMP*x_WLOSS*(x_PEN_K74*Q13+x_PEN_C22*R13) -> 2162459.9 | AJ13: =x_EMP*x_WAGE*(x_WLOSS*(Q13+R13)+S13)+U13*x_ABS_D*x_WAGE/365 -> 8.0999352e+08 | AK13: =AJ13*x_R_FUS -> 2.5628195e+08 | AL13: =AJ13*x_R_NFZ -> 62904907 | AM13: =AJ13*x_R_PIT -> 53851750 | AN13: =AJ13*x_R_FP -> 20654835 | AO13: =AA13+AB13+AC13+AD13+AF13 -> 4.6967179e+08 | AP13: =AO13+AE13+AG13+AH13+AI13+AK13+AL13+AM13+AN13 -> 9.0672844e+08 | AQ13: =AO13+AE13+AG13+AJ13 -> 1.2796653e+09 | AR13: =AB13+AC13+AD13+AF13 -> 96483399 | AS13: =AR13+AE13+AG13 -> 96483399
A14: 2037 | B14: 11 | C14: 3382.4 | D14: 0 | E14: 0 | F14: 0 | G14: 0 | H14: 5287.306 | I14: 798.818 | J14: 1933.378 | K14: 3336.679 | L14: 1378.183 | M14: 33629.044 | N14: 3708.913 | O14: 108.51 | P14: 107.292 | Q14: 2640.436 | R14: 2615.539 | S14: 8242.77 | T14: 6086.125 | U14: 4269.576 | V14: 126078.21 | W14: 400.913 | X14: 1035.066 | Y14: 108.51 | Z14: 1163.383 | AA14: =H14*x_c_F+I14*x_c_CC+J14*x_c_DC+K14*x_c_HCC+L14*x_c_PLT+M14*x_c_SVRn+N14*x_c_SVRcc+O14*x_c_LT+P14*x_c_LT1 -> 3.8157933e+08 | AB14: =C14*x_c_DAA -> 76983424 | AC14: =C14*x_c_MON -> 19499975 | AD14: =D14*(1-x_testy) -> 0 | AE14: =E14*(1-x_testy) -> 0 | AF14: =F14*x_NAV -> 0 | AG14: =G14*x_FIX*(1-x_testy) -> 0 | AH14: =x_z_F*U14+(1-x_AGRI)*x_EMP*x_WLOSS*(x_PEN_K74*Q14+x_PEN_C22*R14) -> 42539714 | AI14: =x_AGRI*x_EMP*x_WLOSS*(x_PEN_K74*Q14+x_PEN_C22*R14) -> 2231594.4 | AJ14: =x_EMP*x_WAGE*(x_WLOSS*(Q14+R14)+S14)+U14*x_ABS_D*x_WAGE/365 -> 8.8736001e+08 | AK14: =AJ14*x_R_FUS -> 2.8076071e+08 | AL14: =AJ14*x_R_NFZ -> 68913266 | AM14: =AJ14*x_R_PIT -> 58995397 | AN14: =AJ14*x_R_FP -> 22627680 | AO14: =AA14+AB14+AC14+AD14+AF14 -> 4.7806273e+08 | AP14: =AO14+AE14+AG14+AH14+AI14+AK14+AL14+AM14+AN14 -> 9.5413108e+08 | AQ14: =AO14+AE14+AG14+AJ14 -> 1.3654227e+09 | AR14: =AB14+AC14+AD14+AF14 -> 96483399 | AS14: =AR14+AE14+AG14 -> 96483399
... A52: 2075 | B52: 49 | C52: 3382.4 | D52: 0 | E52: 0 | F52: 0 | G52: 0 | H52: 2941.792 | I52: 396.397 | J52: 1844.997 | K52: 3124.199 | L52: 981.031 | M52: 97096.04 | N52: 6939.173 | O52: 103.665 | P52: 103.295 | Q52: 994.735 | R52: 1488.028 | S52: 3767.446 | T52: 3338.189 | U52: 2347.561 | V52: 171037.57 | W52: 359.971 | X52: 935.864 | Y52: 103.665 | Z52: 1085.654 | AA52: =H52*x_c_F+I52*x_c_CC+J52*x_c_DC+K52*x_c_HCC+L52*x_c_PLT+M52*x_c_SVRn+N52*x_c_SVRcc+O52*x_c_LT+P52*x_c_LT1 -> 3.9074791e+08 | AB52: =C52*x_c_DAA -> 76983424 | AC52: =C52*x_c_MON -> 19499975 | AD52: =D52*(1-x_testy) -> 0 | AE52: =E52*(1-x_testy) -> 0 | AF52: =F52*x_NAV -> 0 | AG52: =G52*x_FIX*(1-x_testy) -> 0 | AH52: =x_z_F*U52+(1-x_AGRI)*x_EMP*x_WLOSS*(x_PEN_K74*Q52+x_PEN_C22*R52) -> 20981732 | AI52: =x_AGRI*x_EMP*x_WLOSS*(x_PEN_K74*Q52+x_PEN_C22*R52) -> 1067838.7 | AJ52: =x_EMP*x_WAGE*(x_WLOSS*(Q52+R52)+S52)+U52*x_ABS_D*x_WAGE/365 -> 4.0937457e+08 | AK52: =AJ52*x_R_FUS -> 1.2952612e+08 | AL52: =AJ52*x_R_NFZ -> 31792439 | AM52: =AJ52*x_R_PIT -> 27216930 | AN52: =AJ52*x_R_FP -> 10439052 | AO52: =AA52+AB52+AC52+AD52+AF52 -> 4.8723131e+08 | AP52: =AO52+AE52+AG52+AH52+AI52+AK52+AL52+AM52+AN52 -> 7.0825541e+08 | AQ52: =AO52+AE52+AG52+AJ52 -> 8.9660588e+08 | AR52: =AB52+AC52+AD52+AF52 -> 96483399 | AS52: =AR52+AE52+AG52 -> 96483399

Sheet L_V1
A1: V1: Walidacja: dodatkowi leczeni jak w I1, bez kosztu wykrywania – liczebności (silnik, wartości) i koszty (formuły), zł/rok, niezdyskontowane. Szacunek modelu.
A2: rok | B2: t | C2: treated | D2: NFZ_diag | E2: MZ_SW | F2: nNAV | G2: FIXon | H2: cF03 | I2: cF4 | J2: cDC | K2: cHCC | L2: cPLT | M2: cSVn | N2: cSVc | O2: cLTn | P2: cLT1 | Q2: wAdv | R2: wHCC | S2: wGH | T2: cAbs | U2: cAbsW | V2: QALY | W2: newDC | X2: newHCC | Y2: LT | Z2: liverD | AA2: NFZ_med | AB2: NFZ_DAA | AC2: NFZ_mon | AD2: NFZ_diag_k | AE2: MZ_SW_k | AF2: NAV_k | AG2: FIX_k | AH2: ZUS | AI2: KRUS | AJ2: lostw | AK2: lost_FUS | AL2: lost_NFZ | AM2: lost_PIT | AN2: lost_FP | AO2: NFZ | AP2: PUBLIC | AQ2: SOCIETAL | AR2: INV_NFZ | AS2: INV_PUB
A3: 2026 | B3: 0 | C3: 5213.16 | D3: 0 | E3: 0 | F3: 0 | G3: 0 | H3: 2581.318 | I3: 231.61 | J3: 1579.158 | K3: 2524.378 | L3: 1540.438 | M3: 7100.45 | N3: 627.462 | O3: 89.046 | P3: 44.523 | Q3: 2134.589 | R3: 1702.999 | S3: 312.377 | T3: 2812.928 | U3: 1558.451 | V3: 113433.47 | W3: 265.352 | X3: 710.662 | Y3: 89.046 | Z3: 922.327 | AA3: =H3*x_c_F+I3*x_c_CC+J3*x_c_DC+K3*x_c_HCC+L3*x_c_PLT+M3*x_c_SVRn+N3*x_c_SVRcc+O3*x_c_LT+P3*x_c_LT1 -> 2.8383355e+08 | AB3: =C3*x_c_DAA -> 1.1865152e+08 | AC3: =C3*x_c_MON -> 30054545 | AD3: =D3*(1-x_testy) -> 0 | AE3: =E3*(1-x_testy) -> 0 | AF3: =F3*x_NAV -> 0 | AG3: =G3*x_FIX*(1-x_testy) -> 0 | AH3: =x_z_F*U3+(1-x_AGRI)*x_EMP*x_WLOSS*(x_PEN_K74*Q3+x_PEN_C22*R3) -> 27685181 | AI3: =x_AGRI*x_EMP*x_WLOSS*(x_PEN_K74*Q3+x_PEN_C22*R3) -> 1618157.1 | AJ3: =x_EMP*x_WAGE*(x_WLOSS*(Q3+R3)+S3)+U3*x_ABS_D*x_WAGE/365 -> 1.5682123e+08 | AK3: =AJ3*x_R_FUS -> 49618236 | AL3: =AJ3*x_R_NFZ -> 12178893 | AM3: =AJ3*x_R_PIT -> 10426130 | AN3: =AJ3*x_R_FP -> 3998941.2 | AO3: =AA3+AB3+AC3+AD3+AF3 -> 4.3253961e+08 | AP3: =AO3+AE3+AG3+AH3+AI3+AK3+AL3+AM3+AN3 -> 5.3806515e+08 | AQ3: =AO3+AE3+AG3+AJ3 -> 5.8936084e+08 | AR3: =AB3+AC3+AD3+AF3 -> 1.4870607e+08 | AS3: =AR3+AE3+AG3 -> 1.4870607e+08
A4: 2027 | B4: 1 | C4: 5576.635 | D4: 0 | E4: 0 | F4: 0 | G4: 0 | H4: 2728.1 | I4: 259.776 | J4: 1563.329 | K4: 2519.58 | L4: 1489.389 | M4: 12106.359 | N4: 1093.455 | O4: 87.89 | P4: 88.468 | Q4: 2137.52 | R4: 1715.76 | S4: 939.875 | T4: 2987.876 | U4: 1705.223 | V4: 114593.88 | W4: 274.078 | X4: 738.717 | Y4: 87.89 | Z4: 925.455 | AA4: =H4*x_c_F+I4*x_c_CC+J4*x_c_DC+K4*x_c_HCC+L4*x_c_PLT+M4*x_c_SVRn+N4*x_c_SVRcc+O4*x_c_LT+P4*x_c_LT1 -> 2.8824558e+08 | AB4: =C4*x_c_DAA -> 1.2692421e+08 | AC4: =C4*x_c_MON -> 32150025 | AD4: =D4*(1-x_testy) -> 0 | AE4: =E4*(1-x_testy) -> 0 | AF4: =F4*x_NAV -> 0 | AG4: =G4*x_FIX*(1-x_testy) -> 0 | AH4: =x_z_F*U4+(1-x_AGRI)*x_EMP*x_WLOSS*(x_PEN_K74*Q4+x_PEN_C22*R4) -> 28091794 | AI4: =x_AGRI*x_EMP*x_WLOSS*(x_PEN_K74*Q4+x_PEN_C22*R4) -> 1625088.4 | AJ4: =x_EMP*x_WAGE*(x_WLOSS*(Q4+R4)+S4)+U4*x_ABS_D*x_WAGE/365 -> 2.1126676e+08 | AK4: =AJ4*x_R_FUS -> 66844804 | AL4: =AJ4*x_R_NFZ -> 16407188 | AM4: =AJ4*x_R_PIT -> 14045896 | AN4: =AJ4*x_R_FP -> 5387302.5 | AO4: =AA4+AB4+AC4+AD4+AF4 -> 4.4731982e+08 | AP4: =AO4+AE4+AG4+AH4+AI4+AK4+AL4+AM4+AN4 -> 5.7972189e+08 | AQ4: =AO4+AE4+AG4+AJ4 -> 6.5858658e+08 | AR4: =AB4+AC4+AD4+AF4 -> 1.5907424e+08 | AS4: =AR4+AE4+AG4 -> 1.5907424e+08
A5: 2028 | B5: 2 | C5: 5921.215 | D5: 0 | E5: 0 | F5: 0 | G5: 0 | H5: 2782.017 | I5: 281.64 | J5: 1558.707 | K5: 2542.654 | L5: 1475.757 | M5: 17159.078 | N5: 1586.693 | O5: 87.523 | P5: 87.707 | Q5: 2145.234 | R5: 1751.363 | S5: 1572.496 | T5: 3063.657 | U5: 1797.2 | V5: 115841.09 | W5: 283.892 | X5: 766.181 | Y5: 87.523 | Z5: 926.072 | AA5: =H5*x_c_F+I5*x_c_CC+J5*x_c_DC+K5*x_c_HCC+L5*x_c_PLT+M5*x_c_SVRn+N5*x_c_SVRcc+O5*x_c_LT+P5*x_c_LT1 -> 2.9374143e+08 | AB5: =C5*x_c_DAA -> 1.3476685e+08 | AC5: =C5*x_c_MON -> 34136574 | AD5: =D5*(1-x_testy) -> 0 | AE5: =E5*(1-x_testy) -> 0 | AF5: =F5*x_NAV -> 0 | AG5: =G5*x_FIX*(1-x_testy) -> 0 | AH5: =x_z_F*U5+(1-x_AGRI)*x_EMP*x_WLOSS*(x_PEN_K74*Q5+x_PEN_C22*R5) -> 28570668 | AI5: =x_AGRI*x_EMP*x_WLOSS*(x_PEN_K74*Q5+x_PEN_C22*R5) -> 1644242.2 | AJ5: =x_EMP*x_WAGE*(x_WLOSS*(Q5+R5)+S5)+U5*x_ABS_D*x_WAGE/365 -> 2.6689234e+08 | AK5: =AJ5*x_R_FUS -> 84444737 | AL5: =AJ5*x_R_NFZ -> 20727126 | AM5: =AJ5*x_R_PIT -> 17744117 | AN5: =AJ5*x_R_FP -> 6805754.7 | AO5: =AA5+AB5+AC5+AD5+AF5 -> 4.6264486e+08 | AP5: =AO5+AE5+AG5+AH5+AI5+AK5+AL5+AM5+AN5 -> 6.2258151e+08 | AQ5: =AO5+AE5+AG5+AJ5 -> 7.295372e+08 | AR5: =AB5+AC5+AD5+AF5 -> 1.6890343e+08 | AS5: =AR5+AE5+AG5 -> 1.6890343e+08
A6: 2029 | B6: 3 | C6: 5892.245 | D6: 0 | E6: 0 | F6: 0 | G6: 0 | H6: 2750.261 | I6: 295.954 | J6: 1564.041 | K6: 2584.625 | L6: 1461.15 | M6: 22088.431 | N6: 2091.139 | O6: 87.808 | P6: 87.666 | Q6: 2161.57 | R6: 1803.154 | S6: 2212.729 | T6: 3046.215 | U6: 1834.537 | V6: 117143.13 | W6: 294.143 | X6: 792.343 | Y6: 87.808 | Z6: 934.044 | AA6: =H6*x_c_F+I6*x_c_CC+J6*x_c_DC+K6*x_c_HCC+L6*x_c_PLT+M6*x_c_SVRn+N6*x_c_SVRcc+O6*x_c_LT+P6*x_c_LT1 -> 3.0049275e+08 | AB6: =C6*x_c_DAA -> 1.341075e+08 | AC6: =C6*x_c_MON -> 33969558 | AD6: =D6*(1-x_testy) -> 0 | AE6: =E6*(1-x_testy) -> 0 | AF6: =F6*x_NAV -> 0 | AG6: =G6*x_FIX*(1-x_testy) -> 0 | AH6: =x_z_F*U6+(1-x_AGRI)*x_EMP*x_WLOSS*(x_PEN_K74*Q6+x_PEN_C22*R6) -> 29099729 | AI6: =x_AGRI*x_EMP*x_WLOSS*(x_PEN_K74*Q6+x_PEN_C22*R6) -> 1674138.3 | AJ6: =x_EMP*x_WAGE*(x_WLOSS*(Q6+R6)+S6)+U6*x_ABS_D*x_WAGE/365 -> 3.238185e+08 | AK6: =AJ6*x_R_FUS -> 1.0245617e+08 | AL6: =AJ6*x_R_NFZ -> 25148068 | AM6: =AJ6*x_R_PIT -> 21528805 | AN6: =AJ6*x_R_FP -> 8257371.6 | AO6: =AA6+AB6+AC6+AD6+AF6 -> 4.6856981e+08 | AP6: =AO6+AE6+AG6+AH6+AI6+AK6+AL6+AM6+AN6 -> 6.5673409e+08 | AQ6: =AO6+AE6+AG6+AJ6 -> 7.923883e+08 | AR6: =AB6+AC6+AD6+AF6 -> 1.6807705e+08 | AS6: =AR6+AE6+AG6 -> 1.6807705e+08
A7: 2030 | B7: 4 | C7: 5864.531 | D7: 0 | E7: 0 | F7: 0 | G7: 0 | H7: 2719.483 | I7: 309.91 | J7: 1577.536 | K7: 2638.027 | L7: 1446.187 | M7: 26894.042 | N7: 2605.141 | O7: 88.61 | P7: 88.209 | Q7: 2185.593 | R7: 1865.614 | S7: 2865.368 | T7: 3029.393 | U7: 1870.053 | V7: 118486.3 | W7: 303.985 | X7: 815.855 | Y7: 88.61 | Z7: 947.075 | AA7: =H7*x_c_F+I7*x_c_CC+J7*x_c_DC+K7*x_c_HCC+L7*x_c_PLT+M7*x_c_SVRn+N7*x_c_SVRcc+O7*x_c_LT+P7*x_c_LT1 -> 3.0825528e+08 | AB7: =C7*x_c_DAA -> 1.3347673e+08 | AC7: =C7*x_c_MON -> 33809783 | AD7: =D7*(1-x_testy) -> 0 | AE7: =E7*(1-x_testy) -> 0 | AF7: =F7*x_NAV -> 0 | AG7: =G7*x_FIX*(1-x_testy) -> 0 | AH7: =x_z_F*U7+(1-x_AGRI)*x_EMP*x_WLOSS*(x_PEN_K74*Q7+x_PEN_C22*R7) -> 29744215 | AI7: =x_AGRI*x_EMP*x_WLOSS*(x_PEN_K74*Q7+x_PEN_C22*R7) -> 1711911.3 | AJ7: =x_EMP*x_WAGE*(x_WLOSS*(Q7+R7)+S7)+U7*x_ABS_D*x_WAGE/365 -> 3.8239786e+08 | AK7: =AJ7*x_R_FUS -> 1.2099068e+08 | AL7: =AJ7*x_R_NFZ -> 29697400 | AM7: =AJ7*x_R_PIT -> 25423406 | AN7: =AJ7*x_R_FP -> 9751145.4 | AO7: =AA7+AB7+AC7+AD7+AF7 -> 4.7554179e+08 | AP7: =AO7+AE7+AG7+AH7+AI7+AK7+AL7+AM7+AN7 -> 6.9286055e+08 | AQ7: =AO7+AE7+AG7+AJ7 -> 8.5793965e+08 | AR7: =AB7+AC7+AD7+AF7 -> 1.6728651e+08 | AS7: =AR7+AE7+AG7 -> 1.6728651e+08
A8: 2031 | B8: 5 | C8: 5837.956 | D8: 0 | E8: 0 | F8: 0 | G8: 0 | H8: 2690.204 | I8: 322.932 | J8: 1596.984 | K8: 2696.394 | L8: 1431.36 | M8: 31576.919 | N8: 3125.977 | O8: 89.777 | P8: 89.193 | Q8: 2215.991 | R8: 1933.958 | S8: 3533.522 | T8: 3013.136 | U8: 1903.771 | V8: 119860.72 | W8: 312.807 | X8: 835.793 | Y8: 89.777 | Z8: 963.061 | AA8: =H8*x_c_F+I8*x_c_CC+J8*x_c_DC+K8*x_c_HCC+L8*x_c_PLT+M8*x_c_SVRn+N8*x_c_SVRcc+O8*x_c_LT+P8*x_c_LT1 -> 3.1653087e+08 | AB8: =C8*x_c_DAA -> 1.3287188e+08 | AC8: =C8*x_c_MON -> 33656575 | AD8: =D8*(1-x_testy) -> 0 | AE8: =E8*(1-x_testy) -> 0 | AF8: =F8*x_NAV -> 0 | AG8: =G8*x_FIX*(1-x_testy) -> 0 | AH8: =x_z_F*U8+(1-x_AGRI)*x_EMP*x_WLOSS*(x_PEN_K74*Q8+x_PEN_C22*R8) -> 30463573 | AI8: =x_AGRI*x_EMP*x_WLOSS*(x_PEN_K74*Q8+x_PEN_C22*R8) -> 1754877.5 | AJ8: =x_EMP*x_WAGE*(x_WLOSS*(Q8+R8)+S8)+U8*x_ABS_D*x_WAGE/365 -> 4.4269601e+08 | AK8: =AJ8*x_R_FUS -> 1.4006902e+08 | AL8: =AJ8*x_R_NFZ -> 34380215 | AM8: =AJ8*x_R_PIT -> 29432279 | AN8: =AJ8*x_R_FP -> 11288748 | AO8: =AA8+AB8+AC8+AD8+AF8 -> 4.8305932e+08 | AP8: =AO8+AE8+AG8+AH8+AI8+AK8+AL8+AM8+AN8 -> 7.3044804e+08 | AQ8: =AO8+AE8+AG8+AJ8 -> 9.2575534e+08 | AR8: =AB8+AC8+AD8+AF8 -> 1.6652845e+08 | AS8: =AR8+AE8+AG8 -> 1.6652845e+08
A9: 2032 | B9: 6 | C9: 5812.447 | D9: 0 | E9: 0 | F9: 0 | G9: 0 | H9: 2662.817 | I9: 334.582 | J9: 1620.016 | K9: 2754.305 | L9: 1416.993 | M9: 36138.643 | N9: 3650.07 | O9: 91.153 | P9: 90.465 | Q9: 2251.22 | R9: 2004.149 | S9: 4218.711 | T9: 2997.399 | U9: 1935.739 | V9: 121256.47 | W9: 320.177 | X9: 851.541 | Y9: 91.153 | Z9: 980.102 | AA9: =H9*x_c_F+I9*x_c_CC+J9*x_c_DC+K9*x_c_HCC+L9*x_c_PLT+M9*x_c_SVRn+N9*x_c_SVRcc+O9*x_c_LT+P9*x_c_LT1 -> 3.2487536e+08 | AB9: =C9*x_c_DAA -> 1.3229129e+08 | AC9: =C9*x_c_MON -> 33509512 | AD9: =D9*(1-x_testy) -> 0 | AE9: =E9*(1-x_testy) -> 0 | AF9: =F9*x_NAV -> 0 | AG9: =G9*x_FIX*(1-x_testy) -> 0 | AH9: =x_z_F*U9+(1-x_AGRI)*x_EMP*x_WLOSS*(x_PEN_K74*Q9+x_PEN_C22*R9) -> 31221018 | AI9: =x_AGRI*x_EMP*x_WLOSS*(x_PEN_K74*Q9+x_PEN_C22*R9) -> 1800599 | AJ9: =x_EMP*x_WAGE*(x_WLOSS*(Q9+R9)+S9)+U9*x_ABS_D*x_WAGE/365 -> 5.0466002e+08 | AK9: =AJ9*x_R_FUS -> 1.5967443e+08 | AL9: =AJ9*x_R_NFZ -> 39192402 | AM9: =AJ9*x_R_PIT -> 33551905 | AN9: =AJ9*x_R_FP -> 12868831 | AO9: =AA9+AB9+AC9+AD9+AF9 -> 4.9067617e+08 | AP9: =AO9+AE9+AG9+AH9+AI9+AK9+AL9+AM9+AN9 -> 7.6898536e+08 | AQ9: =AO9+AE9+AG9+AJ9 -> 9.9533619e+08 | AR9: =AB9+AC9+AD9+AF9 -> 1.6580081e+08 | AS9: =AR9+AE9+AG9 -> 1.6580081e+08
A10: 2033 | B10: 7 | C10: 5787.908 | D10: 0 | E10: 0 | F10: 0 | G10: 0 | H10: 2637.604 | I10: 344.541 | J10: 1644.32 | K10: 2807.41 | L10: 1403.264 | M10: 40581.419 | N10: 4173.275 | O10: 92.597 | P10: 91.875 | Q10: 2289.652 | R10: 2072.888 | S10: 4921.085 | T10: 2982.145 | U10: 1965.997 | V10: 122665 | W10: 325.824 | X10: 862.768 | Y10: 92.597 | Z10: 996.632 | AA10: =H10*x_c_F+I10*x_c_CC+J10*x_c_DC+K10*x_c_HCC+L10*x_c_PLT+M10*x_c_SVRn+N10*x_c_SVRcc+O10*x_c_LT+P10*x_c_LT1 -> 3.3291277e+08 | AB10: =C10*x_c_DAA -> 1.3173279e+08 | AC10: =C10*x_c_MON -> 33368041 | AD10: =D10*(1-x_testy) -> 0 | AE10: =E10*(1-x_testy) -> 0 | AF10: =F10*x_NAV -> 0 | AG10: =G10*x_FIX*(1-x_testy) -> 0 | AH10: =x_z_F*U10+(1-x_AGRI)*x_EMP*x_WLOSS*(x_PEN_K74*Q10+x_PEN_C22*R10) -> 31984288 | AI10: =x_AGRI*x_EMP*x_WLOSS*(x_PEN_K74*Q10+x_PEN_C22*R10) -> 1846937.8 | AJ10: =x_EMP*x_WAGE*(x_WLOSS*(Q10+R10)+S10)+U10*x_ABS_D*x_WAGE/365 -> 5.6814152e+08 | AK10: =AJ10*x_R_FUS -> 1.7975998e+08 | AL10: =AJ10*x_R_NFZ -> 44122439 | AM10: =AJ10*x_R_PIT -> 37772420 | AN10: =AJ10*x_R_FP -> 14487609 | AO10: =AA10+AB10+AC10+AD10+AF10 -> 4.980136e+08 | AP10: =AO10+AE10+AG10+AH10+AI10+AK10+AL10+AM10+AN10 -> 8.0798727e+08 | AQ10: =AO10+AE10+AG10+AJ10 -> 1.0661551e+09 | AR10: =AB10+AC10+AD10+AF10 -> 1.6510083e+08 | AS10: =AR10+AE10+AG10 -> 1.6510083e+08
A11: 2034 | B11: 8 | C11: 5764.307 | D11: 0 | E11: 0 | F11: 0 | G11: 0 | H11: 2614.751 | I11: 352.597 | J11: 1667.77 | K11: 2852.363 | L11: 1390.202 | M11: 44907.583 | N11: 4691.051 | O11: 93.976 | P11: 93.286 | Q11: 2329.669 | R11: 2137.573 | S11: 5639.581 | T11: 2967.348 | U11: 1994.584 | V11: 124078.8 | W11: 329.595 | X11: 869.342 | Y11: 93.976 | Z11: 1011.33 | AA11: =H11*x_c_F+I11*x_c_CC+J11*x_c_DC+K11*x_c_HCC+L11*x_c_PLT+M11*x_c_SVRn+N11*x_c_SVRcc+O11*x_c_LT+P11*x_c_LT1 -> 3.403315e+08 | AB11: =C11*x_c_DAA -> 1.3119563e+08 | AC11: =C11*x_c_MON -> 33231979 | AD11: =D11*(1-x_testy) -> 0 | AE11: =E11*(1-x_testy) -> 0 | AF11: =F11*x_NAV -> 0 | AG11: =G11*x_FIX*(1-x_testy) -> 0 | AH11: =x_z_F*U11+(1-x_AGRI)*x_EMP*x_WLOSS*(x_PEN_K74*Q11+x_PEN_C22*R11) -> 32725944 | AI11: =x_AGRI*x_EMP*x_WLOSS*(x_PEN_K74*Q11+x_PEN_C22*R11) -> 1892075.1 | AJ11: =x_EMP*x_WAGE*(x_WLOSS*(Q11+R11)+S11)+U11*x_ABS_D*x_WAGE/365 -> 6.3291187e+08 | AK11: =AJ11*x_R_FUS -> 2.0025332e+08 | AL11: =AJ11*x_R_NFZ -> 49152569 | AM11: =AJ11*x_R_PIT -> 42078623 | AN11: =AJ11*x_R_FP -> 16139253 | AO11: =AA11+AB11+AC11+AD11+AF11 -> 5.047591e+08 | AP11: =AO11+AE11+AG11+AH11+AI11+AK11+AL11+AM11+AN11 -> 8.4700088e+08 | AQ11: =AO11+AE11+AG11+AJ11 -> 1.137671e+09 | AR11: =AB11+AC11+AD11+AF11 -> 1.6442761e+08 | AS11: =AR11+AE11+AG11 -> 1.6442761e+08
A12: 2035 | B12: 9 | C12: 5741.579 | D12: 0 | E12: 0 | F12: 0 | G12: 0 | H12: 2401.903 | I12: 331.735 | J12: 1688.516 | K12: 2886.756 | L12: 1377.714 | M12: 48741.965 | N12: 5145.901 | O12: 95.185 | P12: 94.581 | Q12: 2369.737 | R12: 2196.226 | S12: 6372.126 | T12: 2733.637 | U12: 1870.026 | V12: 125467.85 | W12: 331.444 | X12: 871.328 | Y12: 95.185 | Z12: 1023.22 | AA12: =H12*x_c_F+I12*x_c_CC+J12*x_c_DC+K12*x_c_HCC+L12*x_c_PLT+M12*x_c_SVRn+N12*x_c_SVRcc+O12*x_c_LT+P12*x_c_LT1 -> 3.4579923e+08 | AB12: =C12*x_c_DAA -> 1.3067834e+08 | AC12: =C12*x_c_MON -> 33100949 | AD12: =D12*(1-x_testy) -> 0 | AE12: =E12*(1-x_testy) -> 0 | AF12: =F12*x_NAV -> 0 | AG12: =G12*x_FIX*(1-x_testy) -> 0 | AH12: =x_z_F*U12+(1-x_AGRI)*x_EMP*x_WLOSS*(x_PEN_K74*Q12+x_PEN_C22*R12) -> 33111820 | AI12: =x_AGRI*x_EMP*x_WLOSS*(x_PEN_K74*Q12+x_PEN_C22*R12) -> 1934507.2 | AJ12: =x_EMP*x_WAGE*(x_WLOSS*(Q12+R12)+S12)+U12*x_ABS_D*x_WAGE/365 -> 6.9823442e+08 | AK12: =AJ12*x_R_FUS -> 2.2092137e+08 | AL12: =AJ12*x_R_NFZ -> 54225584 | AM12: =AJ12*x_R_PIT -> 46421539 | AN12: =AJ12*x_R_FP -> 17804978 | AO12: =AA12+AB12+AC12+AD12+AF12 -> 5.0957851e+08 | AP12: =AO12+AE12+AG12+AH12+AI12+AK12+AL12+AM12+AN12 -> 8.8399831e+08 | AQ12: =AO12+AE12+AG12+AJ12 -> 1.2078129e+09 | AR12: =AB12+AC12+AD12+AF12 -> 1.6377929e+08 | AS12: =AR12+AE12+AG12 -> 1.6377929e+08
A13: 2036 | B13: 10 | C13: 4832 | D13: 0 | E13: 0 | F13: 0 | G13: 0 | H13: 2197.105 | I13: 309.251 | J13: 1705.908 | K13: 2911.047 | L13: 1365.586 | M13: 52100.495 | N13: 5535.595 | O13: 96.13 | P13: 95.658 | Q13: 2409.161 | R13: 2249.068 | S13: 7115.807 | T13: 2506.356 | U13: 1745.465 | V13: 126825.32 | W13: 333.187 | X13: 873.034 | Y13: 96.13 | Z13: 1031.517 | AA13: =H13*x_c_F+I13*x_c_CC+J13*x_c_DC+K13*x_c_HCC+L13*x_c_PLT+M13*x_c_SVRn+N13*x_c_SVRcc+O13*x_c_LT+P13*x_c_LT1 -> 3.5002687e+08 | AB13: =C13*x_c_DAA -> 109976320 | AC13: =C13*x_c_MON -> 27857108 | AD13: =D13*(1-x_testy) -> 0 | AE13: =E13*(1-x_testy) -> 0 | AF13: =F13*x_NAV -> 0 | AG13: =G13*x_FIX*(1-x_testy) -> 0 | AH13: =x_z_F*U13+(1-x_AGRI)*x_EMP*x_WLOSS*(x_PEN_K74*Q13+x_PEN_C22*R13) -> 33454094 | AI13: =x_AGRI*x_EMP*x_WLOSS*(x_PEN_K74*Q13+x_PEN_C22*R13) -> 1974057.6 | AJ13: =x_EMP*x_WAGE*(x_WLOSS*(Q13+R13)+S13)+U13*x_ABS_D*x_WAGE/365 -> 7.6429515e+08 | AK13: =AJ13*x_R_FUS -> 2.4182299e+08 | AL13: =AJ13*x_R_NFZ -> 59355926 | AM13: =AJ13*x_R_PIT -> 50813532 | AN13: =AJ13*x_R_FP -> 19489526 | AO13: =AA13+AB13+AC13+AD13+AF13 -> 4.878603e+08 | AP13: =AO13+AE13+AG13+AH13+AI13+AK13+AL13+AM13+AN13 -> 8.9477042e+08 | AQ13: =AO13+AE13+AG13+AJ13 -> 1.2521554e+09 | AR13: =AB13+AC13+AD13+AF13 -> 1.3783343e+08 | AS13: =AR13+AE13+AG13 -> 1.3783343e+08
A14: 2037 | B14: 11 | C14: 4832 | D14: 0 | E14: 0 | F14: 0 | G14: 0 | H14: 2192.396 | I14: 312.245 | J14: 1719.478 | K14: 2925.845 | L14: 1353.496 | M14: 55375.24 | N14: 5911.053 | O14: 96.856 | P14: 96.493 | Q14: 2447.363 | R14: 2296.446 | S14: 7867.498 | T14: 2504.64 | U14: 1772.488 | V14: 128166.75 | W14: 333.194 | X14: 870.786 | Y14: 96.856 | Z14: 1037.02 | AA14: =H14*x_c_F+I14*x_c_CC+J14*x_c_DC+K14*x_c_HCC+L14*x_c_PLT+M14*x_c_SVRn+N14*x_c_SVRcc+O14*x_c_LT+P14*x_c_LT1 -> 3.5414316e+08 | AB14: =C14*x_c_DAA -> 109976320 | AC14: =C14*x_c_MON -> 27857108 | AD14: =D14*(1-x_testy) -> 0 | AE14: =E14*(1-x_testy) -> 0 | AF14: =F14*x_NAV -> 0 | AG14: =G14*x_FIX*(1-x_testy) -> 0 | AH14: =x_z_F*U14+(1-x_AGRI)*x_EMP*x_WLOSS*(x_PEN_K74*Q14+x_PEN_C22*R14) -> 34063308 | AI14: =x_AGRI*x_EMP*x_WLOSS*(x_PEN_K74*Q14+x_PEN_C22*R14) -> 2010653.2 | AJ14: =x_EMP*x_WAGE*(x_WLOSS*(Q14+R14)+S14)+U14*x_ABS_D*x_WAGE/365 -> 8.3126523e+08 | AK14: =AJ14*x_R_FUS -> 2.6301232e+08 | AL14: =AJ14*x_R_NFZ -> 64556889 | AM14: =AJ14*x_R_PIT -> 55265982 | AN14: =AJ14*x_R_FP -> 21197263 | AO14: =AA14+AB14+AC14+AD14+AF14 -> 4.9197659e+08 | AP14: =AO14+AE14+AG14+AH14+AI14+AK14+AL14+AM14+AN14 -> 9.32083e+08 | AQ14: =AO14+AE14+AG14+AJ14 -> 1.3232418e+09 | AR14: =AB14+AC14+AD14+AF14 -> 1.3783343e+08 | AS14: =AR14+AE14+AG14 -> 1.3783343e+08
... A52: 2075 | B52: 49 | C52: 4832 | D52: 0 | E52: 0 | F52: 0 | G52: 0 | H52: 2275.333 | I52: 198.088 | J52: 998.311 | K52: 1726.201 | L52: 623.744 | M52: 148024.4 | N52: 7675.367 | O52: 56.743 | P52: 56.826 | Q52: 603.504 | R52: 890.852 | S52: 2482.983 | T52: 2473.42 | U52: 1837.38 | V52: 180765.24 | W52: 184.898 | X52: 502.526 | Y52: 56.743 | Z52: 604.432 | AA52: =H52*x_c_F+I52*x_c_CC+J52*x_c_DC+K52*x_c_HCC+L52*x_c_PLT+M52*x_c_SVRn+N52*x_c_SVRcc+O52*x_c_LT+P52*x_c_LT1 -> 2.880617e+08 | AB52: =C52*x_c_DAA -> 109976320 | AC52: =C52*x_c_MON -> 27857108 | AD52: =D52*(1-x_testy) -> 0 | AE52: =E52*(1-x_testy) -> 0 | AF52: =F52*x_NAV -> 0 | AG52: =G52*x_FIX*(1-x_testy) -> 0 | AH52: =x_z_F*U52+(1-x_AGRI)*x_EMP*x_WLOSS*(x_PEN_K74*Q52+x_PEN_C22*R52) -> 13497348 | AI52: =x_AGRI*x_EMP*x_WLOSS*(x_PEN_K74*Q52+x_PEN_C22*R52) -> 642464.53 | AJ52: =x_EMP*x_WAGE*(x_WLOSS*(Q52+R52)+S52)+U52*x_ABS_D*x_WAGE/365 -> 2.6600998e+08 | AK52: =AJ52*x_R_FUS -> 84165557 | AL52: =AJ52*x_R_NFZ -> 20658601 | AM52: =AJ52*x_R_PIT -> 17685454 | AN52: =AJ52*x_R_FP -> 6783254.5 | AO52: =AA52+AB52+AC52+AD52+AF52 -> 4.2589513e+08 | AP52: =AO52+AE52+AG52+AH52+AI52+AK52+AL52+AM52+AN52 -> 5.6932781e+08 | AQ52: =AO52+AE52+AG52+AJ52 -> 6.9190511e+08 | AR52: =AB52+AC52+AD52+AF52 -> 1.3783343e+08 | AS52: =AR52+AE52+AG52 -> 1.3783343e+08

Sheet Inw_S0
A1: S0 vs status quo (S1): Brak leczenia (zaniechanie) – SZACUNEK MODELU
A2: Horyzont (lata) – zmień w Ustawienia!B4 | B2: =x_H -> 20
A3: Inwestycja (sektor publiczny, zdysk., zł) | B3: =SUM(H13:H62) -> -1.8035946e+09
A4: Saldo netto sektor publiczny (zdysk., zł; <0 = oszczędność) | B4: =SUM(F13:F62) -> 1.0355185e+09
A5: Zwroty = inwestycja − saldo (zł) | B5: =B3-B4 -> -2.8391131e+09
A6: ROI = (zwroty − inwestycja)/|inwestycja| | B6: =IF(B3=0,"—",(B5-B3)/ABS(B3)) -> -0.57414148
A7: Rok zwrotu – sektor publiczny | B7: =IFERROR(INDEX(A13:A62,MATCH(1,M13:M62,0)),"brak w horyzoncie") -> brak w horyzoncie
A8: Rok zwrotu – NFZ | B8: =IFERROR(INDEX(A13:A62,MATCH(1,N13:N62,0)),"brak w horyzoncie") -> brak w horyzoncie
A9: Saldo netto NFZ (zdysk., zł) | B9: =SUM(E13:E62) -> -1.4471291e+08
A10: ICER sektor publiczny (zł/QALY; <0 = dominuje) – dodatkowo | B10: =IFERROR(B4/SUM(P13:P62),"—") -> -19245.325
A11: ICER NFZ (zł/QALY) – GŁÓWNY, porównywany z progiem 244 821 zł | B11: =IFERROR(B9/SUM(P13:P62),"—") -> 2689.5194
A12: rok | B12: t | C12: DF koszty | D12: DF efekty | E12: Δ NFZ | F12: Δ publiczny | G12: Δ społeczny | H12: Δ inwestycja (publ.) | I12: skum. NFZ | J12: skum. publiczny | K12: skum. społeczny | L12: maks. dotąd (publ.) | M12: zwrot? (publ.) | N12: zwrot? (NFZ) | O12: maks. dotąd (NFZ) | P12: Δ QALY
A13: 2026 | B13: 0 | C13: =IF(B13<x_H,(1+x_dk)^(-B13),0) -> 1 | D13: =IF(B13<x_H,(1+x_de)^(-B13),0) -> 1 | E13: =(L_S0!AO3-L_S1!AO3)*C13 -> -1.3176842e+08 | F13: =(L_S0!AP3-L_S1!AP3)*C13 -> -1.2483278e+08 | G13: =(L_S0!AQ3-L_S1!AQ3)*C13 -> -1.2582071e+08 | H13: =(L_S0!AS3-L_S1!AS3)*C13 -> -1.3783343e+08 | I13: =E13 -> -1.3176842e+08 | J13: =F13 -> -1.2483278e+08 | K13: =G13 -> -1.2582071e+08 | L13: =J13 -> -1.2483278e+08 | M13: 0 | N13: 0 | O13: =I13 -> -1.3176842e+08 | P13: =(L_S0!V3-L_S1!V3)*D13 -> -391.087
A14: 2027 | B14: 1 | C14: =IF(B14<x_H,(1+x_dk)^(-B14),0) -> 0.95238095 | D14: =IF(B14<x_H,(1+x_de)^(-B14),0) -> 0.96618357 | E14: =(L_S0!AO4-L_S1!AO4)*C14 -> -1.1538632e+08 | F14: =(L_S0!AP4-L_S1!AP4)*C14 -> -1.006263e+08 | G14: =(L_S0!AQ4-L_S1!AQ4)*C14 -> -1.0248408e+08 | H14: =(L_S0!AS4-L_S1!AS4)*C14 -> -1.3126993e+08 | I14: =I13+E14 -> -2.4715474e+08 | J14: =J13+F14 -> -2.2545908e+08 | K14: =K13+G14 -> -2.2830478e+08 | L14: =MAX(L13,J14) -> -1.2483278e+08 | M14: =IF(AND(B14<x_H,J14<=0,L13>0),1,0) -> 0 | N14: =IF(AND(B14<x_H,I14<=0,O13>0),1,0) -> 0 | O14: =MAX(O13,I14) -> -1.3176842e+08 | P14: =(L_S0!V4-L_S1!V4)*D14 -> -642.27053
A15: 2028 | B15: 2 | C15: =IF(B15<x_H,(1+x_dk)^(-B15),0) -> 0.90702948 | D15: =IF(B15<x_H,(1+x_de)^(-B15),0) -> 0.9335107 | E15: =(L_S0!AO5-L_S1!AO5)*C15 -> -99298387 | F15: =(L_S0!AP5-L_S1!AP5)*C15 -> -76726362 | G15: =(L_S0!AQ5-L_S1!AQ5)*C15 -> -79084871 | H15: =(L_S0!AS5-L_S1!AS5)*C15 -> -1.2501898e+08 | I15: =I14+E15 -> -3.4645313e+08 | J15: =J14+F15 -> -3.0218545e+08 | K15: =K14+G15 -> -3.0738965e+08 | L15: =MAX(L14,J15) -> -1.2483278e+08 | M15: =IF(AND(B15<x_H,J15<=0,L14>0),1,0) -> 0 | N15: =IF(AND(B15<x_H,I15<=0,O14>0),1,0) -> 0 | O15: =MAX(O14,I15) -> -1.3176842e+08 | P15: =(L_S0!V5-L_S1!V5)*D15 -> -890.92581
A16: 2029 | B16: 3 | C16: =IF(B16<x_H,(1+x_dk)^(-B16),0) -> 0.8638376 | D16: =IF(B16<x_H,(1+x_de)^(-B16),0) -> 0.90194271 | E16: =(L_S0!AO6-L_S1!AO6)*C16 -> -83573027 | F16: =(L_S0!AP6-L_S1!AP6)*C16 -> -53162170 | G16: =(L_S0!AQ6-L_S1!AQ6)*C16 -> -55573010 | H16: =(L_S0!AS6-L_S1!AS6)*C16 -> -1.190657e+08 | I16: =I15+E16 -> -4.3002615e+08 | J16: =J15+F16 -> -3.5534762e+08 | K16: =K15+G16 -> -3.6296266e+08 | L16: =MAX(L15,J16) -> -1.2483278e+08 | M16: =IF(AND(B16<x_H,J16<=0,L15>0),1,0) -> 0 | N16: =IF(AND(B16<x_H,I16<=0,O15>0),1,0) -> 0 | O16: =MAX(O15,I16) -> -1.3176842e+08 | P16: =(L_S0!V6-L_S1!V6)*D16 -> -1139.2465
A17: 2030 | B17: 4 | C17: =IF(B17<x_H,(1+x_dk)^(-B17),0) -> 0.82270247 | D17: =IF(B17<x_H,(1+x_de)^(-B17),0) -> 0.87144223 | E17: =(L_S0!AO7-L_S1!AO7)*C17 -> -68270380 | F17: =(L_S0!AP7-L_S1!AP7)*C17 -> -29963663 | G17: =(L_S0!AQ7-L_S1!AQ7)*C17 -> -31918816 | H17: =(L_S0!AS7-L_S1!AS7)*C17 -> -1.133959e+08 | I17: =I16+E17 -> -4.9829653e+08 | J17: =J16+F17 -> -3.8531128e+08 | K17: =K16+G17 -> -3.9488148e+08 | L17: =MAX(L16,J17) -> -1.2483278e+08 | M17: =IF(AND(B17<x_H,J17<=0,L16>0),1,0) -> 0 | N17: =IF(AND(B17<x_H,I17<=0,O16>0),1,0) -> 0 | O17: =MAX(O16,I17) -> -1.3176842e+08 | P17: =(L_S0!V7-L_S1!V7)*D17 -> -1388.2589
A18: 2031 | B18: 5 | C18: =IF(B18<x_H,(1+x_dk)^(-B18),0) -> 0.78352617 | D18: =IF(B18<x_H,(1+x_de)^(-B18),0) -> 0.84197317 | E18: =(L_S0!AO8-L_S1!AO8)*C18 -> -53448386 | F18: =(L_S0!AP8-L_S1!AP8)*C18 -> -7167757.4 | G18: =(L_S0!AQ8-L_S1!AQ8)*C18 -> -8117452.8 | H18: =(L_S0!AS8-L_S1!AS8)*C18 -> -1.079961e+08 | I18: =I17+E18 -> -5.5174492e+08 | J18: =J17+F18 -> -3.9247904e+08 | K18: =K17+G18 -> -4.0299893e+08 | L18: =MAX(L17,J18) -> -1.2483278e+08 | M18: =IF(AND(B18<x_H,J18<=0,L17>0),1,0) -> 0 | N18: =IF(AND(B18<x_H,I18<=0,O17>0),1,0) -> 0 | O18: =MAX(O17,I18) -> -1.3176842e+08 | P18: =(L_S0!V8-L_S1!V8)*D18 -> -1638.2247
A19: 2032 | B19: 6 | C19: =IF(B19<x_H,(1+x_dk)^(-B19),0) -> 0.7462154 | D19: =IF(B19<x_H,(1+x_de)^(-B19),0) -> 0.81350064 | E19: =(L_S0!AO9-L_S1!AO9)*C19 -> -39169913 | F19: =(L_S0!AP9-L_S1!AP9)*C19 -> 15172727 | G19: =(L_S0!AQ9-L_S1!AQ9)*C19 -> 15803208 | H19: =(L_S0!AS9-L_S1!AS9)*C19 -> -1.0285343e+08 | I19: =I18+E19 -> -5.9091483e+08 | J19: =J18+F19 -> -3.7730631e+08 | K19: =K18+G19 -> -3.8719572e+08 | L19: =MAX(L18,J19) -> -1.2483278e+08 | M19: =IF(AND(B19<x_H,J19<=0,L18>0),1,0) -> 0 | N19: =IF(AND(B19<x_H,I19<=0,O18>0),1,0) -> 0 | O19: =MAX(O18,I19) -> -1.3176842e+08 | P19: =(L_S0!V9-L_S1!V9)*D19 -> -1888.8737
A20: 2033 | B20: 7 | C20: =IF(B20<x_H,(1+x_dk)^(-B20),0) -> 0.71068133 | D20: =IF(B20<x_H,(1+x_de)^(-B20),0) -> 0.78599096 | E20: =(L_S0!AO10-L_S1!AO10)*C20 -> -25499609 | F20: =(L_S0!AP10-L_S1!AP10)*C20 -> 36992570 | G20: =(L_S0!AQ10-L_S1!AQ10)*C20 -> 39787090 | H20: =(L_S0!AS10-L_S1!AS10)*C20 -> -97955644 | I20: =I19+E20 -> -6.1641444e+08 | J20: =J19+F20 -> -3.4031374e+08 | K20: =K19+G20 -> -3.4740863e+08 | L20: =MAX(L19,J20) -> -1.2483278e+08 | M20: =IF(AND(B20<x_H,J20<=0,L19>0),1,0) -> 0 | N20: =IF(AND(B20<x_H,I20<=0,O19>0),1,0) -> 0 | O20: =MAX(O19,I20) -> -1.3176842e+08 | P20: =(L_S0!V10-L_S1!V10)*D20 -> -2139.5924
A21: 2034 | B21: 8 | C21: =IF(B21<x_H,(1+x_dk)^(-B21),0) -> 0.67683936 | D21: =IF(B21<x_H,(1+x_de)^(-B21),0) -> 0.75941156 | E21: =(L_S0!AO11-L_S1!AO11)*C21 -> -12502245 | F21: =(L_S0!AP11-L_S1!AP11)*C21 -> 58215634 | G21: =(L_S0!AQ11-L_S1!AQ11)*C21 -> 63752257 | H21: =(L_S0!AS11-L_S1!AS11)*C21 -> -93291089 | I21: =I20+E21 -> -6.2891668e+08 | J21: =J20+F21 -> -2.8209811e+08 | K21: =K20+G21 -> -2.8365638e+08 | L21: =MAX(L20,J21) -> -1.2483278e+08 | M21: =IF(AND(B21<x_H,J21<=0,L20>0),1,0) -> 0 | N21: =IF(AND(B21<x_H,I21<=0,O20>0),1,0) -> 0 | O21: =MAX(O20,I21) -> -1.3176842e+08 | P21: =(L_S0!V11-L_S1!V11)*D21 -> -2389.5044
A22: 2035 | B22: 9 | C22: =IF(B22<x_H,(1+x_dk)^(-B22),0) -> 0.64460892 | D22: =IF(B22<x_H,(1+x_de)^(-B22),0) -> 0.73373097 | E22: =(L_S0!AO12-L_S1!AO12)*C22 -> -238135.4 | F22: =(L_S0!AP12-L_S1!AP12)*C22 -> 78760338 | G22: =(L_S0!AQ12-L_S1!AQ12)*C22 -> 87597486 | H22: =(L_S0!AS12-L_S1!AS12)*C22 -> -88848656 | I22: =I21+E22 -> -6.2915482e+08 | J22: =J21+F22 -> -2.0333777e+08 | K22: =K21+G22 -> -1.9605889e+08 | L22: =MAX(L21,J22) -> -1.2483278e+08 | M22: =IF(AND(B22<x_H,J22<=0,L21>0),1,0) -> 0 | N22: =IF(AND(B22<x_H,I22<=0,O21>0),1,0) -> 0 | O22: =MAX(O21,I22) -> -1.3176842e+08 | P22: =(L_S0!V12-L_S1!V12)*D22 -> -2637.5647
A23: 2036 | B23: 10 | C23: =IF(B23<x_H,(1+x_dk)^(-B23),0) -> 0.61391325 | D23: =IF(B23<x_H,(1+x_de)^(-B23),0) -> 0.70891881 | E23: =(L_S0!AO13-L_S1!AO13)*C23 -> 11236646 | F23: =(L_S0!AP13-L_S1!AP13)*C23 -> 98540433 | G23: =(L_S0!AQ13-L_S1!AQ13)*C23 -> 1.1120438e+08 | H23: =(L_S0!AS13-L_S1!AS13)*C23 -> -84617768 | I23: =I22+E23 -> -6.1791817e+08 | J23: =J22+F23 -> -1.0479734e+08 | K23: =K22+G23 -> -84854510 | L23: =MAX(L22,J23) -> -1.0479734e+08 | M23: =IF(AND(B23<x_H,J23<=0,L22>0),1,0) -> 0 | N23: =IF(AND(B23<x_H,I23<=0,O22>0),1,0) -> 0 | O23: =MAX(O22,I23) -> -1.3176842e+08 | P23: =(L_S0!V13-L_S1!V13)*D23 -> -2882.5525
A24: 2037 | B24: 11 | C24: =IF(B24<x_H,(1+x_dk)^(-B24),0) -> 0.58467929 | D24: =IF(B24<x_H,(1+x_de)^(-B24),0) -> 0.68494571 | E24: =(L_S0!AO14-L_S1!AO14)*C24 -> 21873416 | F24: =(L_S0!AP14-L_S1!AP14)*C24 -> 1.1746882e+08 | G24: =(L_S0!AQ14-L_S1!AQ14)*C24 -> 1.3444251e+08 | H24: =(L_S0!AS14-L_S1!AS14)*C24 -> -80588350 | I24: =I23+E24 -> -5.9604476e+08 | J24: =J23+F24 -> 12671483 | K24: =K23+G24 -> 49587998 | L24: =MAX(L23,J24) -> 12671483 | M24: =IF(AND(B24<x_H,J24<=0,L23>0),1,0) -> 0 | N24: =IF(AND(B24<x_H,I24<=0,O23>0),1,0) -> 0 | O24: =MAX(O23,I24) -> -1.3176842e+08 | P24: =(L_S0!V14-L_S1!V14)*D24 -> -3123.0874
A25: 2038 | B25: 12 | C25: =IF(B25<x_H,(1+x_dk)^(-B25),0) -> 0.55683742 | D25: =IF(B25<x_H,(1+x_de)^(-B25),0) -> 0.6617833 | E25: =(L_S0!AO15-L_S1!AO15)*C25 -> 31634524 | F25: =(L_S0!AP15-L_S1!AP15)*C25 -> 1.0834264e+08 | G25: =(L_S0!AQ15-L_S1!AQ15)*C25 -> 1.1974033e+08 | H25: =(L_S0!AS15-L_S1!AS15)*C25 -> -76750810 | I25: =I24+E25 -> -5.6441023e+08 | J25: =J24+F25 -> 1.2101412e+08 | K25: =K24+G25 -> 1.6932833e+08 | L25: =MAX(L24,J25) -> 1.2101412e+08 | M25: =IF(AND(B25<x_H,J25<=0,L24>0),1,0) -> 0 | N25: =IF(AND(B25<x_H,I25<=0,O24>0),1,0) -> 0 | O25: =MAX(O24,I25) -> -1.3176842e+08 | P25: =(L_S0!V15-L_S1!V15)*D25 -> -3357.6873
... A62: 2075 | B62: 49 | C62: =IF(B62<x_H,(1+x_dk)^(-B62),0) -> 0 | D62: =IF(B62<x_H,(1+x_de)^(-B62),0) -> 0 | E62: =(L_S0!AO52-L_S1!AO52)*C62 -> 0 | F62: =(L_S0!AP52-L_S1!AP52)*C62 -> 0 | G62: =(L_S0!AQ52-L_S1!AQ52)*C62 -> 0 | H62: =(L_S0!AS52-L_S1!AS52)*C62 -> 0 | I62: =I61+E62 -> -1.4471291e+08 | J62: =J61+F62 -> 1.0355185e+09 | K62: =K61+G62 -> 1.1576372e+09 | L62: =MAX(L61,J62) -> 1.0355185e+09 | M62: =IF(AND(B62<x_H,J62<=0,L61>0),1,0) -> 0 | N62: =IF(AND(B62<x_H,I62<=0,O61>0),1,0) -> 0 | O62: =MAX(O61,I62) -> -1.3176842e+08 | P62: =(L_S0!V52-L_S1!V52)*D62 -> 0

Sheet Inw_I1
A1: I1 vs status quo (S1): Celowane testowanie w szpitalach i laboratoriach (+50 mln zł/rok) – SZACUNEK MODELU
A2: Horyzont (lata) – zmień w Ustawienia!B4 | B2: =x_H -> 20
A3: Inwestycja (sektor publiczny, zdysk., zł) | B3: =SUM(H13:H62) -> 5.7320206e+08
A4: Saldo netto sektor publiczny (zdysk., zł; <0 = oszczędność) | B4: =SUM(F13:F62) -> 4.9442199e+08
A5: Zwroty = inwestycja − saldo (zł) | B5: =B3-B4 -> 78780070
A6: ROI = (zwroty − inwestycja)/|inwestycja| | B6: =IF(B3=0,"—",(B5-B3)/ABS(B3)) -> -0.86256143
A7: Rok zwrotu – sektor publiczny | B7: =IFERROR(INDEX(A13:A62,MATCH(1,M13:M62,0)),"brak w horyzoncie") -> brak w horyzoncie
A8: Rok zwrotu – NFZ | B8: =IFERROR(INDEX(A13:A62,MATCH(1,N13:N62,0)),"brak w horyzoncie") -> brak w horyzoncie
A9: Saldo netto NFZ (zdysk., zł) | B9: =SUM(E13:E62) -> 5.2830921e+08
A10: ICER sektor publiczny (zł/QALY; <0 = dominuje) – dodatkowo | B10: =IFERROR(B4/SUM(P13:P62),"—") -> 63119.874
A11: ICER NFZ (zł/QALY) – GŁÓWNY, porównywany z progiem 244 821 zł | B11: =IFERROR(B9/SUM(P13:P62),"—") -> 67446.05
A12: rok | B12: t | C12: DF koszty | D12: DF efekty | E12: Δ NFZ | F12: Δ publiczny | G12: Δ społeczny | H12: Δ inwestycja (publ.) | I12: skum. NFZ | J12: skum. publiczny | K12: skum. społeczny | L12: maks. dotąd (publ.) | M12: zwrot? (publ.) | N12: zwrot? (NFZ) | O12: maks. dotąd (NFZ) | P12: Δ QALY
A13: 2026 | B13: 0 | C13: =IF(B13<x_H,(1+x_dk)^(-B13),0) -> 1 | D13: =IF(B13<x_H,(1+x_de)^(-B13),0) -> 1 | E13: =(L_I1!AO3-L_S1!AO3)*C13 -> 28967829 | F13: =(L_I1!AP3-L_S1!AP3)*C13 -> 30728724 | G13: =(L_I1!AQ3-L_S1!AQ3)*C13 -> 30636636 | H13: =(L_I1!AS3-L_S1!AS3)*C13 -> 28762926 | I13: =E13 -> 28967829 | J13: =F13 -> 30728724 | K13: =G13 -> 30636636 | L13: =J13 -> 30728724 | M13: 0 | N13: 0 | O13: =I13 -> 28967829 | P13: =(L_I1!V3-L_S1!V3)*D13 -> 40.546
A14: 2027 | B14: 1 | C14: =IF(B14<x_H,(1+x_dk)^(-B14),0) -> 0.95238095 | D14: =IF(B14<x_H,(1+x_de)^(-B14),0) -> 0.96618357 | E14: =(L_I1!AO4-L_S1!AO4)*C14 -> 54366779 | F14: =(L_I1!AP4-L_S1!AP4)*C14 -> 56337597 | G14: =(L_I1!AQ4-L_S1!AQ4)*C14 -> 56167591 | H14: =(L_I1!AS4-L_S1!AS4)*C14 -> 53140728 | I14: =I13+E14 -> 83334608 | J14: =J13+F14 -> 87066321 | K14: =K13+G14 -> 86804227 | L14: =MAX(L13,J14) -> 87066321 | M14: =IF(AND(B14<x_H,J14<=0,L13>0),1,0) -> 0 | N14: =IF(AND(B14<x_H,I14<=0,O13>0),1,0) -> 0 | O14: =MAX(O13,I14) -> 83334608 | P14: =(L_I1!V4-L_S1!V4)*D14 -> 88.007729
A15: 2028 | B15: 2 | C15: =IF(B15<x_H,(1+x_dk)^(-B15),0) -> 0.90702948 | D15: =IF(B15<x_H,(1+x_de)^(-B15),0) -> 0.9335107 | E15: =(L_I1!AO5-L_S1!AO5)*C15 -> 76411357 | F15: =(L_I1!AP5-L_S1!AP5)*C15 -> 78319144 | G15: =(L_I1!AQ5-L_S1!AQ5)*C15 -> 78058252 | H15: =(L_I1!AS5-L_S1!AS5)*C15 -> 74642739 | I15: =I14+E15 -> 1.5974597e+08 | J15: =J14+F15 -> 1.6538546e+08 | K15: =K14+G15 -> 1.6486248e+08 | L15: =MAX(L14,J15) -> 1.6538546e+08 | M15: =IF(AND(B15<x_H,J15<=0,L14>0),1,0) -> 0 | N15: =IF(AND(B15<x_H,I15<=0,O14>0),1,0) -> 0 | O15: =MAX(O14,I15) -> 1.5974597e+08 | P15: =(L_I1!V5-L_S1!V5)*D15 -> 142.478
A16: 2029 | B16: 3 | C16: =IF(B16<x_H,(1+x_dk)^(-B16),0) -> 0.8638376 | D16: =IF(B16<x_H,(1+x_de)^(-B16),0) -> 0.90194271 | E16: =(L_I1!AO6-L_S1!AO6)*C16 -> 72123240 | F16: =(L_I1!AP6-L_S1!AP6)*C16 -> 73698878 | G16: =(L_I1!AQ6-L_S1!AQ6)*C16 -> 73307253 | H16: =(L_I1!AS6-L_S1!AS6)*C16 -> 70374471 | I16: =I15+E16 -> 2.318692e+08 | J16: =J15+F16 -> 2.3908434e+08 | K16: =K15+G16 -> 2.3816973e+08 | L16: =MAX(L15,J16) -> 2.3908434e+08 | M16: =IF(AND(B16<x_H,J16<=0,L15>0),1,0) -> 0 | N16: =IF(AND(B16<x_H,I16<=0,O15>0),1,0) -> 0 | O16: =MAX(O15,I16) -> 2.318692e+08 | P16: =(L_I1!V6-L_S1!V6)*D16 -> 195.09382
A17: 2030 | B17: 4 | C17: =IF(B17<x_H,(1+x_dk)^(-B17),0) -> 0.82270247 | D17: =IF(B17<x_H,(1+x_de)^(-B17),0) -> 0.87144223 | E17: =(L_I1!AO7-L_S1!AO7)*C17 -> 67878478 | F17: =(L_I1!AP7-L_S1!AP7)*C17 -> 69019312 | G17: =(L_I1!AQ7-L_S1!AQ7)*C17 -> 68413470 | H17: =(L_I1!AS7-L_S1!AS7)*C17 -> 66372922 | I17: =I16+E17 -> 2.9974768e+08 | J17: =J16+F17 -> 3.0810365e+08 | K17: =K16+G17 -> 3.065832e+08 | L17: =MAX(L16,J17) -> 3.0810365e+08 | M17: =IF(AND(B17<x_H,J17<=0,L16>0),1,0) -> 0 | N17: =IF(AND(B17<x_H,I17<=0,O16>0),1,0) -> 0 | O17: =MAX(O16,I17) -> 2.9974768e+08 | P17: =(L_I1!V7-L_S1!V7)*D17 -> 246.4212
A18: 2031 | B18: 5 | C18: =IF(B18<x_H,(1+x_dk)^(-B18),0) -> 0.78352617 | D18: =IF(B18<x_H,(1+x_de)^(-B18),0) -> 0.84197317 | E18: =(L_I1!AO8-L_S1!AO8)*C18 -> 63704539 | F18: =(L_I1!AP8-L_S1!AP8)*C18 -> 64303614 | G18: =(L_I1!AQ8-L_S1!AQ8)*C18 -> 63389534 | H18: =(L_I1!AS8-L_S1!AS8)*C18 -> 62618350 | I18: =I17+E18 -> 3.6345222e+08 | J18: =J17+F18 -> 3.7240727e+08 | K18: =K17+G18 -> 3.6997274e+08 | L18: =MAX(L17,J18) -> 3.7240727e+08 | M18: =IF(AND(B18<x_H,J18<=0,L17>0),1,0) -> 0 | N18: =IF(AND(B18<x_H,I18<=0,O17>0),1,0) -> 0 | O18: =MAX(O17,I18) -> 3.6345222e+08 | P18: =(L_I1!V8-L_S1!V8)*D18 -> 296.74923
A19: 2032 | B19: 6 | C19: =IF(B19<x_H,(1+x_dk)^(-B19),0) -> 0.7462154 | D19: =IF(B19<x_H,(1+x_de)^(-B19),0) -> 0.81350064 | E19: =(L_I1!AO9-L_S1!AO9)*C19 -> 59625412 | F19: =(L_I1!AP9-L_S1!AP9)*C19 -> 59575411 | G19: =(L_I1!AQ9-L_S1!AQ9)*C19 -> 58253226 | H19: =(L_I1!AS9-L_S1!AS9)*C19 -> 59093542 | I19: =I18+E19 -> 4.2307763e+08 | J19: =J18+F19 -> 4.3198268e+08 | K19: =K18+G19 -> 4.2822596e+08 | L19: =MAX(L18,J19) -> 4.3198268e+08 | M19: =IF(AND(B19<x_H,J19<=0,L18>0),1,0) -> 0 | N19: =IF(AND(B19<x_H,I19<=0,O18>0),1,0) -> 0 | O19: =MAX(O18,I19) -> 4.2307763e+08 | P19: =(L_I1!V9-L_S1!V9)*D19 -> 346.18195
A20: 2033 | B20: 7 | C20: =IF(B20<x_H,(1+x_dk)^(-B20),0) -> 0.71068133 | D20: =IF(B20<x_H,(1+x_de)^(-B20),0) -> 0.78599096 | E20: =(L_I1!AO10-L_S1!AO10)*C20 -> 55663096 | F20: =(L_I1!AP10-L_S1!AP10)*C20 -> 54860114 | G20: =(L_I1!AQ10-L_S1!AQ10)*C20 -> 53028408 | H20: =(L_I1!AS10-L_S1!AS10)*C20 -> 55782103 | I20: =I19+E20 -> 4.7874073e+08 | J20: =J19+F20 -> 4.8684279e+08 | K20: =K19+G20 -> 4.8125437e+08 | L20: =MAX(L19,J20) -> 4.8684279e+08 | M20: =IF(AND(B20<x_H,J20<=0,L19>0),1,0) -> 0 | N20: =IF(AND(B20<x_H,I20<=0,O19>0),1,0) -> 0 | O20: =MAX(O19,I20) -> 4.7874073e+08 | P20: =(L_I1!V10-L_S1!V10)*D20 -> 394.69558
A21: 2034 | B21: 8 | C21: =IF(B21<x_H,(1+x_dk)^(-B21),0) -> 0.67683936 | D21: =IF(B21<x_H,(1+x_de)^(-B21),0) -> 0.75941156 | E21: =(L_I1!AO11-L_S1!AO11)*C21 -> 51836538 | F21: =(L_I1!AP11-L_S1!AP11)*C21 -> 50183375 | G21: =(L_I1!AQ11-L_S1!AQ11)*C21 -> 47742948 | H21: =(L_I1!AS11-L_S1!AS11)*C21 -> 52670149 | I21: =I20+E21 -> 5.3057727e+08 | J21: =J20+F21 -> 5.3702617e+08 | K21: =K20+G21 -> 5.2899732e+08 | L21: =MAX(L20,J21) -> 5.3702617e+08 | M21: =IF(AND(B21<x_H,J21<=0,L20>0),1,0) -> 0 | N21: =IF(AND(B21<x_H,I21<=0,O20>0),1,0) -> 0 | O21: =MAX(O20,I21) -> 5.3057727e+08 | P21: =(L_I1!V11-L_S1!V11)*D21 -> 442.18333
A22: 2035 | B22: 9 | C22: =IF(B22<x_H,(1+x_dk)^(-B22),0) -> 0.64460892 | D22: =IF(B22<x_H,(1+x_de)^(-B22),0) -> 0.73373097 | E22: =(L_I1!AO12-L_S1!AO12)*C22 -> 47459871 | F22: =(L_I1!AP12-L_S1!AP12)*C22 -> 44528545 | G22: =(L_I1!AQ12-L_S1!AQ12)*C22 -> 41438945 | H22: =(L_I1!AS12-L_S1!AS12)*C22 -> 49744135 | I22: =I21+E22 -> 5.7803714e+08 | J22: =J21+F22 -> 5.8155471e+08 | K22: =K21+G22 -> 5.7043626e+08 | L22: =MAX(L21,J22) -> 5.8155471e+08 | M22: =IF(AND(B22<x_H,J22<=0,L21>0),1,0) -> 0 | N22: =IF(AND(B22<x_H,I22<=0,O21>0),1,0) -> 0 | O22: =MAX(O21,I22) -> 5.7803714e+08 | P22: =(L_I1!V12-L_S1!V12)*D22 -> 471.11031
A23: 2036 | B23: 10 | C23: =IF(B23<x_H,(1+x_dk)^(-B23),0) -> 0.61391325 | D23: =IF(B23<x_H,(1+x_de)^(-B23),0) -> 0.70891881 | E23: =(L_I1!AO13-L_S1!AO13)*C23 -> -3042094.8 | F23: =(L_I1!AP13-L_S1!AP13)*C23 -> -8009894.3 | G23: =(L_I1!AQ13-L_S1!AQ13)*C23 -> -11825686 | H23: =(L_I1!AS13-L_S1!AS13)*C23 -> 0 | I23: =I22+E23 -> 5.7499504e+08 | J23: =J22+F23 -> 5.7354482e+08 | K23: =K22+G23 -> 5.5861058e+08 | L23: =MAX(L22,J23) -> 5.8155471e+08 | M23: =IF(AND(B23<x_H,J23<=0,L22>0),1,0) -> 0 | N23: =IF(AND(B23<x_H,I23<=0,O22>0),1,0) -> 0 | O23: =MAX(O22,I23) -> 5.7803714e+08 | P23: =(L_I1!V13-L_S1!V13)*D23 -> 482.63122
A24: 2037 | B24: 11 | C24: =IF(B24<x_H,(1+x_dk)^(-B24),0) -> 0.58467929 | D24: =IF(B24<x_H,(1+x_de)^(-B24),0) -> 0.68494571 | E24: =(L_I1!AO14-L_S1!AO14)*C24 -> -3871885.1 | F24: =(L_I1!AP14-L_S1!AP14)*C24 -> -9742537.8 | G24: =(L_I1!AQ14-L_S1!AQ14)*C24 -> -14376375 | H24: =(L_I1!AS14-L_S1!AS14)*C24 -> 0 | I24: =I23+E24 -> 5.7112316e+08 | J24: =J23+F24 -> 5.6380228e+08 | K24: =K23+G24 -> 5.442342e+08 | L24: =MAX(L23,J24) -> 5.8155471e+08 | M24: =IF(AND(B24<x_H,J24<=0,L23>0),1,0) -> 0 | N24: =IF(AND(B24<x_H,I24<=0,O23>0),1,0) -> 0 | O24: =MAX(O23,I24) -> 5.7803714e+08 | P24: =(L_I1!V14-L_S1!V14)*D24 -> 493.83901
A25: 2038 | B25: 12 | C25: =IF(B25<x_H,(1+x_dk)^(-B25),0) -> 0.55683742 | D25: =IF(B25<x_H,(1+x_de)^(-B25),0) -> 0.6617833 | E25: =(L_I1!AO15-L_S1!AO15)*C25 -> -4504110.2 | F25: =(L_I1!AP15-L_S1!AP15)*C25 -> -8700974.5 | G25: =(L_I1!AQ15-L_S1!AQ15)*C25 -> -12084149 | H25: =(L_I1!AS15-L_S1!AS15)*C25 -> 0 | I25: =I24+E25 -> 5.6661905e+08 | J25: =J24+F25 -> 5.5510131e+08 | K25: =K24+G25 -> 5.3215005e+08 | L25: =MAX(L24,J25) -> 5.8155471e+08 | M25: =IF(AND(B25<x_H,J25<=0,L24>0),1,0) -> 0 | N25: =IF(AND(B25<x_H,I25<=0,O24>0),1,0) -> 0 | O25: =MAX(O24,I25) -> 5.7803714e+08 | P25: =(L_I1!V15-L_S1!V15)*D25 -> 504.18027
... A62: 2075 | B62: 49 | C62: =IF(B62<x_H,(1+x_dk)^(-B62),0) -> 0 | D62: =IF(B62<x_H,(1+x_de)^(-B62),0) -> 0 | E62: =(L_I1!AO52-L_S1!AO52)*C62 -> 0 | F62: =(L_I1!AP52-L_S1!AP52)*C62 -> 0 | G62: =(L_I1!AQ52-L_S1!AQ52)*C62 -> 0 | H62: =(L_I1!AS52-L_S1!AS52)*C62 -> 0 | I62: =I61+E62 -> 5.2830921e+08 | J62: =J61+F62 -> 4.9442199e+08 | K62: =K61+G62 -> 4.5199731e+08 | L62: =MAX(L61,J62) -> 5.8155471e+08 | M62: =IF(AND(B62<x_H,J62<=0,L61>0),1,0) -> 0 | N62: =IF(AND(B62<x_H,I62<=0,O61>0),1,0) -> 0 | O62: =MAX(O61,I62) -> 5.7803714e+08 | P62: =(L_I1!V52-L_S1!V52)*D62 -> 0

Sheet Inw_I2
A1: I2 vs status quo (S1): Szerokie testowanie w POZ (+50 mln zł/rok) – SZACUNEK MODELU
A2: Horyzont (lata) – zmień w Ustawienia!B4 | B2: =x_H -> 20
A3: Inwestycja (sektor publiczny, zdysk., zł) | B3: =SUM(H13:H62) -> 4.3205939e+08
A4: Saldo netto sektor publiczny (zdysk., zł; <0 = oszczędność) | B4: =SUM(F13:F62) -> 4.0701998e+08
A5: Zwroty = inwestycja − saldo (zł) | B5: =B3-B4 -> 25039410
A6: ROI = (zwroty − inwestycja)/|inwestycja| | B6: =IF(B3=0,"—",(B5-B3)/ABS(B3)) -> -0.94204637
